[{"doc_id": "8b455ddf-c916-11e9-8670-b831b5755f6c", "person": "Yasir-Arafat", "question_class": "error", "label": "badentity"}, {"doc_id": "8b455ddf-c916-11e9-8670-b831b5755f6c", "person": "Yasir-Arafat", "question_class": "affiliation", "label": "government"}, {"doc_id": "8b455ddf-c916-11e9-8670-b831b5755f6c", "person": "Yasir-Arafat", "question_class": "gov-branch", "label": "executive"}, {"doc_id": "8b455ddf-c916-11e9-8670-b831b5755f6c", "person": "Yasir-Arafat", "question_class": "gov-person-role", "label": "spokesman"}, {"doc_id": "8b455ddf-c916-11e9-8670-b831b5755f6c", "person": "Yasir-Arafat", "question_class": "victim-person-role"}, {"doc_id": "8b455ddf-c916-11e9-8670-b831b5755f6c", "person": "Yasir-Arafat", "question_class": "academic-person-role"}, {"doc_id": "8b455ddf-c916-11e9-8670-b831b5755f6c", "person": "Yasir-Arafat", "question_class": "witness-person-role"}, {"doc_id": "8b455ddf-c916-11e9-8670-b831b5755f6c", "person": "Yasir-Arafat", "question_class": "actor-affiliation-type"}, {"doc_id": "8b455ddf-c916-11e9-8670-b831b5755f6c", "person": "Yasir-Arafat", "question_class": "actor-individual-person-role"}, {"doc_id": "8b455ddf-c916-11e9-8670-b831b5755f6c", "person": "Yasir-Arafat", "question_class": "actor-group-person-role"}, {"doc_id": "8b455ddf-c916-11e9-8670-b831b5755f6c", "person": "Yasir-Arafat", "question_class": "corporate-person-role"}, {"doc_id": "8b455ddf-c916-11e9-8670-b831b5755f6c", "person": "Yasir-Arafat", "question_class": "lawyer-role"}, {"doc_id": "8b455ddf-c916-11e9-8670-b831b5755f6c", "person": "Yasir-Arafat", "question_class": "ngo-person-role"}, {"doc_id": "8b455ddf-c916-11e9-8670-b831b5755f6c", "person": "Yasir-Arafat", "question_class": "stance", "label": "supporting"}, {"doc_id": "8b455ddf-c916-11e9-8670-b831b5755f6c", "person": "Yasir-Arafat", "question_class": "current", "label": "current"}, {"doc_id": "8b455ddf-c916-11e9-8670-b831b5755f6c", "person": "Barry-Rubin", "question_class": "error", "label": "legit"}, {"doc_id": "8b455ddf-c916-11e9-8670-b831b5755f6c", "person": "Barry-Rubin", "question_class": "affiliation", "label": "academic"}, {"doc_id": "8b455ddf-c916-11e9-8670-b831b5755f6c", "person": "Barry-Rubin", "question_class": "gov-branch"}, {"doc_id": "8b455ddf-c916-11e9-8670-b831b5755f6c", "person": "Barry-Rubin", "question_class": "gov-person-role"}, {"doc_id": "8b455ddf-c916-11e9-8670-b831b5755f6c", "person": "Barry-Rubin", "question_class": "victim-person-role"}, {"doc_id": "8b455ddf-c916-11e9-8670-b831b5755f6c", "person": "Barry-Rubin", "question_class": "academic-person-role", "label": "other"}, {"doc_id": "8b455ddf-c916-11e9-8670-b831b5755f6c", "person": "Barry-Rubin", "question_class": "witness-person-role"}, {"doc_id": "8b455ddf-c916-11e9-8670-b831b5755f6c", "person": "Barry-Rubin", "question_class": "actor-affiliation-type"}, {"doc_id": "8b455ddf-c916-11e9-8670-b831b5755f6c", "person": "Barry-Rubin", "question_class": "actor-individual-person-role"}, {"doc_id": "8b455ddf-c916-11e9-8670-b831b5755f6c", "person": "Barry-Rubin", "question_class": "actor-group-person-role"}, {"doc_id": "8b455ddf-c916-11e9-8670-b831b5755f6c", "person": "Barry-Rubin", "question_class": "corporate-person-role"}, {"doc_id": "8b455ddf-c916-11e9-8670-b831b5755f6c", "person": "Barry-Rubin", "question_class": "lawyer-role"}, {"doc_id": "8b455ddf-c916-11e9-8670-b831b5755f6c", "person": "Barry-Rubin", "question_class": "ngo-person-role"}, {"doc_id": "8b455ddf-c916-11e9-8670-b831b5755f6c", "person": "Barry-Rubin", "question_class": "stance", "label": "informational"}, {"doc_id": "8b455ddf-c916-11e9-8670-b831b5755f6c", "person": "Barry-Rubin", "question_class": "current", "label": "current"}, {"doc_id": "8b455ddf-c916-11e9-8670-b831b5755f6c", "person": "Menachem-Klein", "question_class": "error", "label": "legit"}, {"doc_id": "8b455ddf-c916-11e9-8670-b831b5755f6c", "person": "Menachem-Klein", "question_class": "affiliation", "label": "academic"}, {"doc_id": "8b455ddf-c916-11e9-8670-b831b5755f6c", "person": "Menachem-Klein", "question_class": "gov-branch"}, {"doc_id": "8b455ddf-c916-11e9-8670-b831b5755f6c", "person": "Menachem-Klein", "question_class": "gov-person-role"}, {"doc_id": "8b455ddf-c916-11e9-8670-b831b5755f6c", "person": "Menachem-Klein", "question_class": "victim-person-role"}, {"doc_id": "8b455ddf-c916-11e9-8670-b831b5755f6c", "person": "Menachem-Klein", "question_class": "academic-person-role", "label": "other"}, {"doc_id": "8b455ddf-c916-11e9-8670-b831b5755f6c", "person": "Menachem-Klein", "question_class": "witness-person-role"}, {"doc_id": "8b455ddf-c916-11e9-8670-b831b5755f6c", "person": "Menachem-Klein", "question_class": "actor-affiliation-type"}, {"doc_id": "8b455ddf-c916-11e9-8670-b831b5755f6c", "person": "Menachem-Klein", "question_class": "actor-individual-person-role"}, {"doc_id": "8b455ddf-c916-11e9-8670-b831b5755f6c", "person": "Menachem-Klein", "question_class": "actor-group-person-role"}, {"doc_id": "8b455ddf-c916-11e9-8670-b831b5755f6c", "person": "Menachem-Klein", "question_class": "corporate-person-role"}, {"doc_id": "8b455ddf-c916-11e9-8670-b831b5755f6c", "person": "Menachem-Klein", "question_class": "lawyer-role"}, {"doc_id": "8b455ddf-c916-11e9-8670-b831b5755f6c", "person": "Menachem-Klein", "question_class": "ngo-person-role"}, {"doc_id": "8b455ddf-c916-11e9-8670-b831b5755f6c", "person": "Menachem-Klein", "question_class": "stance", "label": "informational"}, {"doc_id": "8b455ddf-c916-11e9-8670-b831b5755f6c", "person": "Menachem-Klein", "question_class": "current", "label": "current"}, {"doc_id": "8b455ddf-c916-11e9-8670-b831b5755f6c", "person": "Danny-Rubinstein", "question_class": "error", "label": "legit"}, {"doc_id": "8b455ddf-c916-11e9-8670-b831b5755f6c", "person": "Danny-Rubinstein", "question_class": "affiliation", "label": "academic"}, {"doc_id": "8b455ddf-c916-11e9-8670-b831b5755f6c", "person": "Danny-Rubinstein", "question_class": "gov-branch"}, {"doc_id": "8b455ddf-c916-11e9-8670-b831b5755f6c", "person": "Danny-Rubinstein", "question_class": "gov-person-role"}, {"doc_id": "8b455ddf-c916-11e9-8670-b831b5755f6c", "person": "Danny-Rubinstein", "question_class": "victim-person-role"}, {"doc_id": "8b455ddf-c916-11e9-8670-b831b5755f6c", "person": "Danny-Rubinstein", "question_class": "academic-person-role", "label": "decision-maker"}, {"doc_id": "8b455ddf-c916-11e9-8670-b831b5755f6c", "person": "Danny-Rubinstein", "question_class": "witness-person-role"}, {"doc_id": "8b455ddf-c916-11e9-8670-b831b5755f6c", "person": "Danny-Rubinstein", "question_class": "actor-affiliation-type"}, {"doc_id": "8b455ddf-c916-11e9-8670-b831b5755f6c", "person": "Danny-Rubinstein", "question_class": "actor-individual-person-role"}, {"doc_id": "8b455ddf-c916-11e9-8670-b831b5755f6c", "person": "Danny-Rubinstein", "question_class": "actor-group-person-role"}, {"doc_id": "8b455ddf-c916-11e9-8670-b831b5755f6c", "person": "Danny-Rubinstein", "question_class": "corporate-person-role"}, {"doc_id": "8b455ddf-c916-11e9-8670-b831b5755f6c", "person": "Danny-Rubinstein", "question_class": "lawyer-role"}, {"doc_id": "8b455ddf-c916-11e9-8670-b831b5755f6c", "person": "Danny-Rubinstein", "question_class": "ngo-person-role"}, {"doc_id": "8b455ddf-c916-11e9-8670-b831b5755f6c", "person": "Danny-Rubinstein", "question_class": "stance", "label": "informational"}, {"doc_id": "8b455ddf-c916-11e9-8670-b831b5755f6c", "person": "Danny-Rubinstein", "question_class": "current", "label": "current"}, {"doc_id": "8b455ddf-c916-11e9-8670-b831b5755f6c", "person": "Ashraf-Kurdi", "question_class": "error", "label": "legit"}, {"doc_id": "8b455ddf-c916-11e9-8670-b831b5755f6c", "person": "Ashraf-Kurdi", "question_class": "affiliation", "label": "actor"}, {"doc_id": "8b455ddf-c916-11e9-8670-b831b5755f6c", "person": "Ashraf-Kurdi", "question_class": "gov-branch"}, {"doc_id": "8b455ddf-c916-11e9-8670-b831b5755f6c", "person": "Ashraf-Kurdi", "question_class": "gov-person-role"}, {"doc_id": "8b455ddf-c916-11e9-8670-b831b5755f6c", "person": "Ashraf-Kurdi", "question_class": "victim-person-role"}, {"doc_id": "8b455ddf-c916-11e9-8670-b831b5755f6c", "person": "Ashraf-Kurdi", "question_class": "academic-person-role"}, {"doc_id": "8b455ddf-c916-11e9-8670-b831b5755f6c", "person": "Ashraf-Kurdi", "question_class": "witness-person-role"}, {"doc_id": "8b455ddf-c916-11e9-8670-b831b5755f6c", "person": "Ashraf-Kurdi", "question_class": "actor-affiliation-type", "label": "individual"}, {"doc_id": "8b455ddf-c916-11e9-8670-b831b5755f6c", "person": "Ashraf-Kurdi", "question_class": "actor-individual-person-role", "label": "doctor"}, {"doc_id": "8b455ddf-c916-11e9-8670-b831b5755f6c", "person": "Ashraf-Kurdi", "question_class": "actor-group-person-role"}, {"doc_id": "8b455ddf-c916-11e9-8670-b831b5755f6c", "person": "Ashraf-Kurdi", "question_class": "corporate-person-role"}, {"doc_id": "8b455ddf-c916-11e9-8670-b831b5755f6c", "person": "Ashraf-Kurdi", "question_class": "lawyer-role"}, {"doc_id": "8b455ddf-c916-11e9-8670-b831b5755f6c", "person": "Ashraf-Kurdi", "question_class": "ngo-person-role"}, {"doc_id": "8b455ddf-c916-11e9-8670-b831b5755f6c", "person": "Ashraf-Kurdi", "question_class": "stance", "label": "informational"}, {"doc_id": "8b455ddf-c916-11e9-8670-b831b5755f6c", "person": "Ashraf-Kurdi", "question_class": "current", "label": "current"}, {"doc_id": "1dcd13ca-c916-11e9-ab94-b831b5755f6c", "person": "William-Stern", "question_class": "error", "label": "badentity"}, {"doc_id": "1dcd13ca-c916-11e9-ab94-b831b5755f6c", "person": "William-Stern", "question_class": "affiliation"}, {"doc_id": "1dcd13ca-c916-11e9-ab94-b831b5755f6c", "person": "William-Stern", "question_class": "gov-branch"}, {"doc_id": "1dcd13ca-c916-11e9-ab94-b831b5755f6c", "person": "William-Stern", "question_class": "gov-person-role"}, {"doc_id": "1dcd13ca-c916-11e9-ab94-b831b5755f6c", "person": "William-Stern", "question_class": "victim-person-role", "label": "individual"}, {"doc_id": "1dcd13ca-c916-11e9-ab94-b831b5755f6c", "person": "William-Stern", "question_class": "academic-person-role", "label": "decision-maker"}, {"doc_id": "1dcd13ca-c916-11e9-ab94-b831b5755f6c", "person": "William-Stern", "question_class": "witness-person-role", "label": "casual"}, {"doc_id": "1dcd13ca-c916-11e9-ab94-b831b5755f6c", "person": "William-Stern", "question_class": "actor-affiliation-type", "label": "individual"}, {"doc_id": "1dcd13ca-c916-11e9-ab94-b831b5755f6c", "person": "William-Stern", "question_class": "actor-individual-person-role", "label": "individual"}, {"doc_id": "1dcd13ca-c916-11e9-ab94-b831b5755f6c", "person": "William-Stern", "question_class": "actor-group-person-role", "label": "leader"}, {"doc_id": "1dcd13ca-c916-11e9-ab94-b831b5755f6c", "person": "William-Stern", "question_class": "corporate-person-role"}, {"doc_id": "1dcd13ca-c916-11e9-ab94-b831b5755f6c", "person": "William-Stern", "question_class": "lawyer-role"}, {"doc_id": "1dcd13ca-c916-11e9-ab94-b831b5755f6c", "person": "William-Stern", "question_class": "ngo-person-role"}, {"doc_id": "1dcd13ca-c916-11e9-ab94-b831b5755f6c", "person": "William-Stern", "question_class": "stance", "label": "informational"}, {"doc_id": "1dcd13ca-c916-11e9-ab94-b831b5755f6c", "person": "William-Stern", "question_class": "current", "label": "current"}, {"doc_id": "1dcd13ca-c916-11e9-ab94-b831b5755f6c", "person": "Mary-Beth-Whitehead", "question_class": "error", "label": "legit"}, {"doc_id": "1dcd13ca-c916-11e9-ab94-b831b5755f6c", "person": "Mary-Beth-Whitehead", "question_class": "affiliation", "label": "actor"}, {"doc_id": "1dcd13ca-c916-11e9-ab94-b831b5755f6c", "person": "Mary-Beth-Whitehead", "question_class": "gov-branch"}, {"doc_id": "1dcd13ca-c916-11e9-ab94-b831b5755f6c", "person": "Mary-Beth-Whitehead", "question_class": "gov-person-role"}, {"doc_id": "1dcd13ca-c916-11e9-ab94-b831b5755f6c", "person": "Mary-Beth-Whitehead", "question_class": "victim-person-role"}, {"doc_id": "1dcd13ca-c916-11e9-ab94-b831b5755f6c", "person": "Mary-Beth-Whitehead", "question_class": "academic-person-role"}, {"doc_id": "1dcd13ca-c916-11e9-ab94-b831b5755f6c", "person": "Mary-Beth-Whitehead", "question_class": "witness-person-role"}, {"doc_id": "1dcd13ca-c916-11e9-ab94-b831b5755f6c", "person": "Mary-Beth-Whitehead", "question_class": "actor-affiliation-type", "label": "individual"}, {"doc_id": "1dcd13ca-c916-11e9-ab94-b831b5755f6c", "person": "Mary-Beth-Whitehead", "question_class": "actor-individual-person-role", "label": "doctor"}, {"doc_id": "1dcd13ca-c916-11e9-ab94-b831b5755f6c", "person": "Mary-Beth-Whitehead", "question_class": "actor-group-person-role"}, {"doc_id": "1dcd13ca-c916-11e9-ab94-b831b5755f6c", "person": "Mary-Beth-Whitehead", "question_class": "corporate-person-role"}, {"doc_id": "1dcd13ca-c916-11e9-ab94-b831b5755f6c", "person": "Mary-Beth-Whitehead", "question_class": "lawyer-role"}, {"doc_id": "1dcd13ca-c916-11e9-ab94-b831b5755f6c", "person": "Mary-Beth-Whitehead", "question_class": "ngo-person-role"}, {"doc_id": "1dcd13ca-c916-11e9-ab94-b831b5755f6c", "person": "Mary-Beth-Whitehead", "question_class": "stance", "label": "cant-tell"}, {"doc_id": "1dcd13ca-c916-11e9-ab94-b831b5755f6c", "person": "Mary-Beth-Whitehead", "question_class": "current", "label": "current"}, {"doc_id": "1dcd13ca-c916-11e9-ab94-b831b5755f6c", "person": "Harvey-R.-Sorkow", "question_class": "error", "label": "badentity"}, {"doc_id": "1dcd13ca-c916-11e9-ab94-b831b5755f6c", "person": "Harvey-R.-Sorkow", "question_class": "affiliation"}, {"doc_id": "1dcd13ca-c916-11e9-ab94-b831b5755f6c", "person": "Harvey-R.-Sorkow", "question_class": "gov-branch"}, {"doc_id": "1dcd13ca-c916-11e9-ab94-b831b5755f6c", "person": "Harvey-R.-Sorkow", "question_class": "gov-person-role"}, {"doc_id": "1dcd13ca-c916-11e9-ab94-b831b5755f6c", "person": "Harvey-R.-Sorkow", "question_class": "victim-person-role", "label": "individual"}, {"doc_id": "1dcd13ca-c916-11e9-ab94-b831b5755f6c", "person": "Harvey-R.-Sorkow", "question_class": "academic-person-role", "label": "decision-maker"}, {"doc_id": "1dcd13ca-c916-11e9-ab94-b831b5755f6c", "person": "Harvey-R.-Sorkow", "question_class": "witness-person-role", "label": "casual"}, {"doc_id": "1dcd13ca-c916-11e9-ab94-b831b5755f6c", "person": "Harvey-R.-Sorkow", "question_class": "actor-affiliation-type", "label": "individual"}, {"doc_id": "1dcd13ca-c916-11e9-ab94-b831b5755f6c", "person": "Harvey-R.-Sorkow", "question_class": "actor-individual-person-role", "label": "individual"}, {"doc_id": "1dcd13ca-c916-11e9-ab94-b831b5755f6c", "person": "Harvey-R.-Sorkow", "question_class": "actor-group-person-role", "label": "leader"}, {"doc_id": "1dcd13ca-c916-11e9-ab94-b831b5755f6c", "person": "Harvey-R.-Sorkow", "question_class": "corporate-person-role"}, {"doc_id": "1dcd13ca-c916-11e9-ab94-b831b5755f6c", "person": "Harvey-R.-Sorkow", "question_class": "lawyer-role"}, {"doc_id": "1dcd13ca-c916-11e9-ab94-b831b5755f6c", "person": "Harvey-R.-Sorkow", "question_class": "ngo-person-role"}, {"doc_id": "1dcd13ca-c916-11e9-ab94-b831b5755f6c", "person": "Harvey-R.-Sorkow", "question_class": "stance", "label": "informational"}, {"doc_id": "1dcd13ca-c916-11e9-ab94-b831b5755f6c", "person": "Harvey-R.-Sorkow", "question_class": "current", "label": "current"}, {"doc_id": "1dcd13ca-c916-11e9-ab94-b831b5755f6c", "person": "Floyd-Abrams", "question_class": "error", "label": "legit"}, {"doc_id": "1dcd13ca-c916-11e9-ab94-b831b5755f6c", "person": "Floyd-Abrams", "question_class": "affiliation", "label": "academic"}, {"doc_id": "1dcd13ca-c916-11e9-ab94-b831b5755f6c", "person": "Floyd-Abrams", "question_class": "gov-branch"}, {"doc_id": "1dcd13ca-c916-11e9-ab94-b831b5755f6c", "person": "Floyd-Abrams", "question_class": "gov-person-role"}, {"doc_id": "1dcd13ca-c916-11e9-ab94-b831b5755f6c", "person": "Floyd-Abrams", "question_class": "victim-person-role"}, {"doc_id": "1dcd13ca-c916-11e9-ab94-b831b5755f6c", "person": "Floyd-Abrams", "question_class": "academic-person-role", "label": "other"}, {"doc_id": "1dcd13ca-c916-11e9-ab94-b831b5755f6c", "person": "Floyd-Abrams", "question_class": "witness-person-role"}, {"doc_id": "1dcd13ca-c916-11e9-ab94-b831b5755f6c", "person": "Floyd-Abrams", "question_class": "actor-affiliation-type"}, {"doc_id": "1dcd13ca-c916-11e9-ab94-b831b5755f6c", "person": "Floyd-Abrams", "question_class": "actor-individual-person-role"}, {"doc_id": "1dcd13ca-c916-11e9-ab94-b831b5755f6c", "person": "Floyd-Abrams", "question_class": "actor-group-person-role"}, {"doc_id": "1dcd13ca-c916-11e9-ab94-b831b5755f6c", "person": "Floyd-Abrams", "question_class": "corporate-person-role"}, {"doc_id": "1dcd13ca-c916-11e9-ab94-b831b5755f6c", "person": "Floyd-Abrams", "question_class": "lawyer-role"}, {"doc_id": "1dcd13ca-c916-11e9-ab94-b831b5755f6c", "person": "Floyd-Abrams", "question_class": "ngo-person-role"}, {"doc_id": "1dcd13ca-c916-11e9-ab94-b831b5755f6c", "person": "Floyd-Abrams", "question_class": "stance", "label": "opposing"}, {"doc_id": "1dcd13ca-c916-11e9-ab94-b831b5755f6c", "person": "Floyd-Abrams", "question_class": "current", "label": "current"}, {"doc_id": "1dcd13ca-c916-11e9-ab94-b831b5755f6c", "person": "Edward-J.-O'Donnell", "question_class": "error", "label": "badentity"}, {"doc_id": "1dcd13ca-c916-11e9-ab94-b831b5755f6c", "person": "Edward-J.-O'Donnell", "question_class": "affiliation", "label": "actor"}, {"doc_id": "1dcd13ca-c916-11e9-ab94-b831b5755f6c", "person": "Edward-J.-O'Donnell", "question_class": "gov-branch"}, {"doc_id": "1dcd13ca-c916-11e9-ab94-b831b5755f6c", "person": "Edward-J.-O'Donnell", "question_class": "gov-person-role"}, {"doc_id": "1dcd13ca-c916-11e9-ab94-b831b5755f6c", "person": "Edward-J.-O'Donnell", "question_class": "victim-person-role"}, {"doc_id": "1dcd13ca-c916-11e9-ab94-b831b5755f6c", "person": "Edward-J.-O'Donnell", "question_class": "academic-person-role"}, {"doc_id": "1dcd13ca-c916-11e9-ab94-b831b5755f6c", "person": "Edward-J.-O'Donnell", "question_class": "witness-person-role"}, {"doc_id": "1dcd13ca-c916-11e9-ab94-b831b5755f6c", "person": "Edward-J.-O'Donnell", "question_class": "actor-affiliation-type", "label": "individual"}, {"doc_id": "1dcd13ca-c916-11e9-ab94-b831b5755f6c", "person": "Edward-J.-O'Donnell", "question_class": "actor-individual-person-role", "label": "lawyer"}, {"doc_id": "1dcd13ca-c916-11e9-ab94-b831b5755f6c", "person": "Edward-J.-O'Donnell", "question_class": "actor-group-person-role"}, {"doc_id": "1dcd13ca-c916-11e9-ab94-b831b5755f6c", "person": "Edward-J.-O'Donnell", "question_class": "corporate-person-role"}, {"doc_id": "1dcd13ca-c916-11e9-ab94-b831b5755f6c", "person": "Edward-J.-O'Donnell", "question_class": "lawyer-role", "label": "prosecutor"}, {"doc_id": "1dcd13ca-c916-11e9-ab94-b831b5755f6c", "person": "Edward-J.-O'Donnell", "question_class": "ngo-person-role"}, {"doc_id": "1dcd13ca-c916-11e9-ab94-b831b5755f6c", "person": "Edward-J.-O'Donnell", "question_class": "stance"}, {"doc_id": "1dcd13ca-c916-11e9-ab94-b831b5755f6c", "person": "Edward-J.-O'Donnell", "question_class": "current", "label": "current"}, {"doc_id": "1e1a73b6-c916-11e9-bc0f-b831b5755f6c", "person": "Martin-Lovett", "question_class": "error", "label": "badentity"}, {"doc_id": "1e1a73b6-c916-11e9-bc0f-b831b5755f6c", "person": "Martin-Lovett", "question_class": "affiliation", "label": "actor"}, {"doc_id": "1e1a73b6-c916-11e9-bc0f-b831b5755f6c", "person": "Martin-Lovett", "question_class": "gov-branch"}, {"doc_id": "1e1a73b6-c916-11e9-bc0f-b831b5755f6c", "person": "Martin-Lovett", "question_class": "gov-person-role"}, {"doc_id": "1e1a73b6-c916-11e9-bc0f-b831b5755f6c", "person": "Martin-Lovett", "question_class": "victim-person-role"}, {"doc_id": "1e1a73b6-c916-11e9-bc0f-b831b5755f6c", "person": "Martin-Lovett", "question_class": "academic-person-role"}, {"doc_id": "1e1a73b6-c916-11e9-bc0f-b831b5755f6c", "person": "Martin-Lovett", "question_class": "witness-person-role"}, {"doc_id": "1e1a73b6-c916-11e9-bc0f-b831b5755f6c", "person": "Martin-Lovett", "question_class": "actor-affiliation-type", "label": "group"}, {"doc_id": "1e1a73b6-c916-11e9-bc0f-b831b5755f6c", "person": "Martin-Lovett", "question_class": "actor-individual-person-role"}, {"doc_id": "1e1a73b6-c916-11e9-bc0f-b831b5755f6c", "person": "Martin-Lovett", "question_class": "actor-group-person-role", "label": "member"}, {"doc_id": "1e1a73b6-c916-11e9-bc0f-b831b5755f6c", "person": "Martin-Lovett", "question_class": "corporate-person-role"}, {"doc_id": "1e1a73b6-c916-11e9-bc0f-b831b5755f6c", "person": "Martin-Lovett", "question_class": "lawyer-role"}, {"doc_id": "1e1a73b6-c916-11e9-bc0f-b831b5755f6c", "person": "Martin-Lovett", "question_class": "ngo-person-role"}, {"doc_id": "1e1a73b6-c916-11e9-bc0f-b831b5755f6c", "person": "Martin-Lovett", "question_class": "stance", "label": "supporting"}, {"doc_id": "1e1a73b6-c916-11e9-bc0f-b831b5755f6c", "person": "Martin-Lovett", "question_class": "current", "label": "current"}, {"doc_id": "1e1a73b6-c916-11e9-bc0f-b831b5755f6c", "person": "Peter-Schidlof", "question_class": "error", "label": "notsource"}, {"doc_id": "1e1a73b6-c916-11e9-bc0f-b831b5755f6c", "person": "Peter-Schidlof", "question_class": "affiliation"}, {"doc_id": "1e1a73b6-c916-11e9-bc0f-b831b5755f6c", "person": "Peter-Schidlof", "question_class": "gov-branch"}, {"doc_id": "1e1a73b6-c916-11e9-bc0f-b831b5755f6c", "person": "Peter-Schidlof", "question_class": "gov-person-role"}, {"doc_id": "1e1a73b6-c916-11e9-bc0f-b831b5755f6c", "person": "Peter-Schidlof", "question_class": "victim-person-role", "label": "individual"}, {"doc_id": "1e1a73b6-c916-11e9-bc0f-b831b5755f6c", "person": "Peter-Schidlof", "question_class": "academic-person-role", "label": "decision-maker"}, {"doc_id": "1e1a73b6-c916-11e9-bc0f-b831b5755f6c", "person": "Peter-Schidlof", "question_class": "witness-person-role", "label": "casual"}, {"doc_id": "1e1a73b6-c916-11e9-bc0f-b831b5755f6c", "person": "Peter-Schidlof", "question_class": "actor-affiliation-type", "label": "individual"}, {"doc_id": "1e1a73b6-c916-11e9-bc0f-b831b5755f6c", "person": "Peter-Schidlof", "question_class": "actor-individual-person-role", "label": "individual"}, {"doc_id": "1e1a73b6-c916-11e9-bc0f-b831b5755f6c", "person": "Peter-Schidlof", "question_class": "actor-group-person-role", "label": "leader"}, {"doc_id": "1e1a73b6-c916-11e9-bc0f-b831b5755f6c", "person": "Peter-Schidlof", "question_class": "corporate-person-role"}, {"doc_id": "1e1a73b6-c916-11e9-bc0f-b831b5755f6c", "person": "Peter-Schidlof", "question_class": "lawyer-role"}, {"doc_id": "1e1a73b6-c916-11e9-bc0f-b831b5755f6c", "person": "Peter-Schidlof", "question_class": "ngo-person-role"}, {"doc_id": "1e1a73b6-c916-11e9-bc0f-b831b5755f6c", "person": "Peter-Schidlof", "question_class": "stance", "label": "informational"}, {"doc_id": "1e1a73b6-c916-11e9-bc0f-b831b5755f6c", "person": "Peter-Schidlof", "question_class": "current", "label": "current"}, {"doc_id": "1e1a73b6-c916-11e9-bc0f-b831b5755f6c", "person": "Wendy-Champney", "question_class": "error", "label": "legit"}, {"doc_id": "1e1a73b6-c916-11e9-bc0f-b831b5755f6c", "person": "Wendy-Champney", "question_class": "affiliation", "label": "actor"}, {"doc_id": "1e1a73b6-c916-11e9-bc0f-b831b5755f6c", "person": "Wendy-Champney", "question_class": "gov-branch"}, {"doc_id": "1e1a73b6-c916-11e9-bc0f-b831b5755f6c", "person": "Wendy-Champney", "question_class": "gov-person-role"}, {"doc_id": "1e1a73b6-c916-11e9-bc0f-b831b5755f6c", "person": "Wendy-Champney", "question_class": "victim-person-role"}, {"doc_id": "1e1a73b6-c916-11e9-bc0f-b831b5755f6c", "person": "Wendy-Champney", "question_class": "academic-person-role"}, {"doc_id": "1e1a73b6-c916-11e9-bc0f-b831b5755f6c", "person": "Wendy-Champney", "question_class": "witness-person-role"}, {"doc_id": "1e1a73b6-c916-11e9-bc0f-b831b5755f6c", "person": "Wendy-Champney", "question_class": "actor-affiliation-type", "label": "group"}, {"doc_id": "1e1a73b6-c916-11e9-bc0f-b831b5755f6c", "person": "Wendy-Champney", "question_class": "actor-individual-person-role"}, {"doc_id": "1e1a73b6-c916-11e9-bc0f-b831b5755f6c", "person": "Wendy-Champney", "question_class": "actor-group-person-role", "label": "member"}, {"doc_id": "1e1a73b6-c916-11e9-bc0f-b831b5755f6c", "person": "Wendy-Champney", "question_class": "corporate-person-role"}, {"doc_id": "1e1a73b6-c916-11e9-bc0f-b831b5755f6c", "person": "Wendy-Champney", "question_class": "lawyer-role"}, {"doc_id": "1e1a73b6-c916-11e9-bc0f-b831b5755f6c", "person": "Wendy-Champney", "question_class": "ngo-person-role"}, {"doc_id": "1e1a73b6-c916-11e9-bc0f-b831b5755f6c", "person": "Wendy-Champney", "question_class": "stance", "label": "supporting"}, {"doc_id": "1e1a73b6-c916-11e9-bc0f-b831b5755f6c", "person": "Wendy-Champney", "question_class": "current", "label": "current"}, {"doc_id": "1e1a73b6-c916-11e9-bc0f-b831b5755f6c", "person": "Bernard-Levin", "question_class": "error", "label": "legit"}, {"doc_id": "1e1a73b6-c916-11e9-bc0f-b831b5755f6c", "person": "Bernard-Levin", "question_class": "affiliation", "label": "academic"}, {"doc_id": "1e1a73b6-c916-11e9-bc0f-b831b5755f6c", "person": "Bernard-Levin", "question_class": "gov-branch"}, {"doc_id": "1e1a73b6-c916-11e9-bc0f-b831b5755f6c", "person": "Bernard-Levin", "question_class": "gov-person-role"}, {"doc_id": "1e1a73b6-c916-11e9-bc0f-b831b5755f6c", "person": "Bernard-Levin", "question_class": "victim-person-role"}, {"doc_id": "1e1a73b6-c916-11e9-bc0f-b831b5755f6c", "person": "Bernard-Levin", "question_class": "academic-person-role", "label": "actor"}, {"doc_id": "1e1a73b6-c916-11e9-bc0f-b831b5755f6c", "person": "Bernard-Levin", "question_class": "witness-person-role"}, {"doc_id": "1e1a73b6-c916-11e9-bc0f-b831b5755f6c", "person": "Bernard-Levin", "question_class": "actor-affiliation-type"}, {"doc_id": "1e1a73b6-c916-11e9-bc0f-b831b5755f6c", "person": "Bernard-Levin", "question_class": "actor-individual-person-role"}, {"doc_id": "1e1a73b6-c916-11e9-bc0f-b831b5755f6c", "person": "Bernard-Levin", "question_class": "actor-group-person-role"}, {"doc_id": "1e1a73b6-c916-11e9-bc0f-b831b5755f6c", "person": "Bernard-Levin", "question_class": "corporate-person-role"}, {"doc_id": "1e1a73b6-c916-11e9-bc0f-b831b5755f6c", "person": "Bernard-Levin", "question_class": "lawyer-role"}, {"doc_id": "1e1a73b6-c916-11e9-bc0f-b831b5755f6c", "person": "Bernard-Levin", "question_class": "ngo-person-role"}, {"doc_id": "1e1a73b6-c916-11e9-bc0f-b831b5755f6c", "person": "Bernard-Levin", "question_class": "stance", "label": "supporting"}, {"doc_id": "1e1a73b6-c916-11e9-bc0f-b831b5755f6c", "person": "Bernard-Levin", "question_class": "current", "label": "current"}, {"doc_id": "1e1a73b6-c916-11e9-bc0f-b831b5755f6c", "person": "Enderle-Matthias", "question_class": "error", "label": "legit"}, {"doc_id": "1e1a73b6-c916-11e9-bc0f-b831b5755f6c", "person": "Enderle-Matthias", "question_class": "affiliation", "label": "actor"}, {"doc_id": "1e1a73b6-c916-11e9-bc0f-b831b5755f6c", "person": "Enderle-Matthias", "question_class": "gov-branch"}, {"doc_id": "1e1a73b6-c916-11e9-bc0f-b831b5755f6c", "person": "Enderle-Matthias", "question_class": "gov-person-role"}, {"doc_id": "1e1a73b6-c916-11e9-bc0f-b831b5755f6c", "person": "Enderle-Matthias", "question_class": "victim-person-role"}, {"doc_id": "1e1a73b6-c916-11e9-bc0f-b831b5755f6c", "person": "Enderle-Matthias", "question_class": "academic-person-role"}, {"doc_id": "1e1a73b6-c916-11e9-bc0f-b831b5755f6c", "person": "Enderle-Matthias", "question_class": "witness-person-role"}, {"doc_id": "1e1a73b6-c916-11e9-bc0f-b831b5755f6c", "person": "Enderle-Matthias", "question_class": "actor-affiliation-type", "label": "group"}, {"doc_id": "1e1a73b6-c916-11e9-bc0f-b831b5755f6c", "person": "Enderle-Matthias", "question_class": "actor-individual-person-role"}, {"doc_id": "1e1a73b6-c916-11e9-bc0f-b831b5755f6c", "person": "Enderle-Matthias", "question_class": "actor-group-person-role", "label": "member"}, {"doc_id": "1e1a73b6-c916-11e9-bc0f-b831b5755f6c", "person": "Enderle-Matthias", "question_class": "corporate-person-role"}, {"doc_id": "1e1a73b6-c916-11e9-bc0f-b831b5755f6c", "person": "Enderle-Matthias", "question_class": "lawyer-role"}, {"doc_id": "1e1a73b6-c916-11e9-bc0f-b831b5755f6c", "person": "Enderle-Matthias", "question_class": "ngo-person-role"}, {"doc_id": "1e1a73b6-c916-11e9-bc0f-b831b5755f6c", "person": "Enderle-Matthias", "question_class": "stance", "label": "supporting"}, {"doc_id": "1e1a73b6-c916-11e9-bc0f-b831b5755f6c", "person": "Enderle-Matthias", "question_class": "current", "label": "current"}, {"doc_id": "91f02c93-c916-11e9-80e4-b831b5755f6c", "person": "J.-Harvie-Wilkinson-III", "question_class": "error", "label": "legit"}, {"doc_id": "91f02c93-c916-11e9-80e4-b831b5755f6c", "person": "J.-Harvie-Wilkinson-III", "question_class": "affiliation", "label": "government"}, {"doc_id": "91f02c93-c916-11e9-80e4-b831b5755f6c", "person": "J.-Harvie-Wilkinson-III", "question_class": "gov-branch", "label": "judicial"}, {"doc_id": "91f02c93-c916-11e9-80e4-b831b5755f6c", "person": "J.-Harvie-Wilkinson-III", "question_class": "gov-person-role", "label": "decision-maker"}, {"doc_id": "91f02c93-c916-11e9-80e4-b831b5755f6c", "person": "J.-Harvie-Wilkinson-III", "question_class": "victim-person-role"}, {"doc_id": "91f02c93-c916-11e9-80e4-b831b5755f6c", "person": "J.-Harvie-Wilkinson-III", "question_class": "academic-person-role"}, {"doc_id": "91f02c93-c916-11e9-80e4-b831b5755f6c", "person": "J.-Harvie-Wilkinson-III", "question_class": "witness-person-role"}, {"doc_id": "91f02c93-c916-11e9-80e4-b831b5755f6c", "person": "J.-Harvie-Wilkinson-III", "question_class": "actor-affiliation-type"}, {"doc_id": "91f02c93-c916-11e9-80e4-b831b5755f6c", "person": "J.-Harvie-Wilkinson-III", "question_class": "actor-individual-person-role"}, {"doc_id": "91f02c93-c916-11e9-80e4-b831b5755f6c", "person": "J.-Harvie-Wilkinson-III", "question_class": "actor-group-person-role"}, {"doc_id": "91f02c93-c916-11e9-80e4-b831b5755f6c", "person": "J.-Harvie-Wilkinson-III", "question_class": "corporate-person-role"}, {"doc_id": "91f02c93-c916-11e9-80e4-b831b5755f6c", "person": "J.-Harvie-Wilkinson-III", "question_class": "lawyer-role"}, {"doc_id": "91f02c93-c916-11e9-80e4-b831b5755f6c", "person": "J.-Harvie-Wilkinson-III", "question_class": "ngo-person-role"}, {"doc_id": "91f02c93-c916-11e9-80e4-b831b5755f6c", "person": "J.-Harvie-Wilkinson-III", "question_class": "stance", "label": "supporting"}, {"doc_id": "91f02c93-c916-11e9-80e4-b831b5755f6c", "person": "J.-Harvie-Wilkinson-III", "question_class": "current", "label": "current"}, {"doc_id": "91f02c93-c916-11e9-80e4-b831b5755f6c", "person": "John-G.-Roberts", "question_class": "error", "label": "notsource"}, {"doc_id": "91f02c93-c916-11e9-80e4-b831b5755f6c", "person": "John-G.-Roberts", "question_class": "affiliation"}, {"doc_id": "91f02c93-c916-11e9-80e4-b831b5755f6c", "person": "John-G.-Roberts", "question_class": "gov-branch"}, {"doc_id": "91f02c93-c916-11e9-80e4-b831b5755f6c", "person": "John-G.-Roberts", "question_class": "gov-person-role"}, {"doc_id": "91f02c93-c916-11e9-80e4-b831b5755f6c", "person": "John-G.-Roberts", "question_class": "victim-person-role", "label": "individual"}, {"doc_id": "91f02c93-c916-11e9-80e4-b831b5755f6c", "person": "John-G.-Roberts", "question_class": "academic-person-role", "label": "decision-maker"}, {"doc_id": "91f02c93-c916-11e9-80e4-b831b5755f6c", "person": "John-G.-Roberts", "question_class": "witness-person-role", "label": "casual"}, {"doc_id": "91f02c93-c916-11e9-80e4-b831b5755f6c", "person": "John-G.-Roberts", "question_class": "actor-affiliation-type", "label": "individual"}, {"doc_id": "91f02c93-c916-11e9-80e4-b831b5755f6c", "person": "John-G.-Roberts", "question_class": "actor-individual-person-role", "label": "individual"}, {"doc_id": "91f02c93-c916-11e9-80e4-b831b5755f6c", "person": "John-G.-Roberts", "question_class": "actor-group-person-role", "label": "leader"}, {"doc_id": "91f02c93-c916-11e9-80e4-b831b5755f6c", "person": "John-G.-Roberts", "question_class": "corporate-person-role"}, {"doc_id": "91f02c93-c916-11e9-80e4-b831b5755f6c", "person": "John-G.-Roberts", "question_class": "lawyer-role"}, {"doc_id": "91f02c93-c916-11e9-80e4-b831b5755f6c", "person": "John-G.-Roberts", "question_class": "ngo-person-role"}, {"doc_id": "91f02c93-c916-11e9-80e4-b831b5755f6c", "person": "John-G.-Roberts", "question_class": "stance", "label": "informational"}, {"doc_id": "91f02c93-c916-11e9-80e4-b831b5755f6c", "person": "John-G.-Roberts", "question_class": "current", "label": "current"}, {"doc_id": "91f02c93-c916-11e9-80e4-b831b5755f6c", "person": "Dan-Bartlett", "question_class": "error", "label": "legit"}, {"doc_id": "91f02c93-c916-11e9-80e4-b831b5755f6c", "person": "Dan-Bartlett", "question_class": "affiliation", "label": "government"}, {"doc_id": "91f02c93-c916-11e9-80e4-b831b5755f6c", "person": "Dan-Bartlett", "question_class": "gov-branch", "label": "executive"}, {"doc_id": "91f02c93-c916-11e9-80e4-b831b5755f6c", "person": "Dan-Bartlett", "question_class": "gov-person-role", "label": "advisor"}, {"doc_id": "91f02c93-c916-11e9-80e4-b831b5755f6c", "person": "Dan-Bartlett", "question_class": "victim-person-role"}, {"doc_id": "91f02c93-c916-11e9-80e4-b831b5755f6c", "person": "Dan-Bartlett", "question_class": "academic-person-role"}, {"doc_id": "91f02c93-c916-11e9-80e4-b831b5755f6c", "person": "Dan-Bartlett", "question_class": "witness-person-role"}, {"doc_id": "91f02c93-c916-11e9-80e4-b831b5755f6c", "person": "Dan-Bartlett", "question_class": "actor-affiliation-type"}, {"doc_id": "91f02c93-c916-11e9-80e4-b831b5755f6c", "person": "Dan-Bartlett", "question_class": "actor-individual-person-role"}, {"doc_id": "91f02c93-c916-11e9-80e4-b831b5755f6c", "person": "Dan-Bartlett", "question_class": "actor-group-person-role"}, {"doc_id": "91f02c93-c916-11e9-80e4-b831b5755f6c", "person": "Dan-Bartlett", "question_class": "corporate-person-role"}, {"doc_id": "91f02c93-c916-11e9-80e4-b831b5755f6c", "person": "Dan-Bartlett", "question_class": "lawyer-role"}, {"doc_id": "91f02c93-c916-11e9-80e4-b831b5755f6c", "person": "Dan-Bartlett", "question_class": "ngo-person-role"}, {"doc_id": "91f02c93-c916-11e9-80e4-b831b5755f6c", "person": "Dan-Bartlett", "question_class": "stance", "label": "informational"}, {"doc_id": "91f02c93-c916-11e9-80e4-b831b5755f6c", "person": "Dan-Bartlett", "question_class": "current", "label": "current"}, {"doc_id": "91f02c93-c916-11e9-80e4-b831b5755f6c", "person": "C.-Boyden-Gray", "question_class": "error", "label": "legit"}, {"doc_id": "91f02c93-c916-11e9-80e4-b831b5755f6c", "person": "C.-Boyden-Gray", "question_class": "affiliation", "label": "government"}, {"doc_id": "91f02c93-c916-11e9-80e4-b831b5755f6c", "person": "C.-Boyden-Gray", "question_class": "gov-branch", "label": "executive"}, {"doc_id": "91f02c93-c916-11e9-80e4-b831b5755f6c", "person": "C.-Boyden-Gray", "question_class": "gov-person-role", "label": "advisor"}, {"doc_id": "91f02c93-c916-11e9-80e4-b831b5755f6c", "person": "C.-Boyden-Gray", "question_class": "victim-person-role"}, {"doc_id": "91f02c93-c916-11e9-80e4-b831b5755f6c", "person": "C.-Boyden-Gray", "question_class": "academic-person-role"}, {"doc_id": "91f02c93-c916-11e9-80e4-b831b5755f6c", "person": "C.-Boyden-Gray", "question_class": "witness-person-role"}, {"doc_id": "91f02c93-c916-11e9-80e4-b831b5755f6c", "person": "C.-Boyden-Gray", "question_class": "actor-affiliation-type"}, {"doc_id": "91f02c93-c916-11e9-80e4-b831b5755f6c", "person": "C.-Boyden-Gray", "question_class": "actor-individual-person-role"}, {"doc_id": "91f02c93-c916-11e9-80e4-b831b5755f6c", "person": "C.-Boyden-Gray", "question_class": "actor-group-person-role"}, {"doc_id": "91f02c93-c916-11e9-80e4-b831b5755f6c", "person": "C.-Boyden-Gray", "question_class": "corporate-person-role"}, {"doc_id": "91f02c93-c916-11e9-80e4-b831b5755f6c", "person": "C.-Boyden-Gray", "question_class": "lawyer-role"}, {"doc_id": "91f02c93-c916-11e9-80e4-b831b5755f6c", "person": "C.-Boyden-Gray", "question_class": "ngo-person-role"}, {"doc_id": "91f02c93-c916-11e9-80e4-b831b5755f6c", "person": "C.-Boyden-Gray", "question_class": "stance", "label": "informational"}, {"doc_id": "91f02c93-c916-11e9-80e4-b831b5755f6c", "person": "C.-Boyden-Gray", "question_class": "current", "label": "former"}, {"doc_id": "91f02c93-c916-11e9-80e4-b831b5755f6c", "person": "Scott-McClellan", "question_class": "error", "label": "legit"}, {"doc_id": "91f02c93-c916-11e9-80e4-b831b5755f6c", "person": "Scott-McClellan", "question_class": "affiliation", "label": "government"}, {"doc_id": "91f02c93-c916-11e9-80e4-b831b5755f6c", "person": "Scott-McClellan", "question_class": "gov-branch", "label": "executive"}, {"doc_id": "91f02c93-c916-11e9-80e4-b831b5755f6c", "person": "Scott-McClellan", "question_class": "gov-person-role", "label": "spokesman"}, {"doc_id": "91f02c93-c916-11e9-80e4-b831b5755f6c", "person": "Scott-McClellan", "question_class": "victim-person-role"}, {"doc_id": "91f02c93-c916-11e9-80e4-b831b5755f6c", "person": "Scott-McClellan", "question_class": "academic-person-role"}, {"doc_id": "91f02c93-c916-11e9-80e4-b831b5755f6c", "person": "Scott-McClellan", "question_class": "witness-person-role"}, {"doc_id": "91f02c93-c916-11e9-80e4-b831b5755f6c", "person": "Scott-McClellan", "question_class": "actor-affiliation-type"}, {"doc_id": "91f02c93-c916-11e9-80e4-b831b5755f6c", "person": "Scott-McClellan", "question_class": "actor-individual-person-role"}, {"doc_id": "91f02c93-c916-11e9-80e4-b831b5755f6c", "person": "Scott-McClellan", "question_class": "actor-group-person-role"}, {"doc_id": "91f02c93-c916-11e9-80e4-b831b5755f6c", "person": "Scott-McClellan", "question_class": "corporate-person-role"}, {"doc_id": "91f02c93-c916-11e9-80e4-b831b5755f6c", "person": "Scott-McClellan", "question_class": "lawyer-role"}, {"doc_id": "91f02c93-c916-11e9-80e4-b831b5755f6c", "person": "Scott-McClellan", "question_class": "ngo-person-role"}, {"doc_id": "91f02c93-c916-11e9-80e4-b831b5755f6c", "person": "Scott-McClellan", "question_class": "stance", "label": "informational"}, {"doc_id": "91f02c93-c916-11e9-80e4-b831b5755f6c", "person": "Scott-McClellan", "question_class": "current", "label": "current"}, {"doc_id": "91f02c93-c916-11e9-80e4-b831b5755f6c", "person": "Sandra-Day-O'Connor", "question_class": "error", "label": "legit"}, {"doc_id": "91f02c93-c916-11e9-80e4-b831b5755f6c", "person": "Sandra-Day-O'Connor", "question_class": "affiliation", "label": "government"}, {"doc_id": "91f02c93-c916-11e9-80e4-b831b5755f6c", "person": "Sandra-Day-O'Connor", "question_class": "gov-branch", "label": "judicial"}, {"doc_id": "91f02c93-c916-11e9-80e4-b831b5755f6c", "person": "Sandra-Day-O'Connor", "question_class": "gov-person-role", "label": "decision-maker"}, {"doc_id": "91f02c93-c916-11e9-80e4-b831b5755f6c", "person": "Sandra-Day-O'Connor", "question_class": "victim-person-role"}, {"doc_id": "91f02c93-c916-11e9-80e4-b831b5755f6c", "person": "Sandra-Day-O'Connor", "question_class": "academic-person-role"}, {"doc_id": "91f02c93-c916-11e9-80e4-b831b5755f6c", "person": "Sandra-Day-O'Connor", "question_class": "witness-person-role"}, {"doc_id": "91f02c93-c916-11e9-80e4-b831b5755f6c", "person": "Sandra-Day-O'Connor", "question_class": "actor-affiliation-type"}, {"doc_id": "91f02c93-c916-11e9-80e4-b831b5755f6c", "person": "Sandra-Day-O'Connor", "question_class": "actor-individual-person-role"}, {"doc_id": "91f02c93-c916-11e9-80e4-b831b5755f6c", "person": "Sandra-Day-O'Connor", "question_class": "actor-group-person-role"}, {"doc_id": "91f02c93-c916-11e9-80e4-b831b5755f6c", "person": "Sandra-Day-O'Connor", "question_class": "corporate-person-role"}, {"doc_id": "91f02c93-c916-11e9-80e4-b831b5755f6c", "person": "Sandra-Day-O'Connor", "question_class": "lawyer-role"}, {"doc_id": "91f02c93-c916-11e9-80e4-b831b5755f6c", "person": "Sandra-Day-O'Connor", "question_class": "ngo-person-role"}, {"doc_id": "91f02c93-c916-11e9-80e4-b831b5755f6c", "person": "Sandra-Day-O'Connor", "question_class": "stance", "label": "opposing"}, {"doc_id": "91f02c93-c916-11e9-80e4-b831b5755f6c", "person": "Sandra-Day-O'Connor", "question_class": "current", "label": "former"}, {"doc_id": "91f02c93-c916-11e9-80e4-b831b5755f6c", "person": "Breaux", "question_class": "error", "label": "legit"}, {"doc_id": "91f02c93-c916-11e9-80e4-b831b5755f6c", "person": "Breaux", "question_class": "affiliation", "label": "academic"}, {"doc_id": "91f02c93-c916-11e9-80e4-b831b5755f6c", "person": "Breaux", "question_class": "gov-branch"}, {"doc_id": "91f02c93-c916-11e9-80e4-b831b5755f6c", "person": "Breaux", "question_class": "gov-person-role"}, {"doc_id": "91f02c93-c916-11e9-80e4-b831b5755f6c", "person": "Breaux", "question_class": "victim-person-role"}, {"doc_id": "91f02c93-c916-11e9-80e4-b831b5755f6c", "person": "Breaux", "question_class": "academic-person-role", "label": "other"}, {"doc_id": "91f02c93-c916-11e9-80e4-b831b5755f6c", "person": "Breaux", "question_class": "witness-person-role"}, {"doc_id": "91f02c93-c916-11e9-80e4-b831b5755f6c", "person": "Breaux", "question_class": "actor-affiliation-type"}, {"doc_id": "91f02c93-c916-11e9-80e4-b831b5755f6c", "person": "Breaux", "question_class": "actor-individual-person-role"}, {"doc_id": "91f02c93-c916-11e9-80e4-b831b5755f6c", "person": "Breaux", "question_class": "actor-group-person-role"}, {"doc_id": "91f02c93-c916-11e9-80e4-b831b5755f6c", "person": "Breaux", "question_class": "corporate-person-role"}, {"doc_id": "91f02c93-c916-11e9-80e4-b831b5755f6c", "person": "Breaux", "question_class": "lawyer-role"}, {"doc_id": "91f02c93-c916-11e9-80e4-b831b5755f6c", "person": "Breaux", "question_class": "ngo-person-role"}, {"doc_id": "91f02c93-c916-11e9-80e4-b831b5755f6c", "person": "Breaux", "question_class": "stance", "label": "informational"}, {"doc_id": "91f02c93-c916-11e9-80e4-b831b5755f6c", "person": "Breaux", "question_class": "current", "label": "current"}, {"doc_id": "91f02c93-c916-11e9-80e4-b831b5755f6c", "person": "Jay-Sekulow", "question_class": "error", "label": "legit"}, {"doc_id": "91f02c93-c916-11e9-80e4-b831b5755f6c", "person": "Jay-Sekulow", "question_class": "affiliation", "label": "ngo"}, {"doc_id": "91f02c93-c916-11e9-80e4-b831b5755f6c", "person": "Jay-Sekulow", "question_class": "gov-branch"}, {"doc_id": "91f02c93-c916-11e9-80e4-b831b5755f6c", "person": "Jay-Sekulow", "question_class": "gov-person-role"}, {"doc_id": "91f02c93-c916-11e9-80e4-b831b5755f6c", "person": "Jay-Sekulow", "question_class": "victim-person-role"}, {"doc_id": "91f02c93-c916-11e9-80e4-b831b5755f6c", "person": "Jay-Sekulow", "question_class": "academic-person-role"}, {"doc_id": "91f02c93-c916-11e9-80e4-b831b5755f6c", "person": "Jay-Sekulow", "question_class": "witness-person-role"}, {"doc_id": "91f02c93-c916-11e9-80e4-b831b5755f6c", "person": "Jay-Sekulow", "question_class": "actor-affiliation-type"}, {"doc_id": "91f02c93-c916-11e9-80e4-b831b5755f6c", "person": "Jay-Sekulow", "question_class": "actor-individual-person-role"}, {"doc_id": "91f02c93-c916-11e9-80e4-b831b5755f6c", "person": "Jay-Sekulow", "question_class": "actor-group-person-role"}, {"doc_id": "91f02c93-c916-11e9-80e4-b831b5755f6c", "person": "Jay-Sekulow", "question_class": "corporate-person-role"}, {"doc_id": "91f02c93-c916-11e9-80e4-b831b5755f6c", "person": "Jay-Sekulow", "question_class": "lawyer-role"}, {"doc_id": "91f02c93-c916-11e9-80e4-b831b5755f6c", "person": "Jay-Sekulow", "question_class": "ngo-person-role", "label": "actor"}, {"doc_id": "91f02c93-c916-11e9-80e4-b831b5755f6c", "person": "Jay-Sekulow", "question_class": "stance", "label": "supporting"}, {"doc_id": "91f02c93-c916-11e9-80e4-b831b5755f6c", "person": "Jay-Sekulow", "question_class": "current", "label": "current"}, {"doc_id": "7e4c0b06-c916-11e9-ac35-b831b5755f6c", "person": "Colin-L.-Powell", "question_class": "error", "label": "legit"}, {"doc_id": "7e4c0b06-c916-11e9-ac35-b831b5755f6c", "person": "Colin-L.-Powell", "question_class": "affiliation", "label": "government"}, {"doc_id": "7e4c0b06-c916-11e9-ac35-b831b5755f6c", "person": "Colin-L.-Powell", "question_class": "gov-branch", "label": "executive"}, {"doc_id": "7e4c0b06-c916-11e9-ac35-b831b5755f6c", "person": "Colin-L.-Powell", "question_class": "gov-person-role", "label": "decision-maker"}, {"doc_id": "7e4c0b06-c916-11e9-ac35-b831b5755f6c", "person": "Colin-L.-Powell", "question_class": "victim-person-role"}, {"doc_id": "7e4c0b06-c916-11e9-ac35-b831b5755f6c", "person": "Colin-L.-Powell", "question_class": "academic-person-role"}, {"doc_id": "7e4c0b06-c916-11e9-ac35-b831b5755f6c", "person": "Colin-L.-Powell", "question_class": "witness-person-role"}, {"doc_id": "7e4c0b06-c916-11e9-ac35-b831b5755f6c", "person": "Colin-L.-Powell", "question_class": "actor-affiliation-type"}, {"doc_id": "7e4c0b06-c916-11e9-ac35-b831b5755f6c", "person": "Colin-L.-Powell", "question_class": "actor-individual-person-role"}, {"doc_id": "7e4c0b06-c916-11e9-ac35-b831b5755f6c", "person": "Colin-L.-Powell", "question_class": "actor-group-person-role"}, {"doc_id": "7e4c0b06-c916-11e9-ac35-b831b5755f6c", "person": "Colin-L.-Powell", "question_class": "corporate-person-role"}, {"doc_id": "7e4c0b06-c916-11e9-ac35-b831b5755f6c", "person": "Colin-L.-Powell", "question_class": "lawyer-role"}, {"doc_id": "7e4c0b06-c916-11e9-ac35-b831b5755f6c", "person": "Colin-L.-Powell", "question_class": "ngo-person-role"}, {"doc_id": "7e4c0b06-c916-11e9-ac35-b831b5755f6c", "person": "Colin-L.-Powell", "question_class": "stance", "label": "informational"}, {"doc_id": "7e4c0b06-c916-11e9-ac35-b831b5755f6c", "person": "Colin-L.-Powell", "question_class": "current", "label": "current"}, {"doc_id": "7e4c0b06-c916-11e9-ac35-b831b5755f6c", "person": "Shibley-Telhami", "question_class": "error", "label": "legit"}, {"doc_id": "7e4c0b06-c916-11e9-ac35-b831b5755f6c", "person": "Shibley-Telhami", "question_class": "affiliation", "label": "academic"}, {"doc_id": "7e4c0b06-c916-11e9-ac35-b831b5755f6c", "person": "Shibley-Telhami", "question_class": "gov-branch"}, {"doc_id": "7e4c0b06-c916-11e9-ac35-b831b5755f6c", "person": "Shibley-Telhami", "question_class": "gov-person-role"}, {"doc_id": "7e4c0b06-c916-11e9-ac35-b831b5755f6c", "person": "Shibley-Telhami", "question_class": "victim-person-role"}, {"doc_id": "7e4c0b06-c916-11e9-ac35-b831b5755f6c", "person": "Shibley-Telhami", "question_class": "academic-person-role", "label": "other"}, {"doc_id": "7e4c0b06-c916-11e9-ac35-b831b5755f6c", "person": "Shibley-Telhami", "question_class": "witness-person-role"}, {"doc_id": "7e4c0b06-c916-11e9-ac35-b831b5755f6c", "person": "Shibley-Telhami", "question_class": "actor-affiliation-type"}, {"doc_id": "7e4c0b06-c916-11e9-ac35-b831b5755f6c", "person": "Shibley-Telhami", "question_class": "actor-individual-person-role"}, {"doc_id": "7e4c0b06-c916-11e9-ac35-b831b5755f6c", "person": "Shibley-Telhami", "question_class": "actor-group-person-role"}, {"doc_id": "7e4c0b06-c916-11e9-ac35-b831b5755f6c", "person": "Shibley-Telhami", "question_class": "corporate-person-role"}, {"doc_id": "7e4c0b06-c916-11e9-ac35-b831b5755f6c", "person": "Shibley-Telhami", "question_class": "lawyer-role"}, {"doc_id": "7e4c0b06-c916-11e9-ac35-b831b5755f6c", "person": "Shibley-Telhami", "question_class": "ngo-person-role"}, {"doc_id": "7e4c0b06-c916-11e9-ac35-b831b5755f6c", "person": "Shibley-Telhami", "question_class": "stance", "label": "informational"}, {"doc_id": "7e4c0b06-c916-11e9-ac35-b831b5755f6c", "person": "Shibley-Telhami", "question_class": "current", "label": "current"}, {"doc_id": "31934637-c916-11e9-96ed-b831b5755f6c", "person": "Mikhail-S.-Gorbachev", "question_class": "error", "label": "badentity"}, {"doc_id": "31934637-c916-11e9-96ed-b831b5755f6c", "person": "Mikhail-S.-Gorbachev", "question_class": "affiliation", "label": "government"}, {"doc_id": "31934637-c916-11e9-96ed-b831b5755f6c", "person": "Mikhail-S.-Gorbachev", "question_class": "gov-branch", "label": "executive"}, {"doc_id": "31934637-c916-11e9-96ed-b831b5755f6c", "person": "Mikhail-S.-Gorbachev", "question_class": "gov-person-role", "label": "decision-maker"}, {"doc_id": "31934637-c916-11e9-96ed-b831b5755f6c", "person": "Mikhail-S.-Gorbachev", "question_class": "victim-person-role"}, {"doc_id": "31934637-c916-11e9-96ed-b831b5755f6c", "person": "Mikhail-S.-Gorbachev", "question_class": "academic-person-role"}, {"doc_id": "31934637-c916-11e9-96ed-b831b5755f6c", "person": "Mikhail-S.-Gorbachev", "question_class": "witness-person-role"}, {"doc_id": "31934637-c916-11e9-96ed-b831b5755f6c", "person": "Mikhail-S.-Gorbachev", "question_class": "actor-affiliation-type"}, {"doc_id": "31934637-c916-11e9-96ed-b831b5755f6c", "person": "Mikhail-S.-Gorbachev", "question_class": "actor-individual-person-role"}, {"doc_id": "31934637-c916-11e9-96ed-b831b5755f6c", "person": "Mikhail-S.-Gorbachev", "question_class": "actor-group-person-role"}, {"doc_id": "31934637-c916-11e9-96ed-b831b5755f6c", "person": "Mikhail-S.-Gorbachev", "question_class": "corporate-person-role"}, {"doc_id": "31934637-c916-11e9-96ed-b831b5755f6c", "person": "Mikhail-S.-Gorbachev", "question_class": "lawyer-role"}, {"doc_id": "31934637-c916-11e9-96ed-b831b5755f6c", "person": "Mikhail-S.-Gorbachev", "question_class": "ngo-person-role"}, {"doc_id": "31934637-c916-11e9-96ed-b831b5755f6c", "person": "Mikhail-S.-Gorbachev", "question_class": "stance", "label": "informational"}, {"doc_id": "31934637-c916-11e9-96ed-b831b5755f6c", "person": "Mikhail-S.-Gorbachev", "question_class": "current", "label": "current"}, {"doc_id": "31934637-c916-11e9-96ed-b831b5755f6c", "person": "Nick-Hayes", "question_class": "error", "label": "legit"}, {"doc_id": "31934637-c916-11e9-96ed-b831b5755f6c", "person": "Nick-Hayes", "question_class": "affiliation", "label": "academic"}, {"doc_id": "31934637-c916-11e9-96ed-b831b5755f6c", "person": "Nick-Hayes", "question_class": "gov-branch"}, {"doc_id": "31934637-c916-11e9-96ed-b831b5755f6c", "person": "Nick-Hayes", "question_class": "gov-person-role"}, {"doc_id": "31934637-c916-11e9-96ed-b831b5755f6c", "person": "Nick-Hayes", "question_class": "victim-person-role"}, {"doc_id": "31934637-c916-11e9-96ed-b831b5755f6c", "person": "Nick-Hayes", "question_class": "academic-person-role", "label": "other"}, {"doc_id": "31934637-c916-11e9-96ed-b831b5755f6c", "person": "Nick-Hayes", "question_class": "witness-person-role"}, {"doc_id": "31934637-c916-11e9-96ed-b831b5755f6c", "person": "Nick-Hayes", "question_class": "actor-affiliation-type"}, {"doc_id": "31934637-c916-11e9-96ed-b831b5755f6c", "person": "Nick-Hayes", "question_class": "actor-individual-person-role"}, {"doc_id": "31934637-c916-11e9-96ed-b831b5755f6c", "person": "Nick-Hayes", "question_class": "actor-group-person-role"}, {"doc_id": "31934637-c916-11e9-96ed-b831b5755f6c", "person": "Nick-Hayes", "question_class": "corporate-person-role"}, {"doc_id": "31934637-c916-11e9-96ed-b831b5755f6c", "person": "Nick-Hayes", "question_class": "lawyer-role"}, {"doc_id": "31934637-c916-11e9-96ed-b831b5755f6c", "person": "Nick-Hayes", "question_class": "ngo-person-role"}, {"doc_id": "31934637-c916-11e9-96ed-b831b5755f6c", "person": "Nick-Hayes", "question_class": "stance", "label": "informational"}, {"doc_id": "31934637-c916-11e9-96ed-b831b5755f6c", "person": "Nick-Hayes", "question_class": "current", "label": "current"}, {"doc_id": "31934637-c916-11e9-96ed-b831b5755f6c", "person": "Carey-Kilbo", "question_class": "error", "label": "legit"}, {"doc_id": "31934637-c916-11e9-96ed-b831b5755f6c", "person": "Carey-Kilbo", "question_class": "affiliation", "label": "witness"}, {"doc_id": "31934637-c916-11e9-96ed-b831b5755f6c", "person": "Carey-Kilbo", "question_class": "gov-branch"}, {"doc_id": "31934637-c916-11e9-96ed-b831b5755f6c", "person": "Carey-Kilbo", "question_class": "gov-person-role"}, {"doc_id": "31934637-c916-11e9-96ed-b831b5755f6c", "person": "Carey-Kilbo", "question_class": "victim-person-role"}, {"doc_id": "31934637-c916-11e9-96ed-b831b5755f6c", "person": "Carey-Kilbo", "question_class": "academic-person-role"}, {"doc_id": "31934637-c916-11e9-96ed-b831b5755f6c", "person": "Carey-Kilbo", "question_class": "witness-person-role", "label": "casual"}, {"doc_id": "31934637-c916-11e9-96ed-b831b5755f6c", "person": "Carey-Kilbo", "question_class": "actor-affiliation-type"}, {"doc_id": "31934637-c916-11e9-96ed-b831b5755f6c", "person": "Carey-Kilbo", "question_class": "actor-individual-person-role"}, {"doc_id": "31934637-c916-11e9-96ed-b831b5755f6c", "person": "Carey-Kilbo", "question_class": "actor-group-person-role"}, {"doc_id": "31934637-c916-11e9-96ed-b831b5755f6c", "person": "Carey-Kilbo", "question_class": "corporate-person-role"}, {"doc_id": "31934637-c916-11e9-96ed-b831b5755f6c", "person": "Carey-Kilbo", "question_class": "lawyer-role"}, {"doc_id": "31934637-c916-11e9-96ed-b831b5755f6c", "person": "Carey-Kilbo", "question_class": "ngo-person-role"}, {"doc_id": "31934637-c916-11e9-96ed-b831b5755f6c", "person": "Carey-Kilbo", "question_class": "stance", "label": "informational"}, {"doc_id": "31934637-c916-11e9-96ed-b831b5755f6c", "person": "Carey-Kilbo", "question_class": "current", "label": "current"}, {"doc_id": "31934637-c916-11e9-96ed-b831b5755f6c", "person": "Bush", "question_class": "error", "label": "legit"}, {"doc_id": "31934637-c916-11e9-96ed-b831b5755f6c", "person": "Bush", "question_class": "affiliation", "label": "government"}, {"doc_id": "31934637-c916-11e9-96ed-b831b5755f6c", "person": "Bush", "question_class": "gov-branch", "label": "executive"}, {"doc_id": "31934637-c916-11e9-96ed-b831b5755f6c", "person": "Bush", "question_class": "gov-person-role", "label": "decision-maker"}, {"doc_id": "31934637-c916-11e9-96ed-b831b5755f6c", "person": "Bush", "question_class": "victim-person-role"}, {"doc_id": "31934637-c916-11e9-96ed-b831b5755f6c", "person": "Bush", "question_class": "academic-person-role"}, {"doc_id": "31934637-c916-11e9-96ed-b831b5755f6c", "person": "Bush", "question_class": "witness-person-role"}, {"doc_id": "31934637-c916-11e9-96ed-b831b5755f6c", "person": "Bush", "question_class": "actor-affiliation-type"}, {"doc_id": "31934637-c916-11e9-96ed-b831b5755f6c", "person": "Bush", "question_class": "actor-individual-person-role"}, {"doc_id": "31934637-c916-11e9-96ed-b831b5755f6c", "person": "Bush", "question_class": "actor-group-person-role"}, {"doc_id": "31934637-c916-11e9-96ed-b831b5755f6c", "person": "Bush", "question_class": "corporate-person-role"}, {"doc_id": "31934637-c916-11e9-96ed-b831b5755f6c", "person": "Bush", "question_class": "lawyer-role"}, {"doc_id": "31934637-c916-11e9-96ed-b831b5755f6c", "person": "Bush", "question_class": "ngo-person-role"}, {"doc_id": "31934637-c916-11e9-96ed-b831b5755f6c", "person": "Bush", "question_class": "stance", "label": "supporting"}, {"doc_id": "31934637-c916-11e9-96ed-b831b5755f6c", "person": "Bush", "question_class": "current", "label": "current"}, {"doc_id": "31934637-c916-11e9-96ed-b831b5755f6c", "person": "Nikita-Khrushchev", "question_class": "error", "label": "notsource"}, {"doc_id": "31934637-c916-11e9-96ed-b831b5755f6c", "person": "Nikita-Khrushchev", "question_class": "affiliation", "label": "government"}, {"doc_id": "31934637-c916-11e9-96ed-b831b5755f6c", "person": "Nikita-Khrushchev", "question_class": "gov-branch", "label": "executive"}, {"doc_id": "31934637-c916-11e9-96ed-b831b5755f6c", "person": "Nikita-Khrushchev", "question_class": "gov-person-role", "label": "decision-maker"}, {"doc_id": "31934637-c916-11e9-96ed-b831b5755f6c", "person": "Nikita-Khrushchev", "question_class": "victim-person-role"}, {"doc_id": "31934637-c916-11e9-96ed-b831b5755f6c", "person": "Nikita-Khrushchev", "question_class": "academic-person-role"}, {"doc_id": "31934637-c916-11e9-96ed-b831b5755f6c", "person": "Nikita-Khrushchev", "question_class": "witness-person-role"}, {"doc_id": "31934637-c916-11e9-96ed-b831b5755f6c", "person": "Nikita-Khrushchev", "question_class": "actor-affiliation-type"}, {"doc_id": "31934637-c916-11e9-96ed-b831b5755f6c", "person": "Nikita-Khrushchev", "question_class": "actor-individual-person-role"}, {"doc_id": "31934637-c916-11e9-96ed-b831b5755f6c", "person": "Nikita-Khrushchev", "question_class": "actor-group-person-role"}, {"doc_id": "31934637-c916-11e9-96ed-b831b5755f6c", "person": "Nikita-Khrushchev", "question_class": "corporate-person-role"}, {"doc_id": "31934637-c916-11e9-96ed-b831b5755f6c", "person": "Nikita-Khrushchev", "question_class": "lawyer-role"}, {"doc_id": "31934637-c916-11e9-96ed-b831b5755f6c", "person": "Nikita-Khrushchev", "question_class": "ngo-person-role"}, {"doc_id": "31934637-c916-11e9-96ed-b831b5755f6c", "person": "Nikita-Khrushchev", "question_class": "stance", "label": "supporting"}, {"doc_id": "31934637-c916-11e9-96ed-b831b5755f6c", "person": "Nikita-Khrushchev", "question_class": "current", "label": "former"}, {"doc_id": "1e27df2b-c916-11e9-85ef-b831b5755f6c", "person": "Reagan", "question_class": "error", "label": "legit"}, {"doc_id": "1e27df2b-c916-11e9-85ef-b831b5755f6c", "person": "Reagan", "question_class": "affiliation", "label": "government"}, {"doc_id": "1e27df2b-c916-11e9-85ef-b831b5755f6c", "person": "Reagan", "question_class": "gov-branch", "label": "executive"}, {"doc_id": "1e27df2b-c916-11e9-85ef-b831b5755f6c", "person": "Reagan", "question_class": "gov-person-role", "label": "decision-maker"}, {"doc_id": "1e27df2b-c916-11e9-85ef-b831b5755f6c", "person": "Reagan", "question_class": "victim-person-role"}, {"doc_id": "1e27df2b-c916-11e9-85ef-b831b5755f6c", "person": "Reagan", "question_class": "academic-person-role"}, {"doc_id": "1e27df2b-c916-11e9-85ef-b831b5755f6c", "person": "Reagan", "question_class": "witness-person-role"}, {"doc_id": "1e27df2b-c916-11e9-85ef-b831b5755f6c", "person": "Reagan", "question_class": "actor-affiliation-type"}, {"doc_id": "1e27df2b-c916-11e9-85ef-b831b5755f6c", "person": "Reagan", "question_class": "actor-individual-person-role"}, {"doc_id": "1e27df2b-c916-11e9-85ef-b831b5755f6c", "person": "Reagan", "question_class": "actor-group-person-role"}, {"doc_id": "1e27df2b-c916-11e9-85ef-b831b5755f6c", "person": "Reagan", "question_class": "corporate-person-role"}, {"doc_id": "1e27df2b-c916-11e9-85ef-b831b5755f6c", "person": "Reagan", "question_class": "lawyer-role"}, {"doc_id": "1e27df2b-c916-11e9-85ef-b831b5755f6c", "person": "Reagan", "question_class": "ngo-person-role"}, {"doc_id": "1e27df2b-c916-11e9-85ef-b831b5755f6c", "person": "Reagan", "question_class": "stance", "label": "supporting"}, {"doc_id": "1e27df2b-c916-11e9-85ef-b831b5755f6c", "person": "Reagan", "question_class": "current", "label": "current"}, {"doc_id": "1e27df2b-c916-11e9-85ef-b831b5755f6c", "person": "J.-Laurence-Kulp", "question_class": "error", "label": "legit"}, {"doc_id": "1e27df2b-c916-11e9-85ef-b831b5755f6c", "person": "J.-Laurence-Kulp", "question_class": "affiliation", "label": "academic"}, {"doc_id": "1e27df2b-c916-11e9-85ef-b831b5755f6c", "person": "J.-Laurence-Kulp", "question_class": "gov-branch"}, {"doc_id": "1e27df2b-c916-11e9-85ef-b831b5755f6c", "person": "J.-Laurence-Kulp", "question_class": "gov-person-role"}, {"doc_id": "1e27df2b-c916-11e9-85ef-b831b5755f6c", "person": "J.-Laurence-Kulp", "question_class": "victim-person-role"}, {"doc_id": "1e27df2b-c916-11e9-85ef-b831b5755f6c", "person": "J.-Laurence-Kulp", "question_class": "academic-person-role", "label": "decision-maker"}, {"doc_id": "1e27df2b-c916-11e9-85ef-b831b5755f6c", "person": "J.-Laurence-Kulp", "question_class": "witness-person-role"}, {"doc_id": "1e27df2b-c916-11e9-85ef-b831b5755f6c", "person": "J.-Laurence-Kulp", "question_class": "actor-affiliation-type"}, {"doc_id": "1e27df2b-c916-11e9-85ef-b831b5755f6c", "person": "J.-Laurence-Kulp", "question_class": "actor-individual-person-role"}, {"doc_id": "1e27df2b-c916-11e9-85ef-b831b5755f6c", "person": "J.-Laurence-Kulp", "question_class": "actor-group-person-role"}, {"doc_id": "1e27df2b-c916-11e9-85ef-b831b5755f6c", "person": "J.-Laurence-Kulp", "question_class": "corporate-person-role"}, {"doc_id": "1e27df2b-c916-11e9-85ef-b831b5755f6c", "person": "J.-Laurence-Kulp", "question_class": "lawyer-role"}, {"doc_id": "1e27df2b-c916-11e9-85ef-b831b5755f6c", "person": "J.-Laurence-Kulp", "question_class": "ngo-person-role"}, {"doc_id": "1e27df2b-c916-11e9-85ef-b831b5755f6c", "person": "J.-Laurence-Kulp", "question_class": "stance", "label": "supporting"}, {"doc_id": "1e27df2b-c916-11e9-85ef-b831b5755f6c", "person": "J.-Laurence-Kulp", "question_class": "current", "label": "current"}, {"doc_id": "1e27df2b-c916-11e9-85ef-b831b5755f6c", "person": "Michael-Oppenheimer", "question_class": "error", "label": "legit"}, {"doc_id": "1e27df2b-c916-11e9-85ef-b831b5755f6c", "person": "Michael-Oppenheimer", "question_class": "affiliation", "label": "ngo"}, {"doc_id": "1e27df2b-c916-11e9-85ef-b831b5755f6c", "person": "Michael-Oppenheimer", "question_class": "gov-branch"}, {"doc_id": "1e27df2b-c916-11e9-85ef-b831b5755f6c", "person": "Michael-Oppenheimer", "question_class": "gov-person-role"}, {"doc_id": "1e27df2b-c916-11e9-85ef-b831b5755f6c", "person": "Michael-Oppenheimer", "question_class": "victim-person-role"}, {"doc_id": "1e27df2b-c916-11e9-85ef-b831b5755f6c", "person": "Michael-Oppenheimer", "question_class": "academic-person-role"}, {"doc_id": "1e27df2b-c916-11e9-85ef-b831b5755f6c", "person": "Michael-Oppenheimer", "question_class": "witness-person-role"}, {"doc_id": "1e27df2b-c916-11e9-85ef-b831b5755f6c", "person": "Michael-Oppenheimer", "question_class": "actor-affiliation-type"}, {"doc_id": "1e27df2b-c916-11e9-85ef-b831b5755f6c", "person": "Michael-Oppenheimer", "question_class": "actor-individual-person-role"}, {"doc_id": "1e27df2b-c916-11e9-85ef-b831b5755f6c", "person": "Michael-Oppenheimer", "question_class": "actor-group-person-role"}, {"doc_id": "1e27df2b-c916-11e9-85ef-b831b5755f6c", "person": "Michael-Oppenheimer", "question_class": "corporate-person-role"}, {"doc_id": "1e27df2b-c916-11e9-85ef-b831b5755f6c", "person": "Michael-Oppenheimer", "question_class": "lawyer-role"}, {"doc_id": "1e27df2b-c916-11e9-85ef-b831b5755f6c", "person": "Michael-Oppenheimer", "question_class": "ngo-person-role", "label": "expert"}, {"doc_id": "1e27df2b-c916-11e9-85ef-b831b5755f6c", "person": "Michael-Oppenheimer", "question_class": "stance", "label": "opposing"}, {"doc_id": "1e27df2b-c916-11e9-85ef-b831b5755f6c", "person": "Michael-Oppenheimer", "question_class": "current", "label": "current"}, {"doc_id": "1e27df2b-c916-11e9-85ef-b831b5755f6c", "person": "Richard-Ayres", "question_class": "error", "label": "legit"}, {"doc_id": "1e27df2b-c916-11e9-85ef-b831b5755f6c", "person": "Richard-Ayres", "question_class": "affiliation", "label": "ngo"}, {"doc_id": "1e27df2b-c916-11e9-85ef-b831b5755f6c", "person": "Richard-Ayres", "question_class": "gov-branch"}, {"doc_id": "1e27df2b-c916-11e9-85ef-b831b5755f6c", "person": "Richard-Ayres", "question_class": "gov-person-role"}, {"doc_id": "1e27df2b-c916-11e9-85ef-b831b5755f6c", "person": "Richard-Ayres", "question_class": "victim-person-role"}, {"doc_id": "1e27df2b-c916-11e9-85ef-b831b5755f6c", "person": "Richard-Ayres", "question_class": "academic-person-role"}, {"doc_id": "1e27df2b-c916-11e9-85ef-b831b5755f6c", "person": "Richard-Ayres", "question_class": "witness-person-role"}, {"doc_id": "1e27df2b-c916-11e9-85ef-b831b5755f6c", "person": "Richard-Ayres", "question_class": "actor-affiliation-type"}, {"doc_id": "1e27df2b-c916-11e9-85ef-b831b5755f6c", "person": "Richard-Ayres", "question_class": "actor-individual-person-role"}, {"doc_id": "1e27df2b-c916-11e9-85ef-b831b5755f6c", "person": "Richard-Ayres", "question_class": "actor-group-person-role"}, {"doc_id": "1e27df2b-c916-11e9-85ef-b831b5755f6c", "person": "Richard-Ayres", "question_class": "corporate-person-role"}, {"doc_id": "1e27df2b-c916-11e9-85ef-b831b5755f6c", "person": "Richard-Ayres", "question_class": "lawyer-role"}, {"doc_id": "1e27df2b-c916-11e9-85ef-b831b5755f6c", "person": "Richard-Ayres", "question_class": "ngo-person-role", "label": "expert"}, {"doc_id": "1e27df2b-c916-11e9-85ef-b831b5755f6c", "person": "Richard-Ayres", "question_class": "stance", "label": "opposing"}, {"doc_id": "1e27df2b-c916-11e9-85ef-b831b5755f6c", "person": "Richard-Ayres", "question_class": "current", "label": "current"}, {"doc_id": "1e27df2b-c916-11e9-85ef-b831b5755f6c", "person": "Lee-M.-Thomas", "question_class": "error", "label": "legit"}, {"doc_id": "1e27df2b-c916-11e9-85ef-b831b5755f6c", "person": "Lee-M.-Thomas", "question_class": "affiliation", "label": "government"}, {"doc_id": "1e27df2b-c916-11e9-85ef-b831b5755f6c", "person": "Lee-M.-Thomas", "question_class": "gov-branch", "label": "executive"}, {"doc_id": "1e27df2b-c916-11e9-85ef-b831b5755f6c", "person": "Lee-M.-Thomas", "question_class": "gov-person-role", "label": "expert"}, {"doc_id": "1e27df2b-c916-11e9-85ef-b831b5755f6c", "person": "Lee-M.-Thomas", "question_class": "victim-person-role"}, {"doc_id": "1e27df2b-c916-11e9-85ef-b831b5755f6c", "person": "Lee-M.-Thomas", "question_class": "academic-person-role"}, {"doc_id": "1e27df2b-c916-11e9-85ef-b831b5755f6c", "person": "Lee-M.-Thomas", "question_class": "witness-person-role"}, {"doc_id": "1e27df2b-c916-11e9-85ef-b831b5755f6c", "person": "Lee-M.-Thomas", "question_class": "actor-affiliation-type"}, {"doc_id": "1e27df2b-c916-11e9-85ef-b831b5755f6c", "person": "Lee-M.-Thomas", "question_class": "actor-individual-person-role"}, {"doc_id": "1e27df2b-c916-11e9-85ef-b831b5755f6c", "person": "Lee-M.-Thomas", "question_class": "actor-group-person-role"}, {"doc_id": "1e27df2b-c916-11e9-85ef-b831b5755f6c", "person": "Lee-M.-Thomas", "question_class": "corporate-person-role"}, {"doc_id": "1e27df2b-c916-11e9-85ef-b831b5755f6c", "person": "Lee-M.-Thomas", "question_class": "lawyer-role"}, {"doc_id": "1e27df2b-c916-11e9-85ef-b831b5755f6c", "person": "Lee-M.-Thomas", "question_class": "ngo-person-role"}, {"doc_id": "1e27df2b-c916-11e9-85ef-b831b5755f6c", "person": "Lee-M.-Thomas", "question_class": "stance", "label": "supporting"}, {"doc_id": "1e27df2b-c916-11e9-85ef-b831b5755f6c", "person": "Lee-M.-Thomas", "question_class": "current", "label": "current"}, {"doc_id": "6194170c-c916-11e9-a403-b831b5755f6c", "person": "Randy-Tate", "question_class": "error", "label": "legit"}, {"doc_id": "6194170c-c916-11e9-a403-b831b5755f6c", "person": "Randy-Tate", "question_class": "affiliation", "label": "ngo"}, {"doc_id": "6194170c-c916-11e9-a403-b831b5755f6c", "person": "Randy-Tate", "question_class": "gov-branch"}, {"doc_id": "6194170c-c916-11e9-a403-b831b5755f6c", "person": "Randy-Tate", "question_class": "gov-person-role"}, {"doc_id": "6194170c-c916-11e9-a403-b831b5755f6c", "person": "Randy-Tate", "question_class": "victim-person-role"}, {"doc_id": "6194170c-c916-11e9-a403-b831b5755f6c", "person": "Randy-Tate", "question_class": "academic-person-role"}, {"doc_id": "6194170c-c916-11e9-a403-b831b5755f6c", "person": "Randy-Tate", "question_class": "witness-person-role"}, {"doc_id": "6194170c-c916-11e9-a403-b831b5755f6c", "person": "Randy-Tate", "question_class": "actor-affiliation-type"}, {"doc_id": "6194170c-c916-11e9-a403-b831b5755f6c", "person": "Randy-Tate", "question_class": "actor-individual-person-role"}, {"doc_id": "6194170c-c916-11e9-a403-b831b5755f6c", "person": "Randy-Tate", "question_class": "actor-group-person-role"}, {"doc_id": "6194170c-c916-11e9-a403-b831b5755f6c", "person": "Randy-Tate", "question_class": "corporate-person-role"}, {"doc_id": "6194170c-c916-11e9-a403-b831b5755f6c", "person": "Randy-Tate", "question_class": "lawyer-role"}, {"doc_id": "6194170c-c916-11e9-a403-b831b5755f6c", "person": "Randy-Tate", "question_class": "ngo-person-role", "label": "actor"}, {"doc_id": "6194170c-c916-11e9-a403-b831b5755f6c", "person": "Randy-Tate", "question_class": "stance", "label": "supporting"}, {"doc_id": "6194170c-c916-11e9-a403-b831b5755f6c", "person": "Randy-Tate", "question_class": "current", "label": "current"}, {"doc_id": "6194170c-c916-11e9-a403-b831b5755f6c", "person": "Joe-Cooper", "question_class": "error", "label": "legit"}, {"doc_id": "6194170c-c916-11e9-a403-b831b5755f6c", "person": "Joe-Cooper", "question_class": "affiliation", "label": "ngo"}, {"doc_id": "6194170c-c916-11e9-a403-b831b5755f6c", "person": "Joe-Cooper", "question_class": "gov-branch"}, {"doc_id": "6194170c-c916-11e9-a403-b831b5755f6c", "person": "Joe-Cooper", "question_class": "gov-person-role"}, {"doc_id": "6194170c-c916-11e9-a403-b831b5755f6c", "person": "Joe-Cooper", "question_class": "victim-person-role"}, {"doc_id": "6194170c-c916-11e9-a403-b831b5755f6c", "person": "Joe-Cooper", "question_class": "academic-person-role"}, {"doc_id": "6194170c-c916-11e9-a403-b831b5755f6c", "person": "Joe-Cooper", "question_class": "witness-person-role"}, {"doc_id": "6194170c-c916-11e9-a403-b831b5755f6c", "person": "Joe-Cooper", "question_class": "actor-affiliation-type"}, {"doc_id": "6194170c-c916-11e9-a403-b831b5755f6c", "person": "Joe-Cooper", "question_class": "actor-individual-person-role"}, {"doc_id": "6194170c-c916-11e9-a403-b831b5755f6c", "person": "Joe-Cooper", "question_class": "actor-group-person-role"}, {"doc_id": "6194170c-c916-11e9-a403-b831b5755f6c", "person": "Joe-Cooper", "question_class": "corporate-person-role"}, {"doc_id": "6194170c-c916-11e9-a403-b831b5755f6c", "person": "Joe-Cooper", "question_class": "lawyer-role"}, {"doc_id": "6194170c-c916-11e9-a403-b831b5755f6c", "person": "Joe-Cooper", "question_class": "ngo-person-role", "label": "actor"}, {"doc_id": "6194170c-c916-11e9-a403-b831b5755f6c", "person": "Joe-Cooper", "question_class": "stance", "label": "opposing"}, {"doc_id": "6194170c-c916-11e9-a403-b831b5755f6c", "person": "Joe-Cooper", "question_class": "current", "label": "current"}, {"doc_id": "6194170c-c916-11e9-a403-b831b5755f6c", "person": "Rebecca-Isaacs", "question_class": "error", "label": "legit"}, {"doc_id": "6194170c-c916-11e9-a403-b831b5755f6c", "person": "Rebecca-Isaacs", "question_class": "affiliation", "label": "ngo"}, {"doc_id": "6194170c-c916-11e9-a403-b831b5755f6c", "person": "Rebecca-Isaacs", "question_class": "gov-branch"}, {"doc_id": "6194170c-c916-11e9-a403-b831b5755f6c", "person": "Rebecca-Isaacs", "question_class": "gov-person-role"}, {"doc_id": "6194170c-c916-11e9-a403-b831b5755f6c", "person": "Rebecca-Isaacs", "question_class": "victim-person-role"}, {"doc_id": "6194170c-c916-11e9-a403-b831b5755f6c", "person": "Rebecca-Isaacs", "question_class": "academic-person-role"}, {"doc_id": "6194170c-c916-11e9-a403-b831b5755f6c", "person": "Rebecca-Isaacs", "question_class": "witness-person-role"}, {"doc_id": "6194170c-c916-11e9-a403-b831b5755f6c", "person": "Rebecca-Isaacs", "question_class": "actor-affiliation-type"}, {"doc_id": "6194170c-c916-11e9-a403-b831b5755f6c", "person": "Rebecca-Isaacs", "question_class": "actor-individual-person-role"}, {"doc_id": "6194170c-c916-11e9-a403-b831b5755f6c", "person": "Rebecca-Isaacs", "question_class": "actor-group-person-role"}, {"doc_id": "6194170c-c916-11e9-a403-b831b5755f6c", "person": "Rebecca-Isaacs", "question_class": "corporate-person-role"}, {"doc_id": "6194170c-c916-11e9-a403-b831b5755f6c", "person": "Rebecca-Isaacs", "question_class": "lawyer-role"}, {"doc_id": "6194170c-c916-11e9-a403-b831b5755f6c", "person": "Rebecca-Isaacs", "question_class": "ngo-person-role", "label": "actor"}, {"doc_id": "6194170c-c916-11e9-a403-b831b5755f6c", "person": "Rebecca-Isaacs", "question_class": "stance", "label": "opposing"}, {"doc_id": "6194170c-c916-11e9-a403-b831b5755f6c", "person": "Rebecca-Isaacs", "question_class": "current", "label": "current"}, {"doc_id": "6194170c-c916-11e9-a403-b831b5755f6c", "person": "Gary-Bauer", "question_class": "error", "label": "legit"}, {"doc_id": "6194170c-c916-11e9-a403-b831b5755f6c", "person": "Gary-Bauer", "question_class": "affiliation", "label": "ngo"}, {"doc_id": "6194170c-c916-11e9-a403-b831b5755f6c", "person": "Gary-Bauer", "question_class": "gov-branch"}, {"doc_id": "6194170c-c916-11e9-a403-b831b5755f6c", "person": "Gary-Bauer", "question_class": "gov-person-role"}, {"doc_id": "6194170c-c916-11e9-a403-b831b5755f6c", "person": "Gary-Bauer", "question_class": "victim-person-role"}, {"doc_id": "6194170c-c916-11e9-a403-b831b5755f6c", "person": "Gary-Bauer", "question_class": "academic-person-role"}, {"doc_id": "6194170c-c916-11e9-a403-b831b5755f6c", "person": "Gary-Bauer", "question_class": "witness-person-role"}, {"doc_id": "6194170c-c916-11e9-a403-b831b5755f6c", "person": "Gary-Bauer", "question_class": "actor-affiliation-type"}, {"doc_id": "6194170c-c916-11e9-a403-b831b5755f6c", "person": "Gary-Bauer", "question_class": "actor-individual-person-role"}, {"doc_id": "6194170c-c916-11e9-a403-b831b5755f6c", "person": "Gary-Bauer", "question_class": "actor-group-person-role"}, {"doc_id": "6194170c-c916-11e9-a403-b831b5755f6c", "person": "Gary-Bauer", "question_class": "corporate-person-role"}, {"doc_id": "6194170c-c916-11e9-a403-b831b5755f6c", "person": "Gary-Bauer", "question_class": "lawyer-role"}, {"doc_id": "6194170c-c916-11e9-a403-b831b5755f6c", "person": "Gary-Bauer", "question_class": "ngo-person-role", "label": "actor"}, {"doc_id": "6194170c-c916-11e9-a403-b831b5755f6c", "person": "Gary-Bauer", "question_class": "stance", "label": "supporting"}, {"doc_id": "6194170c-c916-11e9-a403-b831b5755f6c", "person": "Gary-Bauer", "question_class": "current", "label": "current"}, {"doc_id": "6194170c-c916-11e9-a403-b831b5755f6c", "person": "Michael-Heath", "question_class": "error", "label": "legit"}, {"doc_id": "6194170c-c916-11e9-a403-b831b5755f6c", "person": "Michael-Heath", "question_class": "affiliation", "label": "ngo"}, {"doc_id": "6194170c-c916-11e9-a403-b831b5755f6c", "person": "Michael-Heath", "question_class": "gov-branch"}, {"doc_id": "6194170c-c916-11e9-a403-b831b5755f6c", "person": "Michael-Heath", "question_class": "gov-person-role"}, {"doc_id": "6194170c-c916-11e9-a403-b831b5755f6c", "person": "Michael-Heath", "question_class": "victim-person-role"}, {"doc_id": "6194170c-c916-11e9-a403-b831b5755f6c", "person": "Michael-Heath", "question_class": "academic-person-role"}, {"doc_id": "6194170c-c916-11e9-a403-b831b5755f6c", "person": "Michael-Heath", "question_class": "witness-person-role"}, {"doc_id": "6194170c-c916-11e9-a403-b831b5755f6c", "person": "Michael-Heath", "question_class": "actor-affiliation-type"}, {"doc_id": "6194170c-c916-11e9-a403-b831b5755f6c", "person": "Michael-Heath", "question_class": "actor-individual-person-role"}, {"doc_id": "6194170c-c916-11e9-a403-b831b5755f6c", "person": "Michael-Heath", "question_class": "actor-group-person-role"}, {"doc_id": "6194170c-c916-11e9-a403-b831b5755f6c", "person": "Michael-Heath", "question_class": "corporate-person-role"}, {"doc_id": "6194170c-c916-11e9-a403-b831b5755f6c", "person": "Michael-Heath", "question_class": "lawyer-role"}, {"doc_id": "6194170c-c916-11e9-a403-b831b5755f6c", "person": "Michael-Heath", "question_class": "ngo-person-role", "label": "actor"}, {"doc_id": "6194170c-c916-11e9-a403-b831b5755f6c", "person": "Michael-Heath", "question_class": "stance", "label": "supporting"}, {"doc_id": "6194170c-c916-11e9-a403-b831b5755f6c", "person": "Michael-Heath", "question_class": "current", "label": "current"}, {"doc_id": "6194170c-c916-11e9-a403-b831b5755f6c", "person": "Christian-Potholm", "question_class": "error", "label": "legit"}, {"doc_id": "6194170c-c916-11e9-a403-b831b5755f6c", "person": "Christian-Potholm", "question_class": "affiliation", "label": "academic"}, {"doc_id": "6194170c-c916-11e9-a403-b831b5755f6c", "person": "Christian-Potholm", "question_class": "gov-branch"}, {"doc_id": "6194170c-c916-11e9-a403-b831b5755f6c", "person": "Christian-Potholm", "question_class": "gov-person-role"}, {"doc_id": "6194170c-c916-11e9-a403-b831b5755f6c", "person": "Christian-Potholm", "question_class": "victim-person-role"}, {"doc_id": "6194170c-c916-11e9-a403-b831b5755f6c", "person": "Christian-Potholm", "question_class": "academic-person-role", "label": "other"}, {"doc_id": "6194170c-c916-11e9-a403-b831b5755f6c", "person": "Christian-Potholm", "question_class": "witness-person-role"}, {"doc_id": "6194170c-c916-11e9-a403-b831b5755f6c", "person": "Christian-Potholm", "question_class": "actor-affiliation-type"}, {"doc_id": "6194170c-c916-11e9-a403-b831b5755f6c", "person": "Christian-Potholm", "question_class": "actor-individual-person-role"}, {"doc_id": "6194170c-c916-11e9-a403-b831b5755f6c", "person": "Christian-Potholm", "question_class": "actor-group-person-role"}, {"doc_id": "6194170c-c916-11e9-a403-b831b5755f6c", "person": "Christian-Potholm", "question_class": "corporate-person-role"}, {"doc_id": "6194170c-c916-11e9-a403-b831b5755f6c", "person": "Christian-Potholm", "question_class": "lawyer-role"}, {"doc_id": "6194170c-c916-11e9-a403-b831b5755f6c", "person": "Christian-Potholm", "question_class": "ngo-person-role"}, {"doc_id": "6194170c-c916-11e9-a403-b831b5755f6c", "person": "Christian-Potholm", "question_class": "stance", "label": "informational"}, {"doc_id": "6194170c-c916-11e9-a403-b831b5755f6c", "person": "Christian-Potholm", "question_class": "current", "label": "current"}, {"doc_id": "2afdb68a-c916-11e9-a2b5-b831b5755f6c", "person": "James-D.-Watkins", "question_class": "error", "label": "badentity"}, {"doc_id": "2afdb68a-c916-11e9-a2b5-b831b5755f6c", "person": "James-D.-Watkins", "question_class": "affiliation", "label": "government"}, {"doc_id": "2afdb68a-c916-11e9-a2b5-b831b5755f6c", "person": "James-D.-Watkins", "question_class": "gov-branch", "label": "executive"}, {"doc_id": "2afdb68a-c916-11e9-a2b5-b831b5755f6c", "person": "James-D.-Watkins", "question_class": "gov-person-role", "label": "decision-maker"}, {"doc_id": "2afdb68a-c916-11e9-a2b5-b831b5755f6c", "person": "James-D.-Watkins", "question_class": "victim-person-role"}, {"doc_id": "2afdb68a-c916-11e9-a2b5-b831b5755f6c", "person": "James-D.-Watkins", "question_class": "academic-person-role"}, {"doc_id": "2afdb68a-c916-11e9-a2b5-b831b5755f6c", "person": "James-D.-Watkins", "question_class": "witness-person-role"}, {"doc_id": "2afdb68a-c916-11e9-a2b5-b831b5755f6c", "person": "James-D.-Watkins", "question_class": "actor-affiliation-type"}, {"doc_id": "2afdb68a-c916-11e9-a2b5-b831b5755f6c", "person": "James-D.-Watkins", "question_class": "actor-individual-person-role"}, {"doc_id": "2afdb68a-c916-11e9-a2b5-b831b5755f6c", "person": "James-D.-Watkins", "question_class": "actor-group-person-role"}, {"doc_id": "2afdb68a-c916-11e9-a2b5-b831b5755f6c", "person": "James-D.-Watkins", "question_class": "corporate-person-role"}, {"doc_id": "2afdb68a-c916-11e9-a2b5-b831b5755f6c", "person": "James-D.-Watkins", "question_class": "lawyer-role"}, {"doc_id": "2afdb68a-c916-11e9-a2b5-b831b5755f6c", "person": "James-D.-Watkins", "question_class": "ngo-person-role"}, {"doc_id": "2afdb68a-c916-11e9-a2b5-b831b5755f6c", "person": "James-D.-Watkins", "question_class": "stance", "label": "informational"}, {"doc_id": "2afdb68a-c916-11e9-a2b5-b831b5755f6c", "person": "James-D.-Watkins", "question_class": "current", "label": "current"}, {"doc_id": "2afdb68a-c916-11e9-a2b5-b831b5755f6c", "person": "David-E.-Skaggs", "question_class": "error", "label": "legit"}, {"doc_id": "2afdb68a-c916-11e9-a2b5-b831b5755f6c", "person": "David-E.-Skaggs", "question_class": "affiliation", "label": "government"}, {"doc_id": "2afdb68a-c916-11e9-a2b5-b831b5755f6c", "person": "David-E.-Skaggs", "question_class": "gov-branch", "label": "legislative"}, {"doc_id": "2afdb68a-c916-11e9-a2b5-b831b5755f6c", "person": "David-E.-Skaggs", "question_class": "gov-person-role", "label": "decision-maker"}, {"doc_id": "2afdb68a-c916-11e9-a2b5-b831b5755f6c", "person": "David-E.-Skaggs", "question_class": "victim-person-role"}, {"doc_id": "2afdb68a-c916-11e9-a2b5-b831b5755f6c", "person": "David-E.-Skaggs", "question_class": "academic-person-role"}, {"doc_id": "2afdb68a-c916-11e9-a2b5-b831b5755f6c", "person": "David-E.-Skaggs", "question_class": "witness-person-role"}, {"doc_id": "2afdb68a-c916-11e9-a2b5-b831b5755f6c", "person": "David-E.-Skaggs", "question_class": "actor-affiliation-type"}, {"doc_id": "2afdb68a-c916-11e9-a2b5-b831b5755f6c", "person": "David-E.-Skaggs", "question_class": "actor-individual-person-role"}, {"doc_id": "2afdb68a-c916-11e9-a2b5-b831b5755f6c", "person": "David-E.-Skaggs", "question_class": "actor-group-person-role"}, {"doc_id": "2afdb68a-c916-11e9-a2b5-b831b5755f6c", "person": "David-E.-Skaggs", "question_class": "corporate-person-role"}, {"doc_id": "2afdb68a-c916-11e9-a2b5-b831b5755f6c", "person": "David-E.-Skaggs", "question_class": "lawyer-role"}, {"doc_id": "2afdb68a-c916-11e9-a2b5-b831b5755f6c", "person": "David-E.-Skaggs", "question_class": "ngo-person-role"}, {"doc_id": "2afdb68a-c916-11e9-a2b5-b831b5755f6c", "person": "David-E.-Skaggs", "question_class": "stance", "label": "opposing"}, {"doc_id": "2afdb68a-c916-11e9-a2b5-b831b5755f6c", "person": "David-E.-Skaggs", "question_class": "current", "label": "current"}, {"doc_id": "2afdb68a-c916-11e9-a2b5-b831b5755f6c", "person": "Dick-Thornburgh", "question_class": "error", "label": "legit"}, {"doc_id": "2afdb68a-c916-11e9-a2b5-b831b5755f6c", "person": "Dick-Thornburgh", "question_class": "affiliation", "label": "government"}, {"doc_id": "2afdb68a-c916-11e9-a2b5-b831b5755f6c", "person": "Dick-Thornburgh", "question_class": "gov-branch", "label": "executive"}, {"doc_id": "2afdb68a-c916-11e9-a2b5-b831b5755f6c", "person": "Dick-Thornburgh", "question_class": "gov-person-role", "label": "lawyer"}, {"doc_id": "2afdb68a-c916-11e9-a2b5-b831b5755f6c", "person": "Dick-Thornburgh", "question_class": "victim-person-role"}, {"doc_id": "2afdb68a-c916-11e9-a2b5-b831b5755f6c", "person": "Dick-Thornburgh", "question_class": "academic-person-role"}, {"doc_id": "2afdb68a-c916-11e9-a2b5-b831b5755f6c", "person": "Dick-Thornburgh", "question_class": "witness-person-role"}, {"doc_id": "2afdb68a-c916-11e9-a2b5-b831b5755f6c", "person": "Dick-Thornburgh", "question_class": "actor-affiliation-type"}, {"doc_id": "2afdb68a-c916-11e9-a2b5-b831b5755f6c", "person": "Dick-Thornburgh", "question_class": "actor-individual-person-role"}, {"doc_id": "2afdb68a-c916-11e9-a2b5-b831b5755f6c", "person": "Dick-Thornburgh", "question_class": "actor-group-person-role"}, {"doc_id": "2afdb68a-c916-11e9-a2b5-b831b5755f6c", "person": "Dick-Thornburgh", "question_class": "corporate-person-role"}, {"doc_id": "2afdb68a-c916-11e9-a2b5-b831b5755f6c", "person": "Dick-Thornburgh", "question_class": "lawyer-role", "label": "prosecutor"}, {"doc_id": "2afdb68a-c916-11e9-a2b5-b831b5755f6c", "person": "Dick-Thornburgh", "question_class": "ngo-person-role"}, {"doc_id": "2afdb68a-c916-11e9-a2b5-b831b5755f6c", "person": "Dick-Thornburgh", "question_class": "stance"}, {"doc_id": "2afdb68a-c916-11e9-a2b5-b831b5755f6c", "person": "Dick-Thornburgh", "question_class": "current", "label": "current"}, {"doc_id": "2afdb68a-c916-11e9-a2b5-b831b5755f6c", "person": "Patrick-J.-Etchart", "question_class": "error", "label": "legit"}, {"doc_id": "2afdb68a-c916-11e9-a2b5-b831b5755f6c", "person": "Patrick-J.-Etchart", "question_class": "affiliation", "label": "corporate"}, {"doc_id": "2afdb68a-c916-11e9-a2b5-b831b5755f6c", "person": "Patrick-J.-Etchart", "question_class": "gov-branch"}, {"doc_id": "2afdb68a-c916-11e9-a2b5-b831b5755f6c", "person": "Patrick-J.-Etchart", "question_class": "gov-person-role"}, {"doc_id": "2afdb68a-c916-11e9-a2b5-b831b5755f6c", "person": "Patrick-J.-Etchart", "question_class": "victim-person-role"}, {"doc_id": "2afdb68a-c916-11e9-a2b5-b831b5755f6c", "person": "Patrick-J.-Etchart", "question_class": "academic-person-role"}, {"doc_id": "2afdb68a-c916-11e9-a2b5-b831b5755f6c", "person": "Patrick-J.-Etchart", "question_class": "witness-person-role"}, {"doc_id": "2afdb68a-c916-11e9-a2b5-b831b5755f6c", "person": "Patrick-J.-Etchart", "question_class": "actor-affiliation-type"}, {"doc_id": "2afdb68a-c916-11e9-a2b5-b831b5755f6c", "person": "Patrick-J.-Etchart", "question_class": "actor-individual-person-role"}, {"doc_id": "2afdb68a-c916-11e9-a2b5-b831b5755f6c", "person": "Patrick-J.-Etchart", "question_class": "actor-group-person-role"}, {"doc_id": "2afdb68a-c916-11e9-a2b5-b831b5755f6c", "person": "Patrick-J.-Etchart", "question_class": "corporate-person-role", "label": "spokesman"}, {"doc_id": "2afdb68a-c916-11e9-a2b5-b831b5755f6c", "person": "Patrick-J.-Etchart", "question_class": "lawyer-role"}, {"doc_id": "2afdb68a-c916-11e9-a2b5-b831b5755f6c", "person": "Patrick-J.-Etchart", "question_class": "ngo-person-role"}, {"doc_id": "2afdb68a-c916-11e9-a2b5-b831b5755f6c", "person": "Patrick-J.-Etchart", "question_class": "stance", "label": "informational"}, {"doc_id": "2afdb68a-c916-11e9-a2b5-b831b5755f6c", "person": "Patrick-J.-Etchart", "question_class": "current", "label": "current"}, {"doc_id": "2afdb68a-c916-11e9-a2b5-b831b5755f6c", "person": "Dan-W.-Reicher", "question_class": "error", "label": "legit"}, {"doc_id": "2afdb68a-c916-11e9-a2b5-b831b5755f6c", "person": "Dan-W.-Reicher", "question_class": "affiliation", "label": "ngo"}, {"doc_id": "2afdb68a-c916-11e9-a2b5-b831b5755f6c", "person": "Dan-W.-Reicher", "question_class": "gov-branch"}, {"doc_id": "2afdb68a-c916-11e9-a2b5-b831b5755f6c", "person": "Dan-W.-Reicher", "question_class": "gov-person-role"}, {"doc_id": "2afdb68a-c916-11e9-a2b5-b831b5755f6c", "person": "Dan-W.-Reicher", "question_class": "victim-person-role"}, {"doc_id": "2afdb68a-c916-11e9-a2b5-b831b5755f6c", "person": "Dan-W.-Reicher", "question_class": "academic-person-role"}, {"doc_id": "2afdb68a-c916-11e9-a2b5-b831b5755f6c", "person": "Dan-W.-Reicher", "question_class": "witness-person-role"}, {"doc_id": "2afdb68a-c916-11e9-a2b5-b831b5755f6c", "person": "Dan-W.-Reicher", "question_class": "actor-affiliation-type"}, {"doc_id": "2afdb68a-c916-11e9-a2b5-b831b5755f6c", "person": "Dan-W.-Reicher", "question_class": "actor-individual-person-role"}, {"doc_id": "2afdb68a-c916-11e9-a2b5-b831b5755f6c", "person": "Dan-W.-Reicher", "question_class": "actor-group-person-role"}, {"doc_id": "2afdb68a-c916-11e9-a2b5-b831b5755f6c", "person": "Dan-W.-Reicher", "question_class": "corporate-person-role"}, {"doc_id": "2afdb68a-c916-11e9-a2b5-b831b5755f6c", "person": "Dan-W.-Reicher", "question_class": "lawyer-role"}, {"doc_id": "2afdb68a-c916-11e9-a2b5-b831b5755f6c", "person": "Dan-W.-Reicher", "question_class": "ngo-person-role", "label": "expert"}, {"doc_id": "2afdb68a-c916-11e9-a2b5-b831b5755f6c", "person": "Dan-W.-Reicher", "question_class": "stance", "label": "opposing"}, {"doc_id": "2afdb68a-c916-11e9-a2b5-b831b5755f6c", "person": "Dan-W.-Reicher", "question_class": "current", "label": "current"}, {"doc_id": "1df05757-c916-11e9-8d4d-b831b5755f6c", "person": "John-Houser", "question_class": "error", "label": "legit"}, {"doc_id": "1df05757-c916-11e9-8d4d-b831b5755f6c", "person": "John-Houser", "question_class": "affiliation", "label": "corporate"}, {"doc_id": "1df05757-c916-11e9-8d4d-b831b5755f6c", "person": "John-Houser", "question_class": "gov-branch"}, {"doc_id": "1df05757-c916-11e9-8d4d-b831b5755f6c", "person": "John-Houser", "question_class": "gov-person-role"}, {"doc_id": "1df05757-c916-11e9-8d4d-b831b5755f6c", "person": "John-Houser", "question_class": "victim-person-role"}, {"doc_id": "1df05757-c916-11e9-8d4d-b831b5755f6c", "person": "John-Houser", "question_class": "academic-person-role"}, {"doc_id": "1df05757-c916-11e9-8d4d-b831b5755f6c", "person": "John-Houser", "question_class": "witness-person-role"}, {"doc_id": "1df05757-c916-11e9-8d4d-b831b5755f6c", "person": "John-Houser", "question_class": "actor-affiliation-type"}, {"doc_id": "1df05757-c916-11e9-8d4d-b831b5755f6c", "person": "John-Houser", "question_class": "actor-individual-person-role"}, {"doc_id": "1df05757-c916-11e9-8d4d-b831b5755f6c", "person": "John-Houser", "question_class": "actor-group-person-role"}, {"doc_id": "1df05757-c916-11e9-8d4d-b831b5755f6c", "person": "John-Houser", "question_class": "corporate-person-role", "label": "spokesman"}, {"doc_id": "1df05757-c916-11e9-8d4d-b831b5755f6c", "person": "John-Houser", "question_class": "lawyer-role"}, {"doc_id": "1df05757-c916-11e9-8d4d-b831b5755f6c", "person": "John-Houser", "question_class": "ngo-person-role"}, {"doc_id": "1df05757-c916-11e9-8d4d-b831b5755f6c", "person": "John-Houser", "question_class": "stance", "label": "supporting"}, {"doc_id": "1df05757-c916-11e9-8d4d-b831b5755f6c", "person": "John-Houser", "question_class": "current", "label": "current"}, {"doc_id": "1df05757-c916-11e9-8d4d-b831b5755f6c", "person": "Rami-S.-Abuhamdeh", "question_class": "error", "label": "legit"}, {"doc_id": "1df05757-c916-11e9-8d4d-b831b5755f6c", "person": "Rami-S.-Abuhamdeh", "question_class": "affiliation", "label": "ngo"}, {"doc_id": "1df05757-c916-11e9-8d4d-b831b5755f6c", "person": "Rami-S.-Abuhamdeh", "question_class": "gov-branch"}, {"doc_id": "1df05757-c916-11e9-8d4d-b831b5755f6c", "person": "Rami-S.-Abuhamdeh", "question_class": "gov-person-role"}, {"doc_id": "1df05757-c916-11e9-8d4d-b831b5755f6c", "person": "Rami-S.-Abuhamdeh", "question_class": "victim-person-role"}, {"doc_id": "1df05757-c916-11e9-8d4d-b831b5755f6c", "person": "Rami-S.-Abuhamdeh", "question_class": "academic-person-role"}, {"doc_id": "1df05757-c916-11e9-8d4d-b831b5755f6c", "person": "Rami-S.-Abuhamdeh", "question_class": "witness-person-role"}, {"doc_id": "1df05757-c916-11e9-8d4d-b831b5755f6c", "person": "Rami-S.-Abuhamdeh", "question_class": "actor-affiliation-type"}, {"doc_id": "1df05757-c916-11e9-8d4d-b831b5755f6c", "person": "Rami-S.-Abuhamdeh", "question_class": "actor-individual-person-role"}, {"doc_id": "1df05757-c916-11e9-8d4d-b831b5755f6c", "person": "Rami-S.-Abuhamdeh", "question_class": "actor-group-person-role"}, {"doc_id": "1df05757-c916-11e9-8d4d-b831b5755f6c", "person": "Rami-S.-Abuhamdeh", "question_class": "corporate-person-role"}, {"doc_id": "1df05757-c916-11e9-8d4d-b831b5755f6c", "person": "Rami-S.-Abuhamdeh", "question_class": "lawyer-role"}, {"doc_id": "1df05757-c916-11e9-8d4d-b831b5755f6c", "person": "Rami-S.-Abuhamdeh", "question_class": "ngo-person-role", "label": "expert"}, {"doc_id": "1df05757-c916-11e9-8d4d-b831b5755f6c", "person": "Rami-S.-Abuhamdeh", "question_class": "stance", "label": "informational"}, {"doc_id": "1df05757-c916-11e9-8d4d-b831b5755f6c", "person": "Rami-S.-Abuhamdeh", "question_class": "current", "label": "current"}, {"doc_id": "1df05757-c916-11e9-8d4d-b831b5755f6c", "person": "Del-Wnorowski", "question_class": "error", "label": "legit"}, {"doc_id": "1df05757-c916-11e9-8d4d-b831b5755f6c", "person": "Del-Wnorowski", "question_class": "affiliation", "label": "corporate"}, {"doc_id": "1df05757-c916-11e9-8d4d-b831b5755f6c", "person": "Del-Wnorowski", "question_class": "gov-branch"}, {"doc_id": "1df05757-c916-11e9-8d4d-b831b5755f6c", "person": "Del-Wnorowski", "question_class": "gov-person-role"}, {"doc_id": "1df05757-c916-11e9-8d4d-b831b5755f6c", "person": "Del-Wnorowski", "question_class": "victim-person-role"}, {"doc_id": "1df05757-c916-11e9-8d4d-b831b5755f6c", "person": "Del-Wnorowski", "question_class": "academic-person-role"}, {"doc_id": "1df05757-c916-11e9-8d4d-b831b5755f6c", "person": "Del-Wnorowski", "question_class": "witness-person-role"}, {"doc_id": "1df05757-c916-11e9-8d4d-b831b5755f6c", "person": "Del-Wnorowski", "question_class": "actor-affiliation-type"}, {"doc_id": "1df05757-c916-11e9-8d4d-b831b5755f6c", "person": "Del-Wnorowski", "question_class": "actor-individual-person-role"}, {"doc_id": "1df05757-c916-11e9-8d4d-b831b5755f6c", "person": "Del-Wnorowski", "question_class": "actor-group-person-role"}, {"doc_id": "1df05757-c916-11e9-8d4d-b831b5755f6c", "person": "Del-Wnorowski", "question_class": "corporate-person-role", "label": "lawyer"}, {"doc_id": "1df05757-c916-11e9-8d4d-b831b5755f6c", "person": "Del-Wnorowski", "question_class": "lawyer-role", "label": "defense"}, {"doc_id": "1df05757-c916-11e9-8d4d-b831b5755f6c", "person": "Del-Wnorowski", "question_class": "ngo-person-role"}, {"doc_id": "1df05757-c916-11e9-8d4d-b831b5755f6c", "person": "Del-Wnorowski", "question_class": "stance"}, {"doc_id": "1df05757-c916-11e9-8d4d-b831b5755f6c", "person": "Del-Wnorowski", "question_class": "current", "label": "current"}, {"doc_id": "92098468-c916-11e9-85c7-b831b5755f6c", "person": "Made-Pastika", "question_class": "error", "label": "legit"}, {"doc_id": "92098468-c916-11e9-85c7-b831b5755f6c", "person": "Made-Pastika", "question_class": "affiliation", "label": "government"}, {"doc_id": "92098468-c916-11e9-85c7-b831b5755f6c", "person": "Made-Pastika", "question_class": "gov-branch", "label": "executive"}, {"doc_id": "92098468-c916-11e9-85c7-b831b5755f6c", "person": "Made-Pastika", "question_class": "gov-person-role", "label": "decision-maker"}, {"doc_id": "92098468-c916-11e9-85c7-b831b5755f6c", "person": "Made-Pastika", "question_class": "victim-person-role"}, {"doc_id": "92098468-c916-11e9-85c7-b831b5755f6c", "person": "Made-Pastika", "question_class": "academic-person-role"}, {"doc_id": "92098468-c916-11e9-85c7-b831b5755f6c", "person": "Made-Pastika", "question_class": "witness-person-role"}, {"doc_id": "92098468-c916-11e9-85c7-b831b5755f6c", "person": "Made-Pastika", "question_class": "actor-affiliation-type"}, {"doc_id": "92098468-c916-11e9-85c7-b831b5755f6c", "person": "Made-Pastika", "question_class": "actor-individual-person-role"}, {"doc_id": "92098468-c916-11e9-85c7-b831b5755f6c", "person": "Made-Pastika", "question_class": "actor-group-person-role"}, {"doc_id": "92098468-c916-11e9-85c7-b831b5755f6c", "person": "Made-Pastika", "question_class": "corporate-person-role"}, {"doc_id": "92098468-c916-11e9-85c7-b831b5755f6c", "person": "Made-Pastika", "question_class": "lawyer-role"}, {"doc_id": "92098468-c916-11e9-85c7-b831b5755f6c", "person": "Made-Pastika", "question_class": "ngo-person-role"}, {"doc_id": "92098468-c916-11e9-85c7-b831b5755f6c", "person": "Made-Pastika", "question_class": "stance", "label": "informational"}, {"doc_id": "92098468-c916-11e9-85c7-b831b5755f6c", "person": "Made-Pastika", "question_class": "current", "label": "current"}, {"doc_id": "92098468-c916-11e9-85c7-b831b5755f6c", "person": "Susilo-Bambang-Yudhoyono", "question_class": "error", "label": "legit"}, {"doc_id": "92098468-c916-11e9-85c7-b831b5755f6c", "person": "Susilo-Bambang-Yudhoyono", "question_class": "affiliation", "label": "government"}, {"doc_id": "92098468-c916-11e9-85c7-b831b5755f6c", "person": "Susilo-Bambang-Yudhoyono", "question_class": "gov-branch", "label": "executive"}, {"doc_id": "92098468-c916-11e9-85c7-b831b5755f6c", "person": "Susilo-Bambang-Yudhoyono", "question_class": "gov-person-role", "label": "decision-maker"}, {"doc_id": "92098468-c916-11e9-85c7-b831b5755f6c", "person": "Susilo-Bambang-Yudhoyono", "question_class": "victim-person-role"}, {"doc_id": "92098468-c916-11e9-85c7-b831b5755f6c", "person": "Susilo-Bambang-Yudhoyono", "question_class": "academic-person-role"}, {"doc_id": "92098468-c916-11e9-85c7-b831b5755f6c", "person": "Susilo-Bambang-Yudhoyono", "question_class": "witness-person-role"}, {"doc_id": "92098468-c916-11e9-85c7-b831b5755f6c", "person": "Susilo-Bambang-Yudhoyono", "question_class": "actor-affiliation-type"}, {"doc_id": "92098468-c916-11e9-85c7-b831b5755f6c", "person": "Susilo-Bambang-Yudhoyono", "question_class": "actor-individual-person-role"}, {"doc_id": "92098468-c916-11e9-85c7-b831b5755f6c", "person": "Susilo-Bambang-Yudhoyono", "question_class": "actor-group-person-role"}, {"doc_id": "92098468-c916-11e9-85c7-b831b5755f6c", "person": "Susilo-Bambang-Yudhoyono", "question_class": "corporate-person-role"}, {"doc_id": "92098468-c916-11e9-85c7-b831b5755f6c", "person": "Susilo-Bambang-Yudhoyono", "question_class": "lawyer-role"}, {"doc_id": "92098468-c916-11e9-85c7-b831b5755f6c", "person": "Susilo-Bambang-Yudhoyono", "question_class": "ngo-person-role"}, {"doc_id": "92098468-c916-11e9-85c7-b831b5755f6c", "person": "Susilo-Bambang-Yudhoyono", "question_class": "stance", "label": "informational"}, {"doc_id": "92098468-c916-11e9-85c7-b831b5755f6c", "person": "Susilo-Bambang-Yudhoyono", "question_class": "current", "label": "current"}, {"doc_id": "92098468-c916-11e9-85c7-b831b5755f6c", "person": "Sidney-Jones", "question_class": "error", "label": "legit"}, {"doc_id": "92098468-c916-11e9-85c7-b831b5755f6c", "person": "Sidney-Jones", "question_class": "affiliation", "label": "academic"}, {"doc_id": "92098468-c916-11e9-85c7-b831b5755f6c", "person": "Sidney-Jones", "question_class": "gov-branch"}, {"doc_id": "92098468-c916-11e9-85c7-b831b5755f6c", "person": "Sidney-Jones", "question_class": "gov-person-role"}, {"doc_id": "92098468-c916-11e9-85c7-b831b5755f6c", "person": "Sidney-Jones", "question_class": "victim-person-role"}, {"doc_id": "92098468-c916-11e9-85c7-b831b5755f6c", "person": "Sidney-Jones", "question_class": "academic-person-role", "label": "other"}, {"doc_id": "92098468-c916-11e9-85c7-b831b5755f6c", "person": "Sidney-Jones", "question_class": "witness-person-role"}, {"doc_id": "92098468-c916-11e9-85c7-b831b5755f6c", "person": "Sidney-Jones", "question_class": "actor-affiliation-type"}, {"doc_id": "92098468-c916-11e9-85c7-b831b5755f6c", "person": "Sidney-Jones", "question_class": "actor-individual-person-role"}, {"doc_id": "92098468-c916-11e9-85c7-b831b5755f6c", "person": "Sidney-Jones", "question_class": "actor-group-person-role"}, {"doc_id": "92098468-c916-11e9-85c7-b831b5755f6c", "person": "Sidney-Jones", "question_class": "corporate-person-role"}, {"doc_id": "92098468-c916-11e9-85c7-b831b5755f6c", "person": "Sidney-Jones", "question_class": "lawyer-role"}, {"doc_id": "92098468-c916-11e9-85c7-b831b5755f6c", "person": "Sidney-Jones", "question_class": "ngo-person-role"}, {"doc_id": "92098468-c916-11e9-85c7-b831b5755f6c", "person": "Sidney-Jones", "question_class": "stance", "label": "informational"}, {"doc_id": "92098468-c916-11e9-85c7-b831b5755f6c", "person": "Sidney-Jones", "question_class": "current", "label": "current"}, {"doc_id": "92098468-c916-11e9-85c7-b831b5755f6c", "person": "Soviana-Suprato-Ly", "question_class": "error", "label": "legit"}, {"doc_id": "92098468-c916-11e9-85c7-b831b5755f6c", "person": "Soviana-Suprato-Ly", "question_class": "affiliation", "label": "witness"}, {"doc_id": "92098468-c916-11e9-85c7-b831b5755f6c", "person": "Soviana-Suprato-Ly", "question_class": "gov-branch"}, {"doc_id": "92098468-c916-11e9-85c7-b831b5755f6c", "person": "Soviana-Suprato-Ly", "question_class": "gov-person-role"}, {"doc_id": "92098468-c916-11e9-85c7-b831b5755f6c", "person": "Soviana-Suprato-Ly", "question_class": "victim-person-role"}, {"doc_id": "92098468-c916-11e9-85c7-b831b5755f6c", "person": "Soviana-Suprato-Ly", "question_class": "academic-person-role"}, {"doc_id": "92098468-c916-11e9-85c7-b831b5755f6c", "person": "Soviana-Suprato-Ly", "question_class": "witness-person-role", "label": "casual"}, {"doc_id": "92098468-c916-11e9-85c7-b831b5755f6c", "person": "Soviana-Suprato-Ly", "question_class": "actor-affiliation-type"}, {"doc_id": "92098468-c916-11e9-85c7-b831b5755f6c", "person": "Soviana-Suprato-Ly", "question_class": "actor-individual-person-role"}, {"doc_id": "92098468-c916-11e9-85c7-b831b5755f6c", "person": "Soviana-Suprato-Ly", "question_class": "actor-group-person-role"}, {"doc_id": "92098468-c916-11e9-85c7-b831b5755f6c", "person": "Soviana-Suprato-Ly", "question_class": "corporate-person-role"}, {"doc_id": "92098468-c916-11e9-85c7-b831b5755f6c", "person": "Soviana-Suprato-Ly", "question_class": "lawyer-role"}, {"doc_id": "92098468-c916-11e9-85c7-b831b5755f6c", "person": "Soviana-Suprato-Ly", "question_class": "ngo-person-role"}, {"doc_id": "92098468-c916-11e9-85c7-b831b5755f6c", "person": "Soviana-Suprato-Ly", "question_class": "stance", "label": "informational"}, {"doc_id": "92098468-c916-11e9-85c7-b831b5755f6c", "person": "Soviana-Suprato-Ly", "question_class": "current", "label": "current"}]