[{"doc_id": "84ba3ba0-c916-11e9-b04b-b831b5755f6c", "person": "Junior-Bush", "question_class": "error", "label": "legit"}, {"doc_id": "84ba3ba0-c916-11e9-b04b-b831b5755f6c", "person": "Junior-Bush", "question_class": "affiliation", "label": "government"}, {"doc_id": "84ba3ba0-c916-11e9-b04b-b831b5755f6c", "person": "Junior-Bush", "question_class": "gov-branch", "label": "executive"}, {"doc_id": "84ba3ba0-c916-11e9-b04b-b831b5755f6c", "person": "Junior-Bush", "question_class": "gov-person-role", "label": "decision-maker"}, {"doc_id": "84ba3ba0-c916-11e9-b04b-b831b5755f6c", "person": "Junior-Bush", "question_class": "victim-person-role"}, {"doc_id": "84ba3ba0-c916-11e9-b04b-b831b5755f6c", "person": "Junior-Bush", "question_class": "academic-person-role"}, {"doc_id": "84ba3ba0-c916-11e9-b04b-b831b5755f6c", "person": "Junior-Bush", "question_class": "witness-person-role"}, {"doc_id": "84ba3ba0-c916-11e9-b04b-b831b5755f6c", "person": "Junior-Bush", "question_class": "actor-affiliation-type"}, {"doc_id": "84ba3ba0-c916-11e9-b04b-b831b5755f6c", "person": "Junior-Bush", "question_class": "actor-individual-person-role"}, {"doc_id": "84ba3ba0-c916-11e9-b04b-b831b5755f6c", "person": "Junior-Bush", "question_class": "actor-group-person-role"}, {"doc_id": "84ba3ba0-c916-11e9-b04b-b831b5755f6c", "person": "Junior-Bush", "question_class": "corporate-person-role"}, {"doc_id": "84ba3ba0-c916-11e9-b04b-b831b5755f6c", "person": "Junior-Bush", "question_class": "lawyer-role"}, {"doc_id": "84ba3ba0-c916-11e9-b04b-b831b5755f6c", "person": "Junior-Bush", "question_class": "ngo-person-role"}, {"doc_id": "84ba3ba0-c916-11e9-b04b-b831b5755f6c", "person": "Junior-Bush", "question_class": "stance", "label": "informational"}, {"doc_id": "84ba3ba0-c916-11e9-b04b-b831b5755f6c", "person": "Saddam-Hussein", "question_class": "error", "label": "notsource"}, {"doc_id": "84ba3ba0-c916-11e9-b04b-b831b5755f6c", "person": "Saddam-Hussein", "question_class": "affiliation"}, {"doc_id": "84ba3ba0-c916-11e9-b04b-b831b5755f6c", "person": "Saddam-Hussein", "question_class": "gov-branch"}, {"doc_id": "84ba3ba0-c916-11e9-b04b-b831b5755f6c", "person": "Saddam-Hussein", "question_class": "gov-person-role"}, {"doc_id": "84ba3ba0-c916-11e9-b04b-b831b5755f6c", "person": "Saddam-Hussein", "question_class": "victim-person-role", "label": "individual"}, {"doc_id": "84ba3ba0-c916-11e9-b04b-b831b5755f6c", "person": "Saddam-Hussein", "question_class": "academic-person-role", "label": "decision-maker"}, {"doc_id": "84ba3ba0-c916-11e9-b04b-b831b5755f6c", "person": "Saddam-Hussein", "question_class": "witness-person-role", "label": "casual"}, {"doc_id": "84ba3ba0-c916-11e9-b04b-b831b5755f6c", "person": "Saddam-Hussein", "question_class": "actor-affiliation-type", "label": "individual"}, {"doc_id": "84ba3ba0-c916-11e9-b04b-b831b5755f6c", "person": "Saddam-Hussein", "question_class": "actor-individual-person-role", "label": "individual"}, {"doc_id": "84ba3ba0-c916-11e9-b04b-b831b5755f6c", "person": "Saddam-Hussein", "question_class": "actor-group-person-role", "label": "leader"}, {"doc_id": "84ba3ba0-c916-11e9-b04b-b831b5755f6c", "person": "Saddam-Hussein", "question_class": "corporate-person-role"}, {"doc_id": "84ba3ba0-c916-11e9-b04b-b831b5755f6c", "person": "Saddam-Hussein", "question_class": "lawyer-role"}, {"doc_id": "84ba3ba0-c916-11e9-b04b-b831b5755f6c", "person": "Saddam-Hussein", "question_class": "ngo-person-role"}, {"doc_id": "84ba3ba0-c916-11e9-b04b-b831b5755f6c", "person": "Saddam-Hussein", "question_class": "stance"}, {"doc_id": "84ba3ba0-c916-11e9-b04b-b831b5755f6c", "person": "Ari-Fleischer", "question_class": "error", "label": "legit"}, {"doc_id": "84ba3ba0-c916-11e9-b04b-b831b5755f6c", "person": "Ari-Fleischer", "question_class": "affiliation", "label": "government"}, {"doc_id": "84ba3ba0-c916-11e9-b04b-b831b5755f6c", "person": "Ari-Fleischer", "question_class": "gov-branch", "label": "executive"}, {"doc_id": "84ba3ba0-c916-11e9-b04b-b831b5755f6c", "person": "Ari-Fleischer", "question_class": "gov-person-role", "label": "spokesman"}, {"doc_id": "84ba3ba0-c916-11e9-b04b-b831b5755f6c", "person": "Ari-Fleischer", "question_class": "victim-person-role"}, {"doc_id": "84ba3ba0-c916-11e9-b04b-b831b5755f6c", "person": "Ari-Fleischer", "question_class": "academic-person-role"}, {"doc_id": "84ba3ba0-c916-11e9-b04b-b831b5755f6c", "person": "Ari-Fleischer", "question_class": "witness-person-role"}, {"doc_id": "84ba3ba0-c916-11e9-b04b-b831b5755f6c", "person": "Ari-Fleischer", "question_class": "actor-affiliation-type"}, {"doc_id": "84ba3ba0-c916-11e9-b04b-b831b5755f6c", "person": "Ari-Fleischer", "question_class": "actor-individual-person-role"}, {"doc_id": "84ba3ba0-c916-11e9-b04b-b831b5755f6c", "person": "Ari-Fleischer", "question_class": "actor-group-person-role"}, {"doc_id": "84ba3ba0-c916-11e9-b04b-b831b5755f6c", "person": "Ari-Fleischer", "question_class": "corporate-person-role"}, {"doc_id": "84ba3ba0-c916-11e9-b04b-b831b5755f6c", "person": "Ari-Fleischer", "question_class": "lawyer-role"}, {"doc_id": "84ba3ba0-c916-11e9-b04b-b831b5755f6c", "person": "Ari-Fleischer", "question_class": "ngo-person-role"}, {"doc_id": "84ba3ba0-c916-11e9-b04b-b831b5755f6c", "person": "Ari-Fleischer", "question_class": "stance", "label": "informational"}, {"doc_id": "84ba3ba0-c916-11e9-b04b-b831b5755f6c", "person": "Card", "question_class": "error", "label": "notsource"}, {"doc_id": "84ba3ba0-c916-11e9-b04b-b831b5755f6c", "person": "Card", "question_class": "affiliation"}, {"doc_id": "84ba3ba0-c916-11e9-b04b-b831b5755f6c", "person": "Card", "question_class": "gov-branch"}, {"doc_id": "84ba3ba0-c916-11e9-b04b-b831b5755f6c", "person": "Card", "question_class": "gov-person-role"}, {"doc_id": "84ba3ba0-c916-11e9-b04b-b831b5755f6c", "person": "Card", "question_class": "victim-person-role", "label": "individual"}, {"doc_id": "84ba3ba0-c916-11e9-b04b-b831b5755f6c", "person": "Card", "question_class": "academic-person-role", "label": "decision-maker"}, {"doc_id": "84ba3ba0-c916-11e9-b04b-b831b5755f6c", "person": "Card", "question_class": "witness-person-role", "label": "casual"}, {"doc_id": "84ba3ba0-c916-11e9-b04b-b831b5755f6c", "person": "Card", "question_class": "actor-affiliation-type", "label": "individual"}, {"doc_id": "84ba3ba0-c916-11e9-b04b-b831b5755f6c", "person": "Card", "question_class": "actor-individual-person-role", "label": "individual"}, {"doc_id": "84ba3ba0-c916-11e9-b04b-b831b5755f6c", "person": "Card", "question_class": "actor-group-person-role", "label": "leader"}, {"doc_id": "84ba3ba0-c916-11e9-b04b-b831b5755f6c", "person": "Card", "question_class": "corporate-person-role"}, {"doc_id": "84ba3ba0-c916-11e9-b04b-b831b5755f6c", "person": "Card", "question_class": "lawyer-role"}, {"doc_id": "84ba3ba0-c916-11e9-b04b-b831b5755f6c", "person": "Card", "question_class": "ngo-person-role"}, {"doc_id": "84ba3ba0-c916-11e9-b04b-b831b5755f6c", "person": "Card", "question_class": "stance"}, {"doc_id": "5bc9602f-c916-11e9-9f94-b831b5755f6c", "person": "Bobbi-McCaughey", "question_class": "error", "label": "badentity"}, {"doc_id": "5bc9602f-c916-11e9-9f94-b831b5755f6c", "person": "Bobbi-McCaughey", "question_class": "affiliation", "label": "actor"}, {"doc_id": "5bc9602f-c916-11e9-9f94-b831b5755f6c", "person": "Bobbi-McCaughey", "question_class": "gov-branch"}, {"doc_id": "5bc9602f-c916-11e9-9f94-b831b5755f6c", "person": "Bobbi-McCaughey", "question_class": "gov-person-role"}, {"doc_id": "5bc9602f-c916-11e9-9f94-b831b5755f6c", "person": "Bobbi-McCaughey", "question_class": "victim-person-role"}, {"doc_id": "5bc9602f-c916-11e9-9f94-b831b5755f6c", "person": "Bobbi-McCaughey", "question_class": "academic-person-role"}, {"doc_id": "5bc9602f-c916-11e9-9f94-b831b5755f6c", "person": "Bobbi-McCaughey", "question_class": "witness-person-role"}, {"doc_id": "5bc9602f-c916-11e9-9f94-b831b5755f6c", "person": "Bobbi-McCaughey", "question_class": "actor-affiliation-type", "label": "individual"}, {"doc_id": "5bc9602f-c916-11e9-9f94-b831b5755f6c", "person": "Bobbi-McCaughey", "question_class": "actor-individual-person-role", "label": "individual"}, {"doc_id": "5bc9602f-c916-11e9-9f94-b831b5755f6c", "person": "Bobbi-McCaughey", "question_class": "actor-group-person-role"}, {"doc_id": "5bc9602f-c916-11e9-9f94-b831b5755f6c", "person": "Bobbi-McCaughey", "question_class": "corporate-person-role"}, {"doc_id": "5bc9602f-c916-11e9-9f94-b831b5755f6c", "person": "Bobbi-McCaughey", "question_class": "lawyer-role"}, {"doc_id": "5bc9602f-c916-11e9-9f94-b831b5755f6c", "person": "Bobbi-McCaughey", "question_class": "ngo-person-role"}, {"doc_id": "5bc9602f-c916-11e9-9f94-b831b5755f6c", "person": "Bobbi-McCaughey", "question_class": "stance", "label": "informational"}, {"doc_id": "5bc9602f-c916-11e9-9f94-b831b5755f6c", "person": "Paula-Mahone", "question_class": "error", "label": "legit"}, {"doc_id": "5bc9602f-c916-11e9-9f94-b831b5755f6c", "person": "Paula-Mahone", "question_class": "affiliation", "label": "actor"}, {"doc_id": "5bc9602f-c916-11e9-9f94-b831b5755f6c", "person": "Paula-Mahone", "question_class": "gov-branch"}, {"doc_id": "5bc9602f-c916-11e9-9f94-b831b5755f6c", "person": "Paula-Mahone", "question_class": "gov-person-role"}, {"doc_id": "5bc9602f-c916-11e9-9f94-b831b5755f6c", "person": "Paula-Mahone", "question_class": "victim-person-role"}, {"doc_id": "5bc9602f-c916-11e9-9f94-b831b5755f6c", "person": "Paula-Mahone", "question_class": "academic-person-role"}, {"doc_id": "5bc9602f-c916-11e9-9f94-b831b5755f6c", "person": "Paula-Mahone", "question_class": "witness-person-role"}, {"doc_id": "5bc9602f-c916-11e9-9f94-b831b5755f6c", "person": "Paula-Mahone", "question_class": "actor-affiliation-type", "label": "individual"}, {"doc_id": "5bc9602f-c916-11e9-9f94-b831b5755f6c", "person": "Paula-Mahone", "question_class": "actor-individual-person-role", "label": "doctor"}, {"doc_id": "5bc9602f-c916-11e9-9f94-b831b5755f6c", "person": "Paula-Mahone", "question_class": "actor-group-person-role"}, {"doc_id": "5bc9602f-c916-11e9-9f94-b831b5755f6c", "person": "Paula-Mahone", "question_class": "corporate-person-role"}, {"doc_id": "5bc9602f-c916-11e9-9f94-b831b5755f6c", "person": "Paula-Mahone", "question_class": "lawyer-role"}, {"doc_id": "5bc9602f-c916-11e9-9f94-b831b5755f6c", "person": "Paula-Mahone", "question_class": "ngo-person-role"}, {"doc_id": "5bc9602f-c916-11e9-9f94-b831b5755f6c", "person": "Paula-Mahone", "question_class": "stance", "label": "informational"}, {"doc_id": "5bc9602f-c916-11e9-9f94-b831b5755f6c", "person": "Jennifer-A.-McCrickerd", "question_class": "error", "label": "legit"}, {"doc_id": "5bc9602f-c916-11e9-9f94-b831b5755f6c", "person": "Jennifer-A.-McCrickerd", "question_class": "affiliation", "label": "academic"}, {"doc_id": "5bc9602f-c916-11e9-9f94-b831b5755f6c", "person": "Jennifer-A.-McCrickerd", "question_class": "gov-branch"}, {"doc_id": "5bc9602f-c916-11e9-9f94-b831b5755f6c", "person": "Jennifer-A.-McCrickerd", "question_class": "gov-person-role"}, {"doc_id": "5bc9602f-c916-11e9-9f94-b831b5755f6c", "person": "Jennifer-A.-McCrickerd", "question_class": "victim-person-role"}, {"doc_id": "5bc9602f-c916-11e9-9f94-b831b5755f6c", "person": "Jennifer-A.-McCrickerd", "question_class": "academic-person-role", "label": "other"}, {"doc_id": "5bc9602f-c916-11e9-9f94-b831b5755f6c", "person": "Jennifer-A.-McCrickerd", "question_class": "witness-person-role"}, {"doc_id": "5bc9602f-c916-11e9-9f94-b831b5755f6c", "person": "Jennifer-A.-McCrickerd", "question_class": "actor-affiliation-type"}, {"doc_id": "5bc9602f-c916-11e9-9f94-b831b5755f6c", "person": "Jennifer-A.-McCrickerd", "question_class": "actor-individual-person-role"}, {"doc_id": "5bc9602f-c916-11e9-9f94-b831b5755f6c", "person": "Jennifer-A.-McCrickerd", "question_class": "actor-group-person-role"}, {"doc_id": "5bc9602f-c916-11e9-9f94-b831b5755f6c", "person": "Jennifer-A.-McCrickerd", "question_class": "corporate-person-role"}, {"doc_id": "5bc9602f-c916-11e9-9f94-b831b5755f6c", "person": "Jennifer-A.-McCrickerd", "question_class": "lawyer-role"}, {"doc_id": "5bc9602f-c916-11e9-9f94-b831b5755f6c", "person": "Jennifer-A.-McCrickerd", "question_class": "ngo-person-role"}, {"doc_id": "5bc9602f-c916-11e9-9f94-b831b5755f6c", "person": "Jennifer-A.-McCrickerd", "question_class": "stance", "label": "informational"}, {"doc_id": "5bc9602f-c916-11e9-9f94-b831b5755f6c", "person": "Karen-Drake", "question_class": "error", "label": "legit"}, {"doc_id": "5bc9602f-c916-11e9-9f94-b831b5755f6c", "person": "Karen-Drake", "question_class": "affiliation", "label": "actor"}, {"doc_id": "5bc9602f-c916-11e9-9f94-b831b5755f6c", "person": "Karen-Drake", "question_class": "gov-branch"}, {"doc_id": "5bc9602f-c916-11e9-9f94-b831b5755f6c", "person": "Karen-Drake", "question_class": "gov-person-role"}, {"doc_id": "5bc9602f-c916-11e9-9f94-b831b5755f6c", "person": "Karen-Drake", "question_class": "victim-person-role"}, {"doc_id": "5bc9602f-c916-11e9-9f94-b831b5755f6c", "person": "Karen-Drake", "question_class": "academic-person-role"}, {"doc_id": "5bc9602f-c916-11e9-9f94-b831b5755f6c", "person": "Karen-Drake", "question_class": "witness-person-role"}, {"doc_id": "5bc9602f-c916-11e9-9f94-b831b5755f6c", "person": "Karen-Drake", "question_class": "actor-affiliation-type", "label": "individual"}, {"doc_id": "5bc9602f-c916-11e9-9f94-b831b5755f6c", "person": "Karen-Drake", "question_class": "actor-individual-person-role", "label": "doctor"}, {"doc_id": "5bc9602f-c916-11e9-9f94-b831b5755f6c", "person": "Karen-Drake", "question_class": "actor-group-person-role"}, {"doc_id": "5bc9602f-c916-11e9-9f94-b831b5755f6c", "person": "Karen-Drake", "question_class": "corporate-person-role"}, {"doc_id": "5bc9602f-c916-11e9-9f94-b831b5755f6c", "person": "Karen-Drake", "question_class": "lawyer-role"}, {"doc_id": "5bc9602f-c916-11e9-9f94-b831b5755f6c", "person": "Karen-Drake", "question_class": "ngo-person-role"}, {"doc_id": "5bc9602f-c916-11e9-9f94-b831b5755f6c", "person": "Karen-Drake", "question_class": "stance", "label": "informational"}, {"doc_id": "5bc9602f-c916-11e9-9f94-b831b5755f6c", "person": "Lavern-Thompson", "question_class": "error", "label": "legit"}, {"doc_id": "5bc9602f-c916-11e9-9f94-b831b5755f6c", "person": "Lavern-Thompson", "question_class": "affiliation", "label": "witness"}, {"doc_id": "5bc9602f-c916-11e9-9f94-b831b5755f6c", "person": "Lavern-Thompson", "question_class": "gov-branch"}, {"doc_id": "5bc9602f-c916-11e9-9f94-b831b5755f6c", "person": "Lavern-Thompson", "question_class": "gov-person-role"}, {"doc_id": "5bc9602f-c916-11e9-9f94-b831b5755f6c", "person": "Lavern-Thompson", "question_class": "victim-person-role"}, {"doc_id": "5bc9602f-c916-11e9-9f94-b831b5755f6c", "person": "Lavern-Thompson", "question_class": "academic-person-role"}, {"doc_id": "5bc9602f-c916-11e9-9f94-b831b5755f6c", "person": "Lavern-Thompson", "question_class": "witness-person-role", "label": "casual"}, {"doc_id": "5bc9602f-c916-11e9-9f94-b831b5755f6c", "person": "Lavern-Thompson", "question_class": "actor-affiliation-type"}, {"doc_id": "5bc9602f-c916-11e9-9f94-b831b5755f6c", "person": "Lavern-Thompson", "question_class": "actor-individual-person-role"}, {"doc_id": "5bc9602f-c916-11e9-9f94-b831b5755f6c", "person": "Lavern-Thompson", "question_class": "actor-group-person-role"}, {"doc_id": "5bc9602f-c916-11e9-9f94-b831b5755f6c", "person": "Lavern-Thompson", "question_class": "corporate-person-role"}, {"doc_id": "5bc9602f-c916-11e9-9f94-b831b5755f6c", "person": "Lavern-Thompson", "question_class": "lawyer-role"}, {"doc_id": "5bc9602f-c916-11e9-9f94-b831b5755f6c", "person": "Lavern-Thompson", "question_class": "ngo-person-role"}, {"doc_id": "5bc9602f-c916-11e9-9f94-b831b5755f6c", "person": "Lavern-Thompson", "question_class": "stance", "label": "informational"}, {"doc_id": "7e24cec9-c916-11e9-9dd9-b831b5755f6c", "person": "Steven-C.-Lember", "question_class": "error", "label": "legit"}, {"doc_id": "7e24cec9-c916-11e9-9dd9-b831b5755f6c", "person": "Steven-C.-Lember", "question_class": "affiliation", "label": "government"}, {"doc_id": "7e24cec9-c916-11e9-9dd9-b831b5755f6c", "person": "Steven-C.-Lember", "question_class": "gov-branch", "label": "executive"}, {"doc_id": "7e24cec9-c916-11e9-9dd9-b831b5755f6c", "person": "Steven-C.-Lember", "question_class": "gov-person-role", "label": "lawyer"}, {"doc_id": "7e24cec9-c916-11e9-9dd9-b831b5755f6c", "person": "Steven-C.-Lember", "question_class": "victim-person-role"}, {"doc_id": "7e24cec9-c916-11e9-9dd9-b831b5755f6c", "person": "Steven-C.-Lember", "question_class": "academic-person-role"}, {"doc_id": "7e24cec9-c916-11e9-9dd9-b831b5755f6c", "person": "Steven-C.-Lember", "question_class": "witness-person-role"}, {"doc_id": "7e24cec9-c916-11e9-9dd9-b831b5755f6c", "person": "Steven-C.-Lember", "question_class": "actor-affiliation-type"}, {"doc_id": "7e24cec9-c916-11e9-9dd9-b831b5755f6c", "person": "Steven-C.-Lember", "question_class": "actor-individual-person-role"}, {"doc_id": "7e24cec9-c916-11e9-9dd9-b831b5755f6c", "person": "Steven-C.-Lember", "question_class": "actor-group-person-role"}, {"doc_id": "7e24cec9-c916-11e9-9dd9-b831b5755f6c", "person": "Steven-C.-Lember", "question_class": "corporate-person-role"}, {"doc_id": "7e24cec9-c916-11e9-9dd9-b831b5755f6c", "person": "Steven-C.-Lember", "question_class": "lawyer-role", "label": "prosecutor"}, {"doc_id": "7e24cec9-c916-11e9-9dd9-b831b5755f6c", "person": "Steven-C.-Lember", "question_class": "ngo-person-role"}, {"doc_id": "7e24cec9-c916-11e9-9dd9-b831b5755f6c", "person": "Steven-C.-Lember", "question_class": "stance"}, {"doc_id": "7e24cec9-c916-11e9-9dd9-b831b5755f6c", "person": "Costas-Christofi", "question_class": "error", "label": "badentity"}, {"doc_id": "7e24cec9-c916-11e9-9dd9-b831b5755f6c", "person": "Costas-Christofi", "question_class": "affiliation"}, {"doc_id": "7e24cec9-c916-11e9-9dd9-b831b5755f6c", "person": "Costas-Christofi", "question_class": "gov-branch"}, {"doc_id": "7e24cec9-c916-11e9-9dd9-b831b5755f6c", "person": "Costas-Christofi", "question_class": "gov-person-role"}, {"doc_id": "7e24cec9-c916-11e9-9dd9-b831b5755f6c", "person": "Costas-Christofi", "question_class": "victim-person-role", "label": "individual"}, {"doc_id": "7e24cec9-c916-11e9-9dd9-b831b5755f6c", "person": "Costas-Christofi", "question_class": "academic-person-role", "label": "decision-maker"}, {"doc_id": "7e24cec9-c916-11e9-9dd9-b831b5755f6c", "person": "Costas-Christofi", "question_class": "witness-person-role", "label": "casual"}, {"doc_id": "7e24cec9-c916-11e9-9dd9-b831b5755f6c", "person": "Costas-Christofi", "question_class": "actor-affiliation-type", "label": "individual"}, {"doc_id": "7e24cec9-c916-11e9-9dd9-b831b5755f6c", "person": "Costas-Christofi", "question_class": "actor-individual-person-role", "label": "individual"}, {"doc_id": "7e24cec9-c916-11e9-9dd9-b831b5755f6c", "person": "Costas-Christofi", "question_class": "actor-group-person-role", "label": "leader"}, {"doc_id": "7e24cec9-c916-11e9-9dd9-b831b5755f6c", "person": "Costas-Christofi", "question_class": "corporate-person-role"}, {"doc_id": "7e24cec9-c916-11e9-9dd9-b831b5755f6c", "person": "Costas-Christofi", "question_class": "lawyer-role"}, {"doc_id": "7e24cec9-c916-11e9-9dd9-b831b5755f6c", "person": "Costas-Christofi", "question_class": "ngo-person-role"}, {"doc_id": "7e24cec9-c916-11e9-9dd9-b831b5755f6c", "person": "Costas-Christofi", "question_class": "stance"}, {"doc_id": "7e24cec9-c916-11e9-9dd9-b831b5755f6c", "person": "Cameron-Blanchard", "question_class": "error", "label": "legit"}, {"doc_id": "7e24cec9-c916-11e9-9dd9-b831b5755f6c", "person": "Cameron-Blanchard", "question_class": "affiliation", "label": "corporate"}, {"doc_id": "7e24cec9-c916-11e9-9dd9-b831b5755f6c", "person": "Cameron-Blanchard", "question_class": "gov-branch"}, {"doc_id": "7e24cec9-c916-11e9-9dd9-b831b5755f6c", "person": "Cameron-Blanchard", "question_class": "gov-person-role"}, {"doc_id": "7e24cec9-c916-11e9-9dd9-b831b5755f6c", "person": "Cameron-Blanchard", "question_class": "victim-person-role"}, {"doc_id": "7e24cec9-c916-11e9-9dd9-b831b5755f6c", "person": "Cameron-Blanchard", "question_class": "academic-person-role"}, {"doc_id": "7e24cec9-c916-11e9-9dd9-b831b5755f6c", "person": "Cameron-Blanchard", "question_class": "witness-person-role"}, {"doc_id": "7e24cec9-c916-11e9-9dd9-b831b5755f6c", "person": "Cameron-Blanchard", "question_class": "actor-affiliation-type"}, {"doc_id": "7e24cec9-c916-11e9-9dd9-b831b5755f6c", "person": "Cameron-Blanchard", "question_class": "actor-individual-person-role"}, {"doc_id": "7e24cec9-c916-11e9-9dd9-b831b5755f6c", "person": "Cameron-Blanchard", "question_class": "actor-group-person-role"}, {"doc_id": "7e24cec9-c916-11e9-9dd9-b831b5755f6c", "person": "Cameron-Blanchard", "question_class": "corporate-person-role", "label": "spokesman"}, {"doc_id": "7e24cec9-c916-11e9-9dd9-b831b5755f6c", "person": "Cameron-Blanchard", "question_class": "lawyer-role"}, {"doc_id": "7e24cec9-c916-11e9-9dd9-b831b5755f6c", "person": "Cameron-Blanchard", "question_class": "ngo-person-role"}, {"doc_id": "7e24cec9-c916-11e9-9dd9-b831b5755f6c", "person": "Cameron-Blanchard", "question_class": "stance", "label": "informational"}, {"doc_id": "7e24cec9-c916-11e9-9dd9-b831b5755f6c", "person": "John-Fahy", "question_class": "error", "label": "legit"}, {"doc_id": "7e24cec9-c916-11e9-9dd9-b831b5755f6c", "person": "John-Fahy", "question_class": "affiliation", "label": "government"}, {"doc_id": "7e24cec9-c916-11e9-9dd9-b831b5755f6c", "person": "John-Fahy", "question_class": "gov-branch", "label": "executive"}, {"doc_id": "7e24cec9-c916-11e9-9dd9-b831b5755f6c", "person": "John-Fahy", "question_class": "gov-person-role", "label": "lawyer"}, {"doc_id": "7e24cec9-c916-11e9-9dd9-b831b5755f6c", "person": "John-Fahy", "question_class": "victim-person-role"}, {"doc_id": "7e24cec9-c916-11e9-9dd9-b831b5755f6c", "person": "John-Fahy", "question_class": "academic-person-role"}, {"doc_id": "7e24cec9-c916-11e9-9dd9-b831b5755f6c", "person": "John-Fahy", "question_class": "witness-person-role"}, {"doc_id": "7e24cec9-c916-11e9-9dd9-b831b5755f6c", "person": "John-Fahy", "question_class": "actor-affiliation-type"}, {"doc_id": "7e24cec9-c916-11e9-9dd9-b831b5755f6c", "person": "John-Fahy", "question_class": "actor-individual-person-role"}, {"doc_id": "7e24cec9-c916-11e9-9dd9-b831b5755f6c", "person": "John-Fahy", "question_class": "actor-group-person-role"}, {"doc_id": "7e24cec9-c916-11e9-9dd9-b831b5755f6c", "person": "John-Fahy", "question_class": "corporate-person-role"}, {"doc_id": "7e24cec9-c916-11e9-9dd9-b831b5755f6c", "person": "John-Fahy", "question_class": "lawyer-role", "label": "prosecutor"}, {"doc_id": "7e24cec9-c916-11e9-9dd9-b831b5755f6c", "person": "John-Fahy", "question_class": "ngo-person-role"}, {"doc_id": "7e24cec9-c916-11e9-9dd9-b831b5755f6c", "person": "John-Fahy", "question_class": "stance"}, {"doc_id": "7e24cec9-c916-11e9-9dd9-b831b5755f6c", "person": "Chris-Adams", "question_class": "error", "label": "legit"}, {"doc_id": "7e24cec9-c916-11e9-9dd9-b831b5755f6c", "person": "Chris-Adams", "question_class": "affiliation", "label": "victim"}, {"doc_id": "7e24cec9-c916-11e9-9dd9-b831b5755f6c", "person": "Chris-Adams", "question_class": "gov-branch"}, {"doc_id": "7e24cec9-c916-11e9-9dd9-b831b5755f6c", "person": "Chris-Adams", "question_class": "gov-person-role"}, {"doc_id": "7e24cec9-c916-11e9-9dd9-b831b5755f6c", "person": "Chris-Adams", "question_class": "victim-person-role", "label": "relative"}, {"doc_id": "7e24cec9-c916-11e9-9dd9-b831b5755f6c", "person": "Chris-Adams", "question_class": "academic-person-role"}, {"doc_id": "7e24cec9-c916-11e9-9dd9-b831b5755f6c", "person": "Chris-Adams", "question_class": "witness-person-role"}, {"doc_id": "7e24cec9-c916-11e9-9dd9-b831b5755f6c", "person": "Chris-Adams", "question_class": "actor-affiliation-type"}, {"doc_id": "7e24cec9-c916-11e9-9dd9-b831b5755f6c", "person": "Chris-Adams", "question_class": "actor-individual-person-role"}, {"doc_id": "7e24cec9-c916-11e9-9dd9-b831b5755f6c", "person": "Chris-Adams", "question_class": "actor-group-person-role"}, {"doc_id": "7e24cec9-c916-11e9-9dd9-b831b5755f6c", "person": "Chris-Adams", "question_class": "corporate-person-role"}, {"doc_id": "7e24cec9-c916-11e9-9dd9-b831b5755f6c", "person": "Chris-Adams", "question_class": "lawyer-role"}, {"doc_id": "7e24cec9-c916-11e9-9dd9-b831b5755f6c", "person": "Chris-Adams", "question_class": "ngo-person-role"}, {"doc_id": "7e24cec9-c916-11e9-9dd9-b831b5755f6c", "person": "Chris-Adams", "question_class": "stance", "label": "informational"}, {"doc_id": "5bc9ae92-c916-11e9-bd22-b831b5755f6c", "person": "Clinton", "question_class": "error", "label": "legit"}, {"doc_id": "5bc9ae92-c916-11e9-bd22-b831b5755f6c", "person": "Clinton", "question_class": "affiliation", "label": "government"}, {"doc_id": "5bc9ae92-c916-11e9-bd22-b831b5755f6c", "person": "Clinton", "question_class": "gov-branch", "label": "executive"}, {"doc_id": "5bc9ae92-c916-11e9-bd22-b831b5755f6c", "person": "Clinton", "question_class": "gov-person-role", "label": "decision-maker"}, {"doc_id": "5bc9ae92-c916-11e9-bd22-b831b5755f6c", "person": "Clinton", "question_class": "victim-person-role"}, {"doc_id": "5bc9ae92-c916-11e9-bd22-b831b5755f6c", "person": "Clinton", "question_class": "academic-person-role"}, {"doc_id": "5bc9ae92-c916-11e9-bd22-b831b5755f6c", "person": "Clinton", "question_class": "witness-person-role"}, {"doc_id": "5bc9ae92-c916-11e9-bd22-b831b5755f6c", "person": "Clinton", "question_class": "actor-affiliation-type"}, {"doc_id": "5bc9ae92-c916-11e9-bd22-b831b5755f6c", "person": "Clinton", "question_class": "actor-individual-person-role"}, {"doc_id": "5bc9ae92-c916-11e9-bd22-b831b5755f6c", "person": "Clinton", "question_class": "actor-group-person-role"}, {"doc_id": "5bc9ae92-c916-11e9-bd22-b831b5755f6c", "person": "Clinton", "question_class": "corporate-person-role"}, {"doc_id": "5bc9ae92-c916-11e9-bd22-b831b5755f6c", "person": "Clinton", "question_class": "lawyer-role"}, {"doc_id": "5bc9ae92-c916-11e9-bd22-b831b5755f6c", "person": "Clinton", "question_class": "ngo-person-role"}, {"doc_id": "5bc9ae92-c916-11e9-bd22-b831b5755f6c", "person": "Clinton", "question_class": "stance", "label": "supporting"}, {"doc_id": "5bc9ae92-c916-11e9-bd22-b831b5755f6c", "person": "Samuel-Berger", "question_class": "error", "label": "legit"}, {"doc_id": "5bc9ae92-c916-11e9-bd22-b831b5755f6c", "person": "Samuel-Berger", "question_class": "affiliation", "label": "government"}, {"doc_id": "5bc9ae92-c916-11e9-bd22-b831b5755f6c", "person": "Samuel-Berger", "question_class": "gov-branch", "label": "executive"}, {"doc_id": "5bc9ae92-c916-11e9-bd22-b831b5755f6c", "person": "Samuel-Berger", "question_class": "gov-person-role", "label": "advisor"}, {"doc_id": "5bc9ae92-c916-11e9-bd22-b831b5755f6c", "person": "Samuel-Berger", "question_class": "victim-person-role"}, {"doc_id": "5bc9ae92-c916-11e9-bd22-b831b5755f6c", "person": "Samuel-Berger", "question_class": "academic-person-role"}, {"doc_id": "5bc9ae92-c916-11e9-bd22-b831b5755f6c", "person": "Samuel-Berger", "question_class": "witness-person-role"}, {"doc_id": "5bc9ae92-c916-11e9-bd22-b831b5755f6c", "person": "Samuel-Berger", "question_class": "actor-affiliation-type"}, {"doc_id": "5bc9ae92-c916-11e9-bd22-b831b5755f6c", "person": "Samuel-Berger", "question_class": "actor-individual-person-role"}, {"doc_id": "5bc9ae92-c916-11e9-bd22-b831b5755f6c", "person": "Samuel-Berger", "question_class": "actor-group-person-role"}, {"doc_id": "5bc9ae92-c916-11e9-bd22-b831b5755f6c", "person": "Samuel-Berger", "question_class": "corporate-person-role"}, {"doc_id": "5bc9ae92-c916-11e9-bd22-b831b5755f6c", "person": "Samuel-Berger", "question_class": "lawyer-role"}, {"doc_id": "5bc9ae92-c916-11e9-bd22-b831b5755f6c", "person": "Samuel-Berger", "question_class": "ngo-person-role"}, {"doc_id": "5bc9ae92-c916-11e9-bd22-b831b5755f6c", "person": "Samuel-Berger", "question_class": "stance", "label": "opposing"}, {"doc_id": "5bc9ae92-c916-11e9-bd22-b831b5755f6c", "person": "Michael-D.-McCurry", "question_class": "error", "label": "legit"}, {"doc_id": "5bc9ae92-c916-11e9-bd22-b831b5755f6c", "person": "Michael-D.-McCurry", "question_class": "affiliation", "label": "government"}, {"doc_id": "5bc9ae92-c916-11e9-bd22-b831b5755f6c", "person": "Michael-D.-McCurry", "question_class": "gov-branch", "label": "executive"}, {"doc_id": "5bc9ae92-c916-11e9-bd22-b831b5755f6c", "person": "Michael-D.-McCurry", "question_class": "gov-person-role", "label": "spokesman"}, {"doc_id": "5bc9ae92-c916-11e9-bd22-b831b5755f6c", "person": "Michael-D.-McCurry", "question_class": "victim-person-role"}, {"doc_id": "5bc9ae92-c916-11e9-bd22-b831b5755f6c", "person": "Michael-D.-McCurry", "question_class": "academic-person-role"}, {"doc_id": "5bc9ae92-c916-11e9-bd22-b831b5755f6c", "person": "Michael-D.-McCurry", "question_class": "witness-person-role"}, {"doc_id": "5bc9ae92-c916-11e9-bd22-b831b5755f6c", "person": "Michael-D.-McCurry", "question_class": "actor-affiliation-type"}, {"doc_id": "5bc9ae92-c916-11e9-bd22-b831b5755f6c", "person": "Michael-D.-McCurry", "question_class": "actor-individual-person-role"}, {"doc_id": "5bc9ae92-c916-11e9-bd22-b831b5755f6c", "person": "Michael-D.-McCurry", "question_class": "actor-group-person-role"}, {"doc_id": "5bc9ae92-c916-11e9-bd22-b831b5755f6c", "person": "Michael-D.-McCurry", "question_class": "corporate-person-role"}, {"doc_id": "5bc9ae92-c916-11e9-bd22-b831b5755f6c", "person": "Michael-D.-McCurry", "question_class": "lawyer-role"}, {"doc_id": "5bc9ae92-c916-11e9-bd22-b831b5755f6c", "person": "Michael-D.-McCurry", "question_class": "ngo-person-role"}, {"doc_id": "5bc9ae92-c916-11e9-bd22-b831b5755f6c", "person": "Michael-D.-McCurry", "question_class": "stance", "label": "informational"}, {"doc_id": "1dc5c281-c916-11e9-abc4-b831b5755f6c", "person": "Jim-Wright", "question_class": "error", "label": "legit"}, {"doc_id": "1dc5c281-c916-11e9-abc4-b831b5755f6c", "person": "Jim-Wright", "question_class": "affiliation", "label": "government"}, {"doc_id": "1dc5c281-c916-11e9-abc4-b831b5755f6c", "person": "Jim-Wright", "question_class": "gov-branch", "label": "legislative"}, {"doc_id": "1dc5c281-c916-11e9-abc4-b831b5755f6c", "person": "Jim-Wright", "question_class": "gov-person-role", "label": "decision-maker"}, {"doc_id": "1dc5c281-c916-11e9-abc4-b831b5755f6c", "person": "Jim-Wright", "question_class": "victim-person-role"}, {"doc_id": "1dc5c281-c916-11e9-abc4-b831b5755f6c", "person": "Jim-Wright", "question_class": "academic-person-role"}, {"doc_id": "1dc5c281-c916-11e9-abc4-b831b5755f6c", "person": "Jim-Wright", "question_class": "witness-person-role"}, {"doc_id": "1dc5c281-c916-11e9-abc4-b831b5755f6c", "person": "Jim-Wright", "question_class": "actor-affiliation-type"}, {"doc_id": "1dc5c281-c916-11e9-abc4-b831b5755f6c", "person": "Jim-Wright", "question_class": "actor-individual-person-role"}, {"doc_id": "1dc5c281-c916-11e9-abc4-b831b5755f6c", "person": "Jim-Wright", "question_class": "actor-group-person-role"}, {"doc_id": "1dc5c281-c916-11e9-abc4-b831b5755f6c", "person": "Jim-Wright", "question_class": "corporate-person-role"}, {"doc_id": "1dc5c281-c916-11e9-abc4-b831b5755f6c", "person": "Jim-Wright", "question_class": "lawyer-role"}, {"doc_id": "1dc5c281-c916-11e9-abc4-b831b5755f6c", "person": "Jim-Wright", "question_class": "ngo-person-role"}, {"doc_id": "1dc5c281-c916-11e9-abc4-b831b5755f6c", "person": "Jim-Wright", "question_class": "stance", "label": "supporting"}, {"doc_id": "1dc5c281-c916-11e9-abc4-b831b5755f6c", "person": "Reagan", "question_class": "error", "label": "legit"}, {"doc_id": "1dc5c281-c916-11e9-abc4-b831b5755f6c", "person": "Reagan", "question_class": "affiliation", "label": "government"}, {"doc_id": "1dc5c281-c916-11e9-abc4-b831b5755f6c", "person": "Reagan", "question_class": "gov-branch", "label": "executive"}, {"doc_id": "1dc5c281-c916-11e9-abc4-b831b5755f6c", "person": "Reagan", "question_class": "gov-person-role", "label": "decision-maker"}, {"doc_id": "1dc5c281-c916-11e9-abc4-b831b5755f6c", "person": "Reagan", "question_class": "victim-person-role"}, {"doc_id": "1dc5c281-c916-11e9-abc4-b831b5755f6c", "person": "Reagan", "question_class": "academic-person-role"}, {"doc_id": "1dc5c281-c916-11e9-abc4-b831b5755f6c", "person": "Reagan", "question_class": "witness-person-role"}, {"doc_id": "1dc5c281-c916-11e9-abc4-b831b5755f6c", "person": "Reagan", "question_class": "actor-affiliation-type"}, {"doc_id": "1dc5c281-c916-11e9-abc4-b831b5755f6c", "person": "Reagan", "question_class": "actor-individual-person-role"}, {"doc_id": "1dc5c281-c916-11e9-abc4-b831b5755f6c", "person": "Reagan", "question_class": "actor-group-person-role"}, {"doc_id": "1dc5c281-c916-11e9-abc4-b831b5755f6c", "person": "Reagan", "question_class": "corporate-person-role"}, {"doc_id": "1dc5c281-c916-11e9-abc4-b831b5755f6c", "person": "Reagan", "question_class": "lawyer-role"}, {"doc_id": "1dc5c281-c916-11e9-abc4-b831b5755f6c", "person": "Reagan", "question_class": "ngo-person-role"}, {"doc_id": "1dc5c281-c916-11e9-abc4-b831b5755f6c", "person": "Reagan", "question_class": "stance", "label": "opposing"}, {"doc_id": "1dc5c281-c916-11e9-abc4-b831b5755f6c", "person": "William-H.-Gray-3d", "question_class": "error", "label": "legit"}, {"doc_id": "1dc5c281-c916-11e9-abc4-b831b5755f6c", "person": "William-H.-Gray-3d", "question_class": "affiliation", "label": "government"}, {"doc_id": "1dc5c281-c916-11e9-abc4-b831b5755f6c", "person": "William-H.-Gray-3d", "question_class": "gov-branch", "label": "legislative"}, {"doc_id": "1dc5c281-c916-11e9-abc4-b831b5755f6c", "person": "William-H.-Gray-3d", "question_class": "gov-person-role", "label": "decision-maker"}, {"doc_id": "1dc5c281-c916-11e9-abc4-b831b5755f6c", "person": "William-H.-Gray-3d", "question_class": "victim-person-role"}, {"doc_id": "1dc5c281-c916-11e9-abc4-b831b5755f6c", "person": "William-H.-Gray-3d", "question_class": "academic-person-role"}, {"doc_id": "1dc5c281-c916-11e9-abc4-b831b5755f6c", "person": "William-H.-Gray-3d", "question_class": "witness-person-role"}, {"doc_id": "1dc5c281-c916-11e9-abc4-b831b5755f6c", "person": "William-H.-Gray-3d", "question_class": "actor-affiliation-type"}, {"doc_id": "1dc5c281-c916-11e9-abc4-b831b5755f6c", "person": "William-H.-Gray-3d", "question_class": "actor-individual-person-role"}, {"doc_id": "1dc5c281-c916-11e9-abc4-b831b5755f6c", "person": "William-H.-Gray-3d", "question_class": "actor-group-person-role"}, {"doc_id": "1dc5c281-c916-11e9-abc4-b831b5755f6c", "person": "William-H.-Gray-3d", "question_class": "corporate-person-role"}, {"doc_id": "1dc5c281-c916-11e9-abc4-b831b5755f6c", "person": "William-H.-Gray-3d", "question_class": "lawyer-role"}, {"doc_id": "1dc5c281-c916-11e9-abc4-b831b5755f6c", "person": "William-H.-Gray-3d", "question_class": "ngo-person-role"}, {"doc_id": "1dc5c281-c916-11e9-abc4-b831b5755f6c", "person": "William-H.-Gray-3d", "question_class": "stance", "label": "supporting"}, {"doc_id": "1dc5c281-c916-11e9-abc4-b831b5755f6c", "person": "Gray", "question_class": "error", "label": "legit"}, {"doc_id": "1dc5c281-c916-11e9-abc4-b831b5755f6c", "person": "Gray", "question_class": "affiliation", "label": "government"}, {"doc_id": "1dc5c281-c916-11e9-abc4-b831b5755f6c", "person": "Gray", "question_class": "gov-branch", "label": "legislative"}, {"doc_id": "1dc5c281-c916-11e9-abc4-b831b5755f6c", "person": "Gray", "question_class": "gov-person-role", "label": "decision-maker"}, {"doc_id": "1dc5c281-c916-11e9-abc4-b831b5755f6c", "person": "Gray", "question_class": "victim-person-role"}, {"doc_id": "1dc5c281-c916-11e9-abc4-b831b5755f6c", "person": "Gray", "question_class": "academic-person-role"}, {"doc_id": "1dc5c281-c916-11e9-abc4-b831b5755f6c", "person": "Gray", "question_class": "witness-person-role"}, {"doc_id": "1dc5c281-c916-11e9-abc4-b831b5755f6c", "person": "Gray", "question_class": "actor-affiliation-type"}, {"doc_id": "1dc5c281-c916-11e9-abc4-b831b5755f6c", "person": "Gray", "question_class": "actor-individual-person-role"}, {"doc_id": "1dc5c281-c916-11e9-abc4-b831b5755f6c", "person": "Gray", "question_class": "actor-group-person-role"}, {"doc_id": "1dc5c281-c916-11e9-abc4-b831b5755f6c", "person": "Gray", "question_class": "corporate-person-role"}, {"doc_id": "1dc5c281-c916-11e9-abc4-b831b5755f6c", "person": "Gray", "question_class": "lawyer-role"}, {"doc_id": "1dc5c281-c916-11e9-abc4-b831b5755f6c", "person": "Gray", "question_class": "ngo-person-role"}, {"doc_id": "1dc5c281-c916-11e9-abc4-b831b5755f6c", "person": "Gray", "question_class": "stance", "label": "informational"}, {"doc_id": "1dc4d8b2-c916-11e9-a719-b831b5755f6c", "person": "Reagan", "question_class": "error", "label": "badentity"}, {"doc_id": "1dc4d8b2-c916-11e9-a719-b831b5755f6c", "person": "Reagan", "question_class": "affiliation", "label": "government"}, {"doc_id": "1dc4d8b2-c916-11e9-a719-b831b5755f6c", "person": "Reagan", "question_class": "gov-branch", "label": "executive"}, {"doc_id": "1dc4d8b2-c916-11e9-a719-b831b5755f6c", "person": "Reagan", "question_class": "gov-person-role", "label": "decision-maker"}, {"doc_id": "1dc4d8b2-c916-11e9-a719-b831b5755f6c", "person": "Reagan", "question_class": "victim-person-role"}, {"doc_id": "1dc4d8b2-c916-11e9-a719-b831b5755f6c", "person": "Reagan", "question_class": "academic-person-role"}, {"doc_id": "1dc4d8b2-c916-11e9-a719-b831b5755f6c", "person": "Reagan", "question_class": "witness-person-role"}, {"doc_id": "1dc4d8b2-c916-11e9-a719-b831b5755f6c", "person": "Reagan", "question_class": "actor-affiliation-type"}, {"doc_id": "1dc4d8b2-c916-11e9-a719-b831b5755f6c", "person": "Reagan", "question_class": "actor-individual-person-role"}, {"doc_id": "1dc4d8b2-c916-11e9-a719-b831b5755f6c", "person": "Reagan", "question_class": "actor-group-person-role"}, {"doc_id": "1dc4d8b2-c916-11e9-a719-b831b5755f6c", "person": "Reagan", "question_class": "corporate-person-role"}, {"doc_id": "1dc4d8b2-c916-11e9-a719-b831b5755f6c", "person": "Reagan", "question_class": "lawyer-role"}, {"doc_id": "1dc4d8b2-c916-11e9-a719-b831b5755f6c", "person": "Reagan", "question_class": "ngo-person-role"}, {"doc_id": "1dc4d8b2-c916-11e9-a719-b831b5755f6c", "person": "Reagan", "question_class": "stance", "label": "informational"}, {"doc_id": "1dc4d8b2-c916-11e9-a719-b831b5755f6c", "person": "Paul-Laxalt", "question_class": "error", "label": "legit"}, {"doc_id": "1dc4d8b2-c916-11e9-a719-b831b5755f6c", "person": "Paul-Laxalt", "question_class": "affiliation", "label": "government"}, {"doc_id": "1dc4d8b2-c916-11e9-a719-b831b5755f6c", "person": "Paul-Laxalt", "question_class": "gov-branch", "label": "executive"}, {"doc_id": "1dc4d8b2-c916-11e9-a719-b831b5755f6c", "person": "Paul-Laxalt", "question_class": "gov-person-role", "label": "advisor"}, {"doc_id": "1dc4d8b2-c916-11e9-a719-b831b5755f6c", "person": "Paul-Laxalt", "question_class": "victim-person-role"}, {"doc_id": "1dc4d8b2-c916-11e9-a719-b831b5755f6c", "person": "Paul-Laxalt", "question_class": "academic-person-role"}, {"doc_id": "1dc4d8b2-c916-11e9-a719-b831b5755f6c", "person": "Paul-Laxalt", "question_class": "witness-person-role"}, {"doc_id": "1dc4d8b2-c916-11e9-a719-b831b5755f6c", "person": "Paul-Laxalt", "question_class": "actor-affiliation-type"}, {"doc_id": "1dc4d8b2-c916-11e9-a719-b831b5755f6c", "person": "Paul-Laxalt", "question_class": "actor-individual-person-role"}, {"doc_id": "1dc4d8b2-c916-11e9-a719-b831b5755f6c", "person": "Paul-Laxalt", "question_class": "actor-group-person-role"}, {"doc_id": "1dc4d8b2-c916-11e9-a719-b831b5755f6c", "person": "Paul-Laxalt", "question_class": "corporate-person-role"}, {"doc_id": "1dc4d8b2-c916-11e9-a719-b831b5755f6c", "person": "Paul-Laxalt", "question_class": "lawyer-role"}, {"doc_id": "1dc4d8b2-c916-11e9-a719-b831b5755f6c", "person": "Paul-Laxalt", "question_class": "ngo-person-role"}, {"doc_id": "1dc4d8b2-c916-11e9-a719-b831b5755f6c", "person": "Paul-Laxalt", "question_class": "stance", "label": "informational"}, {"doc_id": "1dc4d8b2-c916-11e9-a719-b831b5755f6c", "person": "Albert-R.-Brashear", "question_class": "error", "label": "legit"}, {"doc_id": "1dc4d8b2-c916-11e9-a719-b831b5755f6c", "person": "Albert-R.-Brashear", "question_class": "affiliation", "label": "government"}, {"doc_id": "1dc4d8b2-c916-11e9-a719-b831b5755f6c", "person": "Albert-R.-Brashear", "question_class": "gov-branch", "label": "executive"}, {"doc_id": "1dc4d8b2-c916-11e9-a719-b831b5755f6c", "person": "Albert-R.-Brashear", "question_class": "gov-person-role", "label": "spokesman"}, {"doc_id": "1dc4d8b2-c916-11e9-a719-b831b5755f6c", "person": "Albert-R.-Brashear", "question_class": "victim-person-role"}, {"doc_id": "1dc4d8b2-c916-11e9-a719-b831b5755f6c", "person": "Albert-R.-Brashear", "question_class": "academic-person-role"}, {"doc_id": "1dc4d8b2-c916-11e9-a719-b831b5755f6c", "person": "Albert-R.-Brashear", "question_class": "witness-person-role"}, {"doc_id": "1dc4d8b2-c916-11e9-a719-b831b5755f6c", "person": "Albert-R.-Brashear", "question_class": "actor-affiliation-type"}, {"doc_id": "1dc4d8b2-c916-11e9-a719-b831b5755f6c", "person": "Albert-R.-Brashear", "question_class": "actor-individual-person-role"}, {"doc_id": "1dc4d8b2-c916-11e9-a719-b831b5755f6c", "person": "Albert-R.-Brashear", "question_class": "actor-group-person-role"}, {"doc_id": "1dc4d8b2-c916-11e9-a719-b831b5755f6c", "person": "Albert-R.-Brashear", "question_class": "corporate-person-role"}, {"doc_id": "1dc4d8b2-c916-11e9-a719-b831b5755f6c", "person": "Albert-R.-Brashear", "question_class": "lawyer-role"}, {"doc_id": "1dc4d8b2-c916-11e9-a719-b831b5755f6c", "person": "Albert-R.-Brashear", "question_class": "ngo-person-role"}, {"doc_id": "1dc4d8b2-c916-11e9-a719-b831b5755f6c", "person": "Albert-R.-Brashear", "question_class": "stance", "label": "supporting"}, {"doc_id": "1dc4d8b2-c916-11e9-a719-b831b5755f6c", "person": "Howard-H.-Baker-Jr.", "question_class": "error", "label": "legit"}, {"doc_id": "1dc4d8b2-c916-11e9-a719-b831b5755f6c", "person": "Howard-H.-Baker-Jr.", "question_class": "affiliation", "label": "government"}, {"doc_id": "1dc4d8b2-c916-11e9-a719-b831b5755f6c", "person": "Howard-H.-Baker-Jr.", "question_class": "gov-branch", "label": "executive"}, {"doc_id": "1dc4d8b2-c916-11e9-a719-b831b5755f6c", "person": "Howard-H.-Baker-Jr.", "question_class": "gov-person-role", "label": "advisor"}, {"doc_id": "1dc4d8b2-c916-11e9-a719-b831b5755f6c", "person": "Howard-H.-Baker-Jr.", "question_class": "victim-person-role"}, {"doc_id": "1dc4d8b2-c916-11e9-a719-b831b5755f6c", "person": "Howard-H.-Baker-Jr.", "question_class": "academic-person-role"}, {"doc_id": "1dc4d8b2-c916-11e9-a719-b831b5755f6c", "person": "Howard-H.-Baker-Jr.", "question_class": "witness-person-role"}, {"doc_id": "1dc4d8b2-c916-11e9-a719-b831b5755f6c", "person": "Howard-H.-Baker-Jr.", "question_class": "actor-affiliation-type"}, {"doc_id": "1dc4d8b2-c916-11e9-a719-b831b5755f6c", "person": "Howard-H.-Baker-Jr.", "question_class": "actor-individual-person-role"}, {"doc_id": "1dc4d8b2-c916-11e9-a719-b831b5755f6c", "person": "Howard-H.-Baker-Jr.", "question_class": "actor-group-person-role"}, {"doc_id": "1dc4d8b2-c916-11e9-a719-b831b5755f6c", "person": "Howard-H.-Baker-Jr.", "question_class": "corporate-person-role"}, {"doc_id": "1dc4d8b2-c916-11e9-a719-b831b5755f6c", "person": "Howard-H.-Baker-Jr.", "question_class": "lawyer-role"}, {"doc_id": "1dc4d8b2-c916-11e9-a719-b831b5755f6c", "person": "Howard-H.-Baker-Jr.", "question_class": "ngo-person-role"}, {"doc_id": "1dc4d8b2-c916-11e9-a719-b831b5755f6c", "person": "Howard-H.-Baker-Jr.", "question_class": "stance", "label": "supporting"}, {"doc_id": "1dc4d8b2-c916-11e9-a719-b831b5755f6c", "person": "William-J.-Casey", "question_class": "error", "label": "badentity"}, {"doc_id": "1dc4d8b2-c916-11e9-a719-b831b5755f6c", "person": "William-J.-Casey", "question_class": "affiliation", "label": "government"}, {"doc_id": "1dc4d8b2-c916-11e9-a719-b831b5755f6c", "person": "William-J.-Casey", "question_class": "gov-branch", "label": "legislative"}, {"doc_id": "1dc4d8b2-c916-11e9-a719-b831b5755f6c", "person": "William-J.-Casey", "question_class": "gov-person-role", "label": "decision-maker"}, {"doc_id": "1dc4d8b2-c916-11e9-a719-b831b5755f6c", "person": "William-J.-Casey", "question_class": "victim-person-role"}, {"doc_id": "1dc4d8b2-c916-11e9-a719-b831b5755f6c", "person": "William-J.-Casey", "question_class": "academic-person-role"}, {"doc_id": "1dc4d8b2-c916-11e9-a719-b831b5755f6c", "person": "William-J.-Casey", "question_class": "witness-person-role"}, {"doc_id": "1dc4d8b2-c916-11e9-a719-b831b5755f6c", "person": "William-J.-Casey", "question_class": "actor-affiliation-type"}, {"doc_id": "1dc4d8b2-c916-11e9-a719-b831b5755f6c", "person": "William-J.-Casey", "question_class": "actor-individual-person-role"}, {"doc_id": "1dc4d8b2-c916-11e9-a719-b831b5755f6c", "person": "William-J.-Casey", "question_class": "actor-group-person-role"}, {"doc_id": "1dc4d8b2-c916-11e9-a719-b831b5755f6c", "person": "William-J.-Casey", "question_class": "corporate-person-role"}, {"doc_id": "1dc4d8b2-c916-11e9-a719-b831b5755f6c", "person": "William-J.-Casey", "question_class": "lawyer-role"}, {"doc_id": "1dc4d8b2-c916-11e9-a719-b831b5755f6c", "person": "William-J.-Casey", "question_class": "ngo-person-role"}, {"doc_id": "1dc4d8b2-c916-11e9-a719-b831b5755f6c", "person": "William-J.-Casey", "question_class": "stance", "label": "informational"}, {"doc_id": "1dc4d8b2-c916-11e9-a719-b831b5755f6c", "person": "Bob-Dole", "question_class": "error", "label": "legit"}, {"doc_id": "1dc4d8b2-c916-11e9-a719-b831b5755f6c", "person": "Bob-Dole", "question_class": "affiliation", "label": "government"}, {"doc_id": "1dc4d8b2-c916-11e9-a719-b831b5755f6c", "person": "Bob-Dole", "question_class": "gov-branch", "label": "legislative"}, {"doc_id": "1dc4d8b2-c916-11e9-a719-b831b5755f6c", "person": "Bob-Dole", "question_class": "gov-person-role", "label": "decision-maker"}, {"doc_id": "1dc4d8b2-c916-11e9-a719-b831b5755f6c", "person": "Bob-Dole", "question_class": "victim-person-role"}, {"doc_id": "1dc4d8b2-c916-11e9-a719-b831b5755f6c", "person": "Bob-Dole", "question_class": "academic-person-role"}, {"doc_id": "1dc4d8b2-c916-11e9-a719-b831b5755f6c", "person": "Bob-Dole", "question_class": "witness-person-role"}, {"doc_id": "1dc4d8b2-c916-11e9-a719-b831b5755f6c", "person": "Bob-Dole", "question_class": "actor-affiliation-type"}, {"doc_id": "1dc4d8b2-c916-11e9-a719-b831b5755f6c", "person": "Bob-Dole", "question_class": "actor-individual-person-role"}, {"doc_id": "1dc4d8b2-c916-11e9-a719-b831b5755f6c", "person": "Bob-Dole", "question_class": "actor-group-person-role"}, {"doc_id": "1dc4d8b2-c916-11e9-a719-b831b5755f6c", "person": "Bob-Dole", "question_class": "corporate-person-role"}, {"doc_id": "1dc4d8b2-c916-11e9-a719-b831b5755f6c", "person": "Bob-Dole", "question_class": "lawyer-role"}, {"doc_id": "1dc4d8b2-c916-11e9-a719-b831b5755f6c", "person": "Bob-Dole", "question_class": "ngo-person-role"}, {"doc_id": "1dc4d8b2-c916-11e9-a719-b831b5755f6c", "person": "Bob-Dole", "question_class": "stance", "label": "informational"}, {"doc_id": "1dc4d8b2-c916-11e9-a719-b831b5755f6c", "person": "Robert-M.-Gates", "question_class": "error", "label": "notsource"}, {"doc_id": "1dc4d8b2-c916-11e9-a719-b831b5755f6c", "person": "Robert-M.-Gates", "question_class": "affiliation"}, {"doc_id": "1dc4d8b2-c916-11e9-a719-b831b5755f6c", "person": "Robert-M.-Gates", "question_class": "gov-branch"}, {"doc_id": "1dc4d8b2-c916-11e9-a719-b831b5755f6c", "person": "Robert-M.-Gates", "question_class": "gov-person-role"}, {"doc_id": "1dc4d8b2-c916-11e9-a719-b831b5755f6c", "person": "Robert-M.-Gates", "question_class": "victim-person-role", "label": "individual"}, {"doc_id": "1dc4d8b2-c916-11e9-a719-b831b5755f6c", "person": "Robert-M.-Gates", "question_class": "academic-person-role", "label": "decision-maker"}, {"doc_id": "1dc4d8b2-c916-11e9-a719-b831b5755f6c", "person": "Robert-M.-Gates", "question_class": "witness-person-role", "label": "casual"}, {"doc_id": "1dc4d8b2-c916-11e9-a719-b831b5755f6c", "person": "Robert-M.-Gates", "question_class": "actor-affiliation-type", "label": "individual"}, {"doc_id": "1dc4d8b2-c916-11e9-a719-b831b5755f6c", "person": "Robert-M.-Gates", "question_class": "actor-individual-person-role", "label": "individual"}, {"doc_id": "1dc4d8b2-c916-11e9-a719-b831b5755f6c", "person": "Robert-M.-Gates", "question_class": "actor-group-person-role", "label": "leader"}, {"doc_id": "1dc4d8b2-c916-11e9-a719-b831b5755f6c", "person": "Robert-M.-Gates", "question_class": "corporate-person-role"}, {"doc_id": "1dc4d8b2-c916-11e9-a719-b831b5755f6c", "person": "Robert-M.-Gates", "question_class": "lawyer-role"}, {"doc_id": "1dc4d8b2-c916-11e9-a719-b831b5755f6c", "person": "Robert-M.-Gates", "question_class": "ngo-person-role"}, {"doc_id": "1dc4d8b2-c916-11e9-a719-b831b5755f6c", "person": "Robert-M.-Gates", "question_class": "stance"}, {"doc_id": "1dc4d8b2-c916-11e9-a719-b831b5755f6c", "person": "Leahy", "question_class": "error", "label": "legit"}, {"doc_id": "1dc4d8b2-c916-11e9-a719-b831b5755f6c", "person": "Leahy", "question_class": "affiliation", "label": "government"}, {"doc_id": "1dc4d8b2-c916-11e9-a719-b831b5755f6c", "person": "Leahy", "question_class": "gov-branch", "label": "legislative"}, {"doc_id": "1dc4d8b2-c916-11e9-a719-b831b5755f6c", "person": "Leahy", "question_class": "gov-person-role", "label": "decision-maker"}, {"doc_id": "1dc4d8b2-c916-11e9-a719-b831b5755f6c", "person": "Leahy", "question_class": "victim-person-role"}, {"doc_id": "1dc4d8b2-c916-11e9-a719-b831b5755f6c", "person": "Leahy", "question_class": "academic-person-role"}, {"doc_id": "1dc4d8b2-c916-11e9-a719-b831b5755f6c", "person": "Leahy", "question_class": "witness-person-role"}, {"doc_id": "1dc4d8b2-c916-11e9-a719-b831b5755f6c", "person": "Leahy", "question_class": "actor-affiliation-type"}, {"doc_id": "1dc4d8b2-c916-11e9-a719-b831b5755f6c", "person": "Leahy", "question_class": "actor-individual-person-role"}, {"doc_id": "1dc4d8b2-c916-11e9-a719-b831b5755f6c", "person": "Leahy", "question_class": "actor-group-person-role"}, {"doc_id": "1dc4d8b2-c916-11e9-a719-b831b5755f6c", "person": "Leahy", "question_class": "corporate-person-role"}, {"doc_id": "1dc4d8b2-c916-11e9-a719-b831b5755f6c", "person": "Leahy", "question_class": "lawyer-role"}, {"doc_id": "1dc4d8b2-c916-11e9-a719-b831b5755f6c", "person": "Leahy", "question_class": "ngo-person-role"}, {"doc_id": "1dc4d8b2-c916-11e9-a719-b831b5755f6c", "person": "Leahy", "question_class": "stance", "label": "informational"}, {"doc_id": "1dc4d8b2-c916-11e9-a719-b831b5755f6c", "person": "Kathy-Pherson", "question_class": "error", "label": "legit"}, {"doc_id": "1dc4d8b2-c916-11e9-a719-b831b5755f6c", "person": "Kathy-Pherson", "question_class": "affiliation", "label": "government"}, {"doc_id": "1dc4d8b2-c916-11e9-a719-b831b5755f6c", "person": "Kathy-Pherson", "question_class": "gov-branch", "label": "executive"}, {"doc_id": "1dc4d8b2-c916-11e9-a719-b831b5755f6c", "person": "Kathy-Pherson", "question_class": "gov-person-role", "label": "spokesman"}, {"doc_id": "1dc4d8b2-c916-11e9-a719-b831b5755f6c", "person": "Kathy-Pherson", "question_class": "victim-person-role"}, {"doc_id": "1dc4d8b2-c916-11e9-a719-b831b5755f6c", "person": "Kathy-Pherson", "question_class": "academic-person-role"}, {"doc_id": "1dc4d8b2-c916-11e9-a719-b831b5755f6c", "person": "Kathy-Pherson", "question_class": "witness-person-role"}, {"doc_id": "1dc4d8b2-c916-11e9-a719-b831b5755f6c", "person": "Kathy-Pherson", "question_class": "actor-affiliation-type"}, {"doc_id": "1dc4d8b2-c916-11e9-a719-b831b5755f6c", "person": "Kathy-Pherson", "question_class": "actor-individual-person-role"}, {"doc_id": "1dc4d8b2-c916-11e9-a719-b831b5755f6c", "person": "Kathy-Pherson", "question_class": "actor-group-person-role"}, {"doc_id": "1dc4d8b2-c916-11e9-a719-b831b5755f6c", "person": "Kathy-Pherson", "question_class": "corporate-person-role"}, {"doc_id": "1dc4d8b2-c916-11e9-a719-b831b5755f6c", "person": "Kathy-Pherson", "question_class": "lawyer-role"}, {"doc_id": "1dc4d8b2-c916-11e9-a719-b831b5755f6c", "person": "Kathy-Pherson", "question_class": "ngo-person-role"}, {"doc_id": "1dc4d8b2-c916-11e9-a719-b831b5755f6c", "person": "Kathy-Pherson", "question_class": "stance", "label": "informational"}, {"doc_id": "1dc4d8b2-c916-11e9-a719-b831b5755f6c", "person": "Byrd", "question_class": "error", "label": "legit"}, {"doc_id": "1dc4d8b2-c916-11e9-a719-b831b5755f6c", "person": "Byrd", "question_class": "affiliation", "label": "government"}, {"doc_id": "1dc4d8b2-c916-11e9-a719-b831b5755f6c", "person": "Byrd", "question_class": "gov-branch", "label": "legislative"}, {"doc_id": "1dc4d8b2-c916-11e9-a719-b831b5755f6c", "person": "Byrd", "question_class": "gov-person-role", "label": "decision-maker"}, {"doc_id": "1dc4d8b2-c916-11e9-a719-b831b5755f6c", "person": "Byrd", "question_class": "victim-person-role"}, {"doc_id": "1dc4d8b2-c916-11e9-a719-b831b5755f6c", "person": "Byrd", "question_class": "academic-person-role"}, {"doc_id": "1dc4d8b2-c916-11e9-a719-b831b5755f6c", "person": "Byrd", "question_class": "witness-person-role"}, {"doc_id": "1dc4d8b2-c916-11e9-a719-b831b5755f6c", "person": "Byrd", "question_class": "actor-affiliation-type"}, {"doc_id": "1dc4d8b2-c916-11e9-a719-b831b5755f6c", "person": "Byrd", "question_class": "actor-individual-person-role"}, {"doc_id": "1dc4d8b2-c916-11e9-a719-b831b5755f6c", "person": "Byrd", "question_class": "actor-group-person-role"}, {"doc_id": "1dc4d8b2-c916-11e9-a719-b831b5755f6c", "person": "Byrd", "question_class": "corporate-person-role"}, {"doc_id": "1dc4d8b2-c916-11e9-a719-b831b5755f6c", "person": "Byrd", "question_class": "lawyer-role"}, {"doc_id": "1dc4d8b2-c916-11e9-a719-b831b5755f6c", "person": "Byrd", "question_class": "ngo-person-role"}, {"doc_id": "1dc4d8b2-c916-11e9-a719-b831b5755f6c", "person": "Byrd", "question_class": "stance", "label": "supporting"}, {"doc_id": "1dc4d8b2-c916-11e9-a719-b831b5755f6c", "person": "Alan-Cranston", "question_class": "error", "label": "legit"}, {"doc_id": "1dc4d8b2-c916-11e9-a719-b831b5755f6c", "person": "Alan-Cranston", "question_class": "affiliation", "label": "government"}, {"doc_id": "1dc4d8b2-c916-11e9-a719-b831b5755f6c", "person": "Alan-Cranston", "question_class": "gov-branch", "label": "legislative"}, {"doc_id": "1dc4d8b2-c916-11e9-a719-b831b5755f6c", "person": "Alan-Cranston", "question_class": "gov-person-role", "label": "decision-maker"}, {"doc_id": "1dc4d8b2-c916-11e9-a719-b831b5755f6c", "person": "Alan-Cranston", "question_class": "victim-person-role"}, {"doc_id": "1dc4d8b2-c916-11e9-a719-b831b5755f6c", "person": "Alan-Cranston", "question_class": "academic-person-role"}, {"doc_id": "1dc4d8b2-c916-11e9-a719-b831b5755f6c", "person": "Alan-Cranston", "question_class": "witness-person-role"}, {"doc_id": "1dc4d8b2-c916-11e9-a719-b831b5755f6c", "person": "Alan-Cranston", "question_class": "actor-affiliation-type"}, {"doc_id": "1dc4d8b2-c916-11e9-a719-b831b5755f6c", "person": "Alan-Cranston", "question_class": "actor-individual-person-role"}, {"doc_id": "1dc4d8b2-c916-11e9-a719-b831b5755f6c", "person": "Alan-Cranston", "question_class": "actor-group-person-role"}, {"doc_id": "1dc4d8b2-c916-11e9-a719-b831b5755f6c", "person": "Alan-Cranston", "question_class": "corporate-person-role"}, {"doc_id": "1dc4d8b2-c916-11e9-a719-b831b5755f6c", "person": "Alan-Cranston", "question_class": "lawyer-role"}, {"doc_id": "1dc4d8b2-c916-11e9-a719-b831b5755f6c", "person": "Alan-Cranston", "question_class": "ngo-person-role"}, {"doc_id": "1dc4d8b2-c916-11e9-a719-b831b5755f6c", "person": "Alan-Cranston", "question_class": "stance", "label": "opposing"}, {"doc_id": "1dc4d8b2-c916-11e9-a719-b831b5755f6c", "person": "Tom-Griscom", "question_class": "error", "label": "legit"}, {"doc_id": "1dc4d8b2-c916-11e9-a719-b831b5755f6c", "person": "Tom-Griscom", "question_class": "affiliation", "label": "government"}, {"doc_id": "1dc4d8b2-c916-11e9-a719-b831b5755f6c", "person": "Tom-Griscom", "question_class": "gov-branch", "label": "legislative"}, {"doc_id": "1dc4d8b2-c916-11e9-a719-b831b5755f6c", "person": "Tom-Griscom", "question_class": "gov-person-role", "label": "spokesman"}, {"doc_id": "1dc4d8b2-c916-11e9-a719-b831b5755f6c", "person": "Tom-Griscom", "question_class": "victim-person-role"}, {"doc_id": "1dc4d8b2-c916-11e9-a719-b831b5755f6c", "person": "Tom-Griscom", "question_class": "academic-person-role"}, {"doc_id": "1dc4d8b2-c916-11e9-a719-b831b5755f6c", "person": "Tom-Griscom", "question_class": "witness-person-role"}, {"doc_id": "1dc4d8b2-c916-11e9-a719-b831b5755f6c", "person": "Tom-Griscom", "question_class": "actor-affiliation-type"}, {"doc_id": "1dc4d8b2-c916-11e9-a719-b831b5755f6c", "person": "Tom-Griscom", "question_class": "actor-individual-person-role"}, {"doc_id": "1dc4d8b2-c916-11e9-a719-b831b5755f6c", "person": "Tom-Griscom", "question_class": "actor-group-person-role"}, {"doc_id": "1dc4d8b2-c916-11e9-a719-b831b5755f6c", "person": "Tom-Griscom", "question_class": "corporate-person-role"}, {"doc_id": "1dc4d8b2-c916-11e9-a719-b831b5755f6c", "person": "Tom-Griscom", "question_class": "lawyer-role"}, {"doc_id": "1dc4d8b2-c916-11e9-a719-b831b5755f6c", "person": "Tom-Griscom", "question_class": "ngo-person-role"}, {"doc_id": "1dc4d8b2-c916-11e9-a719-b831b5755f6c", "person": "Tom-Griscom", "question_class": "stance", "label": "informational"}, {"doc_id": "1dc4d8b2-c916-11e9-a719-b831b5755f6c", "person": "Dick-Cheney", "question_class": "error", "label": "badentity"}, {"doc_id": "1dc4d8b2-c916-11e9-a719-b831b5755f6c", "person": "Dick-Cheney", "question_class": "affiliation", "label": "government"}, {"doc_id": "1dc4d8b2-c916-11e9-a719-b831b5755f6c", "person": "Dick-Cheney", "question_class": "gov-branch", "label": "legislative"}, {"doc_id": "1dc4d8b2-c916-11e9-a719-b831b5755f6c", "person": "Dick-Cheney", "question_class": "gov-person-role", "label": "decision-maker"}, {"doc_id": "1dc4d8b2-c916-11e9-a719-b831b5755f6c", "person": "Dick-Cheney", "question_class": "victim-person-role"}, {"doc_id": "1dc4d8b2-c916-11e9-a719-b831b5755f6c", "person": "Dick-Cheney", "question_class": "academic-person-role"}, {"doc_id": "1dc4d8b2-c916-11e9-a719-b831b5755f6c", "person": "Dick-Cheney", "question_class": "witness-person-role"}, {"doc_id": "1dc4d8b2-c916-11e9-a719-b831b5755f6c", "person": "Dick-Cheney", "question_class": "actor-affiliation-type"}, {"doc_id": "1dc4d8b2-c916-11e9-a719-b831b5755f6c", "person": "Dick-Cheney", "question_class": "actor-individual-person-role"}, {"doc_id": "1dc4d8b2-c916-11e9-a719-b831b5755f6c", "person": "Dick-Cheney", "question_class": "actor-group-person-role"}, {"doc_id": "1dc4d8b2-c916-11e9-a719-b831b5755f6c", "person": "Dick-Cheney", "question_class": "corporate-person-role"}, {"doc_id": "1dc4d8b2-c916-11e9-a719-b831b5755f6c", "person": "Dick-Cheney", "question_class": "lawyer-role"}, {"doc_id": "1dc4d8b2-c916-11e9-a719-b831b5755f6c", "person": "Dick-Cheney", "question_class": "ngo-person-role"}, {"doc_id": "1dc4d8b2-c916-11e9-a719-b831b5755f6c", "person": "Dick-Cheney", "question_class": "stance", "label": "supporting"}, {"doc_id": "1dc4d8b2-c916-11e9-a719-b831b5755f6c", "person": "Edmund-S.-Muskie", "question_class": "error", "label": "legit"}, {"doc_id": "1dc4d8b2-c916-11e9-a719-b831b5755f6c", "person": "Edmund-S.-Muskie", "question_class": "affiliation", "label": "government"}, {"doc_id": "1dc4d8b2-c916-11e9-a719-b831b5755f6c", "person": "Edmund-S.-Muskie", "question_class": "gov-branch", "label": "legislative"}, {"doc_id": "1dc4d8b2-c916-11e9-a719-b831b5755f6c", "person": "Edmund-S.-Muskie", "question_class": "gov-person-role", "label": "decision-maker"}, {"doc_id": "1dc4d8b2-c916-11e9-a719-b831b5755f6c", "person": "Edmund-S.-Muskie", "question_class": "victim-person-role"}, {"doc_id": "1dc4d8b2-c916-11e9-a719-b831b5755f6c", "person": "Edmund-S.-Muskie", "question_class": "academic-person-role"}, {"doc_id": "1dc4d8b2-c916-11e9-a719-b831b5755f6c", "person": "Edmund-S.-Muskie", "question_class": "witness-person-role"}, {"doc_id": "1dc4d8b2-c916-11e9-a719-b831b5755f6c", "person": "Edmund-S.-Muskie", "question_class": "actor-affiliation-type"}, {"doc_id": "1dc4d8b2-c916-11e9-a719-b831b5755f6c", "person": "Edmund-S.-Muskie", "question_class": "actor-individual-person-role"}, {"doc_id": "1dc4d8b2-c916-11e9-a719-b831b5755f6c", "person": "Edmund-S.-Muskie", "question_class": "actor-group-person-role"}, {"doc_id": "1dc4d8b2-c916-11e9-a719-b831b5755f6c", "person": "Edmund-S.-Muskie", "question_class": "corporate-person-role"}, {"doc_id": "1dc4d8b2-c916-11e9-a719-b831b5755f6c", "person": "Edmund-S.-Muskie", "question_class": "lawyer-role"}, {"doc_id": "1dc4d8b2-c916-11e9-a719-b831b5755f6c", "person": "Edmund-S.-Muskie", "question_class": "ngo-person-role"}, {"doc_id": "1dc4d8b2-c916-11e9-a719-b831b5755f6c", "person": "Edmund-S.-Muskie", "question_class": "stance", "label": "opposing"}, {"doc_id": "4dd16f1c-c916-11e9-ac65-b831b5755f6c", "person": "Lance-A.-Ito", "question_class": "error", "label": "legit"}, {"doc_id": "4dd16f1c-c916-11e9-ac65-b831b5755f6c", "person": "Lance-A.-Ito", "question_class": "affiliation", "label": "government"}, {"doc_id": "4dd16f1c-c916-11e9-ac65-b831b5755f6c", "person": "Lance-A.-Ito", "question_class": "gov-branch", "label": "judicial"}, {"doc_id": "4dd16f1c-c916-11e9-ac65-b831b5755f6c", "person": "Lance-A.-Ito", "question_class": "gov-person-role", "label": "decision-maker"}, {"doc_id": "4dd16f1c-c916-11e9-ac65-b831b5755f6c", "person": "Lance-A.-Ito", "question_class": "victim-person-role"}, {"doc_id": "4dd16f1c-c916-11e9-ac65-b831b5755f6c", "person": "Lance-A.-Ito", "question_class": "academic-person-role"}, {"doc_id": "4dd16f1c-c916-11e9-ac65-b831b5755f6c", "person": "Lance-A.-Ito", "question_class": "witness-person-role"}, {"doc_id": "4dd16f1c-c916-11e9-ac65-b831b5755f6c", "person": "Lance-A.-Ito", "question_class": "actor-affiliation-type"}, {"doc_id": "4dd16f1c-c916-11e9-ac65-b831b5755f6c", "person": "Lance-A.-Ito", "question_class": "actor-individual-person-role"}, {"doc_id": "4dd16f1c-c916-11e9-ac65-b831b5755f6c", "person": "Lance-A.-Ito", "question_class": "actor-group-person-role"}, {"doc_id": "4dd16f1c-c916-11e9-ac65-b831b5755f6c", "person": "Lance-A.-Ito", "question_class": "corporate-person-role"}, {"doc_id": "4dd16f1c-c916-11e9-ac65-b831b5755f6c", "person": "Lance-A.-Ito", "question_class": "lawyer-role"}, {"doc_id": "4dd16f1c-c916-11e9-ac65-b831b5755f6c", "person": "Lance-A.-Ito", "question_class": "ngo-person-role"}, {"doc_id": "4dd16f1c-c916-11e9-ac65-b831b5755f6c", "person": "Lance-A.-Ito", "question_class": "stance", "label": "informational"}, {"doc_id": "4dd16f1c-c916-11e9-ac65-b831b5755f6c", "person": "Mark-Fuhrman", "question_class": "error", "label": "badentity"}, {"doc_id": "4dd16f1c-c916-11e9-ac65-b831b5755f6c", "person": "Mark-Fuhrman", "question_class": "affiliation"}, {"doc_id": "4dd16f1c-c916-11e9-ac65-b831b5755f6c", "person": "Mark-Fuhrman", "question_class": "gov-branch"}, {"doc_id": "4dd16f1c-c916-11e9-ac65-b831b5755f6c", "person": "Mark-Fuhrman", "question_class": "gov-person-role"}, {"doc_id": "4dd16f1c-c916-11e9-ac65-b831b5755f6c", "person": "Mark-Fuhrman", "question_class": "victim-person-role", "label": "individual"}, {"doc_id": "4dd16f1c-c916-11e9-ac65-b831b5755f6c", "person": "Mark-Fuhrman", "question_class": "academic-person-role", "label": "decision-maker"}, {"doc_id": "4dd16f1c-c916-11e9-ac65-b831b5755f6c", "person": "Mark-Fuhrman", "question_class": "witness-person-role", "label": "casual"}, {"doc_id": "4dd16f1c-c916-11e9-ac65-b831b5755f6c", "person": "Mark-Fuhrman", "question_class": "actor-affiliation-type", "label": "individual"}, {"doc_id": "4dd16f1c-c916-11e9-ac65-b831b5755f6c", "person": "Mark-Fuhrman", "question_class": "actor-individual-person-role", "label": "individual"}, {"doc_id": "4dd16f1c-c916-11e9-ac65-b831b5755f6c", "person": "Mark-Fuhrman", "question_class": "actor-group-person-role", "label": "leader"}, {"doc_id": "4dd16f1c-c916-11e9-ac65-b831b5755f6c", "person": "Mark-Fuhrman", "question_class": "corporate-person-role"}, {"doc_id": "4dd16f1c-c916-11e9-ac65-b831b5755f6c", "person": "Mark-Fuhrman", "question_class": "lawyer-role"}, {"doc_id": "4dd16f1c-c916-11e9-ac65-b831b5755f6c", "person": "Mark-Fuhrman", "question_class": "ngo-person-role"}, {"doc_id": "4dd16f1c-c916-11e9-ac65-b831b5755f6c", "person": "Mark-Fuhrman", "question_class": "stance"}, {"doc_id": "4dd16f1c-c916-11e9-ac65-b831b5755f6c", "person": "Marcia-Clark", "question_class": "error", "label": "legit"}, {"doc_id": "4dd16f1c-c916-11e9-ac65-b831b5755f6c", "person": "Marcia-Clark", "question_class": "affiliation", "label": "government"}, {"doc_id": "4dd16f1c-c916-11e9-ac65-b831b5755f6c", "person": "Marcia-Clark", "question_class": "gov-branch", "label": "executive"}, {"doc_id": "4dd16f1c-c916-11e9-ac65-b831b5755f6c", "person": "Marcia-Clark", "question_class": "gov-person-role", "label": "lawyer"}, {"doc_id": "4dd16f1c-c916-11e9-ac65-b831b5755f6c", "person": "Marcia-Clark", "question_class": "victim-person-role"}, {"doc_id": "4dd16f1c-c916-11e9-ac65-b831b5755f6c", "person": "Marcia-Clark", "question_class": "academic-person-role"}, {"doc_id": "4dd16f1c-c916-11e9-ac65-b831b5755f6c", "person": "Marcia-Clark", "question_class": "witness-person-role"}, {"doc_id": "4dd16f1c-c916-11e9-ac65-b831b5755f6c", "person": "Marcia-Clark", "question_class": "actor-affiliation-type"}, {"doc_id": "4dd16f1c-c916-11e9-ac65-b831b5755f6c", "person": "Marcia-Clark", "question_class": "actor-individual-person-role"}, {"doc_id": "4dd16f1c-c916-11e9-ac65-b831b5755f6c", "person": "Marcia-Clark", "question_class": "actor-group-person-role"}, {"doc_id": "4dd16f1c-c916-11e9-ac65-b831b5755f6c", "person": "Marcia-Clark", "question_class": "corporate-person-role"}, {"doc_id": "4dd16f1c-c916-11e9-ac65-b831b5755f6c", "person": "Marcia-Clark", "question_class": "lawyer-role", "label": "prosecutor"}, {"doc_id": "4dd16f1c-c916-11e9-ac65-b831b5755f6c", "person": "Marcia-Clark", "question_class": "ngo-person-role"}, {"doc_id": "4dd16f1c-c916-11e9-ac65-b831b5755f6c", "person": "Marcia-Clark", "question_class": "stance"}, {"doc_id": "4dd16f1c-c916-11e9-ac65-b831b5755f6c", "person": "Johnnie-L.-Cochran-Jr.", "question_class": "error", "label": "legit"}, {"doc_id": "4dd16f1c-c916-11e9-ac65-b831b5755f6c", "person": "Johnnie-L.-Cochran-Jr.", "question_class": "affiliation", "label": "actor"}, {"doc_id": "4dd16f1c-c916-11e9-ac65-b831b5755f6c", "person": "Johnnie-L.-Cochran-Jr.", "question_class": "gov-branch"}, {"doc_id": "4dd16f1c-c916-11e9-ac65-b831b5755f6c", "person": "Johnnie-L.-Cochran-Jr.", "question_class": "gov-person-role"}, {"doc_id": "4dd16f1c-c916-11e9-ac65-b831b5755f6c", "person": "Johnnie-L.-Cochran-Jr.", "question_class": "victim-person-role"}, {"doc_id": "4dd16f1c-c916-11e9-ac65-b831b5755f6c", "person": "Johnnie-L.-Cochran-Jr.", "question_class": "academic-person-role"}, {"doc_id": "4dd16f1c-c916-11e9-ac65-b831b5755f6c", "person": "Johnnie-L.-Cochran-Jr.", "question_class": "witness-person-role"}, {"doc_id": "4dd16f1c-c916-11e9-ac65-b831b5755f6c", "person": "Johnnie-L.-Cochran-Jr.", "question_class": "actor-affiliation-type", "label": "individual"}, {"doc_id": "4dd16f1c-c916-11e9-ac65-b831b5755f6c", "person": "Johnnie-L.-Cochran-Jr.", "question_class": "actor-individual-person-role", "label": "lawyer"}, {"doc_id": "4dd16f1c-c916-11e9-ac65-b831b5755f6c", "person": "Johnnie-L.-Cochran-Jr.", "question_class": "actor-group-person-role"}, {"doc_id": "4dd16f1c-c916-11e9-ac65-b831b5755f6c", "person": "Johnnie-L.-Cochran-Jr.", "question_class": "corporate-person-role"}, {"doc_id": "4dd16f1c-c916-11e9-ac65-b831b5755f6c", "person": "Johnnie-L.-Cochran-Jr.", "question_class": "lawyer-role", "label": "defense"}, {"doc_id": "4dd16f1c-c916-11e9-ac65-b831b5755f6c", "person": "Johnnie-L.-Cochran-Jr.", "question_class": "ngo-person-role"}, {"doc_id": "4dd16f1c-c916-11e9-ac65-b831b5755f6c", "person": "Johnnie-L.-Cochran-Jr.", "question_class": "stance"}, {"doc_id": "4dd16f1c-c916-11e9-ac65-b831b5755f6c", "person": "Peter-Arenella", "question_class": "error", "label": "legit"}, {"doc_id": "4dd16f1c-c916-11e9-ac65-b831b5755f6c", "person": "Peter-Arenella", "question_class": "affiliation", "label": "academic"}, {"doc_id": "4dd16f1c-c916-11e9-ac65-b831b5755f6c", "person": "Peter-Arenella", "question_class": "gov-branch"}, {"doc_id": "4dd16f1c-c916-11e9-ac65-b831b5755f6c", "person": "Peter-Arenella", "question_class": "gov-person-role"}, {"doc_id": "4dd16f1c-c916-11e9-ac65-b831b5755f6c", "person": "Peter-Arenella", "question_class": "victim-person-role"}, {"doc_id": "4dd16f1c-c916-11e9-ac65-b831b5755f6c", "person": "Peter-Arenella", "question_class": "academic-person-role", "label": "other"}, {"doc_id": "4dd16f1c-c916-11e9-ac65-b831b5755f6c", "person": "Peter-Arenella", "question_class": "witness-person-role"}, {"doc_id": "4dd16f1c-c916-11e9-ac65-b831b5755f6c", "person": "Peter-Arenella", "question_class": "actor-affiliation-type"}, {"doc_id": "4dd16f1c-c916-11e9-ac65-b831b5755f6c", "person": "Peter-Arenella", "question_class": "actor-individual-person-role"}, {"doc_id": "4dd16f1c-c916-11e9-ac65-b831b5755f6c", "person": "Peter-Arenella", "question_class": "actor-group-person-role"}, {"doc_id": "4dd16f1c-c916-11e9-ac65-b831b5755f6c", "person": "Peter-Arenella", "question_class": "corporate-person-role"}, {"doc_id": "4dd16f1c-c916-11e9-ac65-b831b5755f6c", "person": "Peter-Arenella", "question_class": "lawyer-role"}, {"doc_id": "4dd16f1c-c916-11e9-ac65-b831b5755f6c", "person": "Peter-Arenella", "question_class": "ngo-person-role"}, {"doc_id": "4dd16f1c-c916-11e9-ac65-b831b5755f6c", "person": "Peter-Arenella", "question_class": "stance", "label": "informational"}, {"doc_id": "4dd16f1c-c916-11e9-ac65-b831b5755f6c", "person": "F.-Lee-Bailey", "question_class": "error", "label": "legit"}, {"doc_id": "4dd16f1c-c916-11e9-ac65-b831b5755f6c", "person": "F.-Lee-Bailey", "question_class": "affiliation", "label": "actor"}, {"doc_id": "4dd16f1c-c916-11e9-ac65-b831b5755f6c", "person": "F.-Lee-Bailey", "question_class": "gov-branch"}, {"doc_id": "4dd16f1c-c916-11e9-ac65-b831b5755f6c", "person": "F.-Lee-Bailey", "question_class": "gov-person-role"}, {"doc_id": "4dd16f1c-c916-11e9-ac65-b831b5755f6c", "person": "F.-Lee-Bailey", "question_class": "victim-person-role"}, {"doc_id": "4dd16f1c-c916-11e9-ac65-b831b5755f6c", "person": "F.-Lee-Bailey", "question_class": "academic-person-role"}, {"doc_id": "4dd16f1c-c916-11e9-ac65-b831b5755f6c", "person": "F.-Lee-Bailey", "question_class": "witness-person-role"}, {"doc_id": "4dd16f1c-c916-11e9-ac65-b831b5755f6c", "person": "F.-Lee-Bailey", "question_class": "actor-affiliation-type", "label": "individual"}, {"doc_id": "4dd16f1c-c916-11e9-ac65-b831b5755f6c", "person": "F.-Lee-Bailey", "question_class": "actor-individual-person-role", "label": "lawyer"}, {"doc_id": "4dd16f1c-c916-11e9-ac65-b831b5755f6c", "person": "F.-Lee-Bailey", "question_class": "actor-group-person-role"}, {"doc_id": "4dd16f1c-c916-11e9-ac65-b831b5755f6c", "person": "F.-Lee-Bailey", "question_class": "corporate-person-role"}, {"doc_id": "4dd16f1c-c916-11e9-ac65-b831b5755f6c", "person": "F.-Lee-Bailey", "question_class": "lawyer-role", "label": "defense"}, {"doc_id": "4dd16f1c-c916-11e9-ac65-b831b5755f6c", "person": "F.-Lee-Bailey", "question_class": "ngo-person-role"}, {"doc_id": "4dd16f1c-c916-11e9-ac65-b831b5755f6c", "person": "F.-Lee-Bailey", "question_class": "stance"}, {"doc_id": "4dd16f1c-c916-11e9-ac65-b831b5755f6c", "person": "Darden", "question_class": "error", "label": "legit"}, {"doc_id": "4dd16f1c-c916-11e9-ac65-b831b5755f6c", "person": "Darden", "question_class": "affiliation", "label": "government"}, {"doc_id": "4dd16f1c-c916-11e9-ac65-b831b5755f6c", "person": "Darden", "question_class": "gov-branch", "label": "executive"}, {"doc_id": "4dd16f1c-c916-11e9-ac65-b831b5755f6c", "person": "Darden", "question_class": "gov-person-role", "label": "lawyer"}, {"doc_id": "4dd16f1c-c916-11e9-ac65-b831b5755f6c", "person": "Darden", "question_class": "victim-person-role"}, {"doc_id": "4dd16f1c-c916-11e9-ac65-b831b5755f6c", "person": "Darden", "question_class": "academic-person-role"}, {"doc_id": "4dd16f1c-c916-11e9-ac65-b831b5755f6c", "person": "Darden", "question_class": "witness-person-role"}, {"doc_id": "4dd16f1c-c916-11e9-ac65-b831b5755f6c", "person": "Darden", "question_class": "actor-affiliation-type"}, {"doc_id": "4dd16f1c-c916-11e9-ac65-b831b5755f6c", "person": "Darden", "question_class": "actor-individual-person-role"}, {"doc_id": "4dd16f1c-c916-11e9-ac65-b831b5755f6c", "person": "Darden", "question_class": "actor-group-person-role"}, {"doc_id": "4dd16f1c-c916-11e9-ac65-b831b5755f6c", "person": "Darden", "question_class": "corporate-person-role"}, {"doc_id": "4dd16f1c-c916-11e9-ac65-b831b5755f6c", "person": "Darden", "question_class": "lawyer-role", "label": "prosecutor"}, {"doc_id": "4dd16f1c-c916-11e9-ac65-b831b5755f6c", "person": "Darden", "question_class": "ngo-person-role"}, {"doc_id": "4dd16f1c-c916-11e9-ac65-b831b5755f6c", "person": "Darden", "question_class": "stance"}, {"doc_id": "4dd16f1c-c916-11e9-ac65-b831b5755f6c", "person": "James-Bascue", "question_class": "error", "label": "legit"}, {"doc_id": "4dd16f1c-c916-11e9-ac65-b831b5755f6c", "person": "James-Bascue", "question_class": "affiliation", "label": "government"}, {"doc_id": "4dd16f1c-c916-11e9-ac65-b831b5755f6c", "person": "James-Bascue", "question_class": "gov-branch", "label": "judicial"}, {"doc_id": "4dd16f1c-c916-11e9-ac65-b831b5755f6c", "person": "James-Bascue", "question_class": "gov-person-role", "label": "decision-maker"}, {"doc_id": "4dd16f1c-c916-11e9-ac65-b831b5755f6c", "person": "James-Bascue", "question_class": "victim-person-role"}, {"doc_id": "4dd16f1c-c916-11e9-ac65-b831b5755f6c", "person": "James-Bascue", "question_class": "academic-person-role"}, {"doc_id": "4dd16f1c-c916-11e9-ac65-b831b5755f6c", "person": "James-Bascue", "question_class": "witness-person-role"}, {"doc_id": "4dd16f1c-c916-11e9-ac65-b831b5755f6c", "person": "James-Bascue", "question_class": "actor-affiliation-type"}, {"doc_id": "4dd16f1c-c916-11e9-ac65-b831b5755f6c", "person": "James-Bascue", "question_class": "actor-individual-person-role"}, {"doc_id": "4dd16f1c-c916-11e9-ac65-b831b5755f6c", "person": "James-Bascue", "question_class": "actor-group-person-role"}, {"doc_id": "4dd16f1c-c916-11e9-ac65-b831b5755f6c", "person": "James-Bascue", "question_class": "corporate-person-role"}, {"doc_id": "4dd16f1c-c916-11e9-ac65-b831b5755f6c", "person": "James-Bascue", "question_class": "lawyer-role"}, {"doc_id": "4dd16f1c-c916-11e9-ac65-b831b5755f6c", "person": "James-Bascue", "question_class": "ngo-person-role"}, {"doc_id": "4dd16f1c-c916-11e9-ac65-b831b5755f6c", "person": "James-Bascue", "question_class": "stance", "label": "supporting"}, {"doc_id": "428941ca-c916-11e9-b4a5-b831b5755f6c", "person": "Ram-K.-Chopra", "question_class": "error", "label": "legit"}, {"doc_id": "428941ca-c916-11e9-b4a5-b831b5755f6c", "person": "Ram-K.-Chopra", "question_class": "affiliation", "label": "ngo"}, {"doc_id": "428941ca-c916-11e9-b4a5-b831b5755f6c", "person": "Ram-K.-Chopra", "question_class": "gov-branch"}, {"doc_id": "428941ca-c916-11e9-b4a5-b831b5755f6c", "person": "Ram-K.-Chopra", "question_class": "gov-person-role"}, {"doc_id": "428941ca-c916-11e9-b4a5-b831b5755f6c", "person": "Ram-K.-Chopra", "question_class": "victim-person-role"}, {"doc_id": "428941ca-c916-11e9-b4a5-b831b5755f6c", "person": "Ram-K.-Chopra", "question_class": "academic-person-role"}, {"doc_id": "428941ca-c916-11e9-b4a5-b831b5755f6c", "person": "Ram-K.-Chopra", "question_class": "witness-person-role"}, {"doc_id": "428941ca-c916-11e9-b4a5-b831b5755f6c", "person": "Ram-K.-Chopra", "question_class": "actor-affiliation-type"}, {"doc_id": "428941ca-c916-11e9-b4a5-b831b5755f6c", "person": "Ram-K.-Chopra", "question_class": "actor-individual-person-role"}, {"doc_id": "428941ca-c916-11e9-b4a5-b831b5755f6c", "person": "Ram-K.-Chopra", "question_class": "actor-group-person-role"}, {"doc_id": "428941ca-c916-11e9-b4a5-b831b5755f6c", "person": "Ram-K.-Chopra", "question_class": "corporate-person-role"}, {"doc_id": "428941ca-c916-11e9-b4a5-b831b5755f6c", "person": "Ram-K.-Chopra", "question_class": "lawyer-role"}, {"doc_id": "428941ca-c916-11e9-b4a5-b831b5755f6c", "person": "Ram-K.-Chopra", "question_class": "ngo-person-role", "label": "actor"}, {"doc_id": "428941ca-c916-11e9-b4a5-b831b5755f6c", "person": "Ram-K.-Chopra", "question_class": "stance", "label": "supporting"}, {"doc_id": "428941ca-c916-11e9-b4a5-b831b5755f6c", "person": "Yousef-Sayigh", "question_class": "error", "label": "legit"}, {"doc_id": "428941ca-c916-11e9-b4a5-b831b5755f6c", "person": "Yousef-Sayigh", "question_class": "affiliation", "label": "government"}, {"doc_id": "428941ca-c916-11e9-b4a5-b831b5755f6c", "person": "Yousef-Sayigh", "question_class": "gov-branch", "label": "executive"}, {"doc_id": "428941ca-c916-11e9-b4a5-b831b5755f6c", "person": "Yousef-Sayigh", "question_class": "gov-person-role", "label": "advisor"}, {"doc_id": "428941ca-c916-11e9-b4a5-b831b5755f6c", "person": "Yousef-Sayigh", "question_class": "victim-person-role"}, {"doc_id": "428941ca-c916-11e9-b4a5-b831b5755f6c", "person": "Yousef-Sayigh", "question_class": "academic-person-role"}, {"doc_id": "428941ca-c916-11e9-b4a5-b831b5755f6c", "person": "Yousef-Sayigh", "question_class": "witness-person-role"}, {"doc_id": "428941ca-c916-11e9-b4a5-b831b5755f6c", "person": "Yousef-Sayigh", "question_class": "actor-affiliation-type"}, {"doc_id": "428941ca-c916-11e9-b4a5-b831b5755f6c", "person": "Yousef-Sayigh", "question_class": "actor-individual-person-role"}, {"doc_id": "428941ca-c916-11e9-b4a5-b831b5755f6c", "person": "Yousef-Sayigh", "question_class": "actor-group-person-role"}, {"doc_id": "428941ca-c916-11e9-b4a5-b831b5755f6c", "person": "Yousef-Sayigh", "question_class": "corporate-person-role"}, {"doc_id": "428941ca-c916-11e9-b4a5-b831b5755f6c", "person": "Yousef-Sayigh", "question_class": "lawyer-role"}, {"doc_id": "428941ca-c916-11e9-b4a5-b831b5755f6c", "person": "Yousef-Sayigh", "question_class": "ngo-person-role"}, {"doc_id": "428941ca-c916-11e9-b4a5-b831b5755f6c", "person": "Yousef-Sayigh", "question_class": "stance", "label": "supporting"}, {"doc_id": "428941ca-c916-11e9-b4a5-b831b5755f6c", "person": "Avraham-Shochat", "question_class": "error", "label": "legit"}, {"doc_id": "428941ca-c916-11e9-b4a5-b831b5755f6c", "person": "Avraham-Shochat", "question_class": "affiliation", "label": "government"}, {"doc_id": "428941ca-c916-11e9-b4a5-b831b5755f6c", "person": "Avraham-Shochat", "question_class": "gov-branch", "label": "executive"}, {"doc_id": "428941ca-c916-11e9-b4a5-b831b5755f6c", "person": "Avraham-Shochat", "question_class": "gov-person-role", "label": "advisor"}, {"doc_id": "428941ca-c916-11e9-b4a5-b831b5755f6c", "person": "Avraham-Shochat", "question_class": "victim-person-role"}, {"doc_id": "428941ca-c916-11e9-b4a5-b831b5755f6c", "person": "Avraham-Shochat", "question_class": "academic-person-role"}, {"doc_id": "428941ca-c916-11e9-b4a5-b831b5755f6c", "person": "Avraham-Shochat", "question_class": "witness-person-role"}, {"doc_id": "428941ca-c916-11e9-b4a5-b831b5755f6c", "person": "Avraham-Shochat", "question_class": "actor-affiliation-type"}, {"doc_id": "428941ca-c916-11e9-b4a5-b831b5755f6c", "person": "Avraham-Shochat", "question_class": "actor-individual-person-role"}, {"doc_id": "428941ca-c916-11e9-b4a5-b831b5755f6c", "person": "Avraham-Shochat", "question_class": "actor-group-person-role"}, {"doc_id": "428941ca-c916-11e9-b4a5-b831b5755f6c", "person": "Avraham-Shochat", "question_class": "corporate-person-role"}, {"doc_id": "428941ca-c916-11e9-b4a5-b831b5755f6c", "person": "Avraham-Shochat", "question_class": "lawyer-role"}, {"doc_id": "428941ca-c916-11e9-b4a5-b831b5755f6c", "person": "Avraham-Shochat", "question_class": "ngo-person-role"}, {"doc_id": "428941ca-c916-11e9-b4a5-b831b5755f6c", "person": "Avraham-Shochat", "question_class": "stance", "label": "supporting"}]